Workbook

Sheet Summary
A1: Infrasoft Technologies Limited (Kiya.ai) – Consolidated
A2: Going Concern Assessment – Summary (FY 2025-26)
A3: Going concern assessment for the year ended 31 March 2026 | All amounts in INR Lakhs unless stated
A5: INR Lakhs | B5: FY 2025-26 (A) | C5: FY 2026-27 (B) | D5: Apr-Sep 27 (P) | E5: Growth / change
A6: Gross revenue | B6: ='Global PNL'!C11 -> 37981 | C6: ='Global PNL'!Q11 -> 44500 | D6: ='Global PNL'!AB11 -> 24475 | E6: =IF(B6=0,0,(C6-B6)/ABS(B6)) -> 0.17163845
A7: Channel partner cost | B7: ='Global PNL'!C12 -> 0 | C7: ='Global PNL'!Q12 -> 1300 | D7: ='Global PNL'!AB12 -> 715 | E7: =IF(B7=0,0,(C7-B7)/ABS(B7)) -> 0
A8: Net revenue | B8: ='Global PNL'!C13 -> 37981 | C8: ='Global PNL'!Q13 -> 43200 | D8: ='Global PNL'!AB13 -> 23760 | E8: =IF(B8=0,0,(C8-B8)/ABS(B8)) -> 0.13741081
A9: Operating cost (CoR + G&A + S&M) | B9: ='Global PNL'!C44 -> 36952.7 | C9: ='Global PNL'!Q44 -> 36525 | D9: ='Global PNL'!AB44 -> 20088.75 | E9: =IF(B9=0,0,(C9-B9)/ABS(B9)) -> -0.011574256
A10: EBITDA before ECL / write-offs | B10: ='Global PNL'!C45 -> 1028.3 | C10: ='Global PNL'!Q45 -> 6675 | D10: ='Global PNL'!AB45 -> 3671.25 | E10: =IF(B10=0,0,(C10-B10)/ABS(B10)) -> 5.4912963
A11: ECL provision & write-offs | B11: ='Global PNL'!C47 -> 3647.3 | C11: ='Global PNL'!Q47 -> 1335 | D11: ='Global PNL'!AB47 -> 734.25 | E11: =IF(B11=0,0,(C11-B11)/ABS(B11)) -> -0.63397582
A12: EBITDA after ECL / write-offs | B12: ='Global PNL'!C48 -> -2619 | C12: ='Global PNL'!Q48 -> 5340 | D12: ='Global PNL'!AB48 -> 2937 | E12: =IF(B12=0,0,(C12-B12)/ABS(B12)) -> 3.0389462
A13: EBITDA % of gross revenue | B13: =IF(B6=0,0,B12/B6) -> -0.06895553 | C13: =IF(C6=0,0,C12/C6) -> 0.12 | D13: =IF(D6=0,0,D12/D6) -> 0.12
A14: Profit / (Loss) before tax | B14: ='Global PNL'!C57 -> -4327.6 | C14: ='Global PNL'!Q57 -> 3895.6 | D14: ='Global PNL'!AB57 -> 2142.58 | E14: =IF(B14=0,0,(C14-B14)/ABS(B14)) -> 1.9001756
A15: Profit / (Loss) after tax | B15: ='Global PNL'!C59 -> -3351.6 | C15: ='Global PNL'!Q59 -> 2915.0775 | D15: ='Global PNL'!AB59 -> 1603.2926 | E15: =IF(B15=0,0,(C15-B15)/ABS(B15)) -> 1.869757
A17: Liquidity
A18: Cash & cash equivalents – 31 March 2026 (audited) | B18: =Assumptions!$B$39 -> 4324.9
A19: Projected cash – 31 March 2027 | B19: ='Global Cashflow'!O28 -> 6880.1949
A20: Projected cash – 30 September 2027 | B20: ='Global Cashflow'!V28 -> 6525.5293
A21: Minimum month-end cash over Apr-26 to Sep-27 | B21: ='Global Cashflow'!C31 -> 1749.2862
A22: Months with negative closing cash | B22: ='Global Cashflow'!C33 -> 0
A23: Borrowings at 31 March 2026 | B23: ='FY26 Actual'!D56 -> 0
A24: Closing cash 31-Mar-27 – combined stress (revenue –5%, cost +2%) | B24: =Sensitivity!E26 -> 4767.1828
A25: Revenue decline that brings FY27 EBITDA to nil | B25: =Sensitivity!B30 -> 0.12755285
A27: Going-concern indicator checks
A28: FY27 EBITDA equals 12% of gross revenue | B28: =IF(ABS('Global PNL'!Q50)<0.01,"Yes","No") -> Yes
A29: Positive net worth at 31-Mar-26 | B29: =IF('FY26 Actual'!D57>0,"Yes","No") -> Yes
A30: Cash stays positive in every month to Sep-27 (base case) | B30: =IF(B22=0,"Yes","No") -> Yes
A31: Cash stays positive at 31-Mar-27 under combined stress | B31: =IF(B24>0,"Yes","No") -> Yes
A32: No external borrowings at 31-Mar-26 | B32: =IF(B23=0,"Yes","No") -> Yes
A34: Management assessment (draft)
A35: • The Group reported a loss before tax of INR 4,327.8 lakhs for FY 2025-26. The main driver was a one-time clean-up of receivables: ECL, bad-debt and unbilled revenue write-offs of about INR 3,647 lakhs. Before these write-offs, EBITDA was positive.
A36: • The Group has positive net worth, no external borrowings at 31 March 2026, and cash & cash equivalents of INR 4,324.9 lakhs. It also holds a further INR 1,470 lakhs in other bank balances and current investments.
A37: • FY 2026-27 budget: gross revenue INR 44,500 lakhs and net revenue INR 43,200 lakhs (after INR 1,300 lakhs channel partner cost). Operating costs are rationalised to deliver EBITDA of 12% of gross revenue.
A38: • Apr-Sep 2027 is projected at a 10% annualised increase on FY 2026-27. Month-end cash balances stay positive in every month through September 2027, i.e. 12 months from the date of approval of the financial statements. The lowest point is about INR 1,750 lakhs in Aug-26, because revenue is back-ended while costs are spread evenly.
A39: • Under the combined stress (revenue –5%, cost +2%), closing cash at 31 March 2027 remains positive. Based on the above, the going concern assumption is considered appropriate and no material uncertainty is expected.

Sheet Valuation
A1: Infrasoft Technologies Limited (Kiya.ai) – Consolidated
A2: Business Valuation – DCF (FCFF) with Market Cross-checks
A3: Valuation date 31 March 2026 (audited balance sheet) | INR Lakhs unless stated | Blue on yellow = input; green = link to another sheet; black = formula
A5: A. Valuation assumptions | B5: Value | C5: Unit | D5: Basis / Source
A6: Risk-free rate | B6: 0.068 | C6: % | D6: Assumption – approx. yield on 10-yr Government of India bond (update to valuation-date yield)
A7: Equity risk premium (India) | B7: 0.07 | C7: % | D7: Assumption – long-run India ERP range 6.5%–7.5%
A8: Equity beta (levered) | B8: 1.1 | C8: x | D8: Assumption – listed Indian IT/software product & services peers ~0.9–1.3; company is debt-free so levered ≈ unlevered
A9: Size / company-specific risk premium | B9: 0.03 | C9: % | D9: Assumption – small cap, FY26 loss & receivable write-offs, concentration of receivables, execution risk on FY27 budget
A10: Cost of equity (CAPM + premium) | B10: =B6+B8*B7+B9 -> 0.175 | C10: % | D10: Formula: Rf + β × ERP + specific premium
A11: Pre-tax cost of debt | B11: 0.1 | C11: % | D11: Assumption – indicative INR working-capital borrowing rate (only used if target debt > 0)
A12: Tax rate | B12: =Assumptions!B30 -> 0.2517 | C12: % | D12: Link: Sec 115BAA effective rate
A13: Target debt / (debt + equity) | B13: 0 | C13: % | D13: Assumption – no borrowings at 31-Mar-26 (Note 18); lease liabilities treated as operating (lease payments deducted in FCFF)
A14: WACC | B14: =B10*(1-B13)+B11*(1-B12)*B13 -> 0.175 | C14: % | D14: Formula: Ke × E/V + Kd × (1–t) × D/V
A15: Terminal growth rate (g) | B15: 0.05 | C15: % | D15: Assumption – below long-run nominal GDP growth of India; capped at ~5%
A16: Mid-year discounting (1 = yes, 0 = year-end) | B16: 1 | C16: switch | D16: Assumption – cash flows arise evenly through the year
A17: Net working capital % of net revenue | B17: =('Working Capital'!F12+'Working Capital'!F13-'Working Capital'!F14-'Working Capital'!F15)/'Working Capital'!E8 -> 0.517782 | C17: % | D17: Link: 31-Mar-27 budget NWC (receivables + unbilled – unearned – payables) ÷ FY27 net revenue; used for incremental NWC FY28+
A18: EBITDA (after ECL) % of net revenue | B18: =Summary!C12/Summary!C8 -> 0.12361111 | C18: % | D18: Link: FY27 budget – 12% of gross revenue = 12.36% of net revenue; held flat (no further margin expansion)
A19: D&A % of net revenue | B19: =Assumptions!B28/Summary!C8 -> 0.03349537 | C19: % | D19: Link: FY27 D&A held at FY26 level, kept at same % of revenue
A20: Capex % of net revenue | B20: =Assumptions!B33/Summary!C8 -> 0.0069444444 | C20: % | D20: Link: FY27 capex INR 300 lakhs
A21: Lease payments % of net revenue | B21: =Assumptions!B34/Summary!C8 -> 0.023226852 | C21: % | D21: Link: FY27 lease payments (principal + interest) – Ind AS 116 cash cost deducted from FCFF
A22: Terminal FCFF margin before NWC (k) | B22: =B18-B12*MAX(0,B18-(B20+B21))-B20-B21 -> 0.069921013 | C22: % | D22: Formula: terminal D&A set = capex + lease payments (steady state); used in terminal value and sensitivity grid
A23: Shares outstanding (lakhs) | C23: lakhs | D23: INPUT REQUIRED – share count not in the workbook; per-share value computes once entered
A25: B. Free cash flow to firm (FCFF) projection | B25: FY26 (A) | C25: FY27 (B) | D25: FY28 (P) | E25: FY29 (P) | F25: FY30 (P) | G25: FY31 (P) | H25: Terminal
A26: Net revenue growth % | C26: =C27/B27-1 -> 0.13741081 | D26: =Assumptions!B42 -> 0.1 | E26: 0.09 | F26: 0.08 | G26: 0.07 | H26: =B15 -> 0.05
A27: Net revenue | B27: =Summary!B8 -> 37981 | C27: =Summary!C8 -> 43200 | D27: =C27*(1+D26) -> 47520 | E27: =D27*(1+E26) -> 51796.8 | F27: =E27*(1+F26) -> 55940.544 | G27: =F27*(1+G26) -> 59856.382 | H27: =G27*(1+H26) -> 62849.201
A28: EBITDA margin % (after ECL / write-offs) | B28: =B29/B27 -> -0.06895553 | C28: =$B$18 -> 0.12361111 | D28: =$B$18 -> 0.12361111 | E28: =$B$18 -> 0.12361111 | F28: =$B$18 -> 0.12361111 | G28: =$B$18 -> 0.12361111 | H28: =$B$18 -> 0.12361111
A29: EBITDA (after ECL / write-offs) | B29: =Summary!B12 -> -2619 | C29: =C27*C28 -> 5340 | D29: =D27*D28 -> 5874 | E29: =E27*E28 -> 6402.66 | F29: =F27*F28 -> 6914.8728 | G29: =G27*G28 -> 7398.9139 | H29: =H27*H28 -> 7768.8596
A30: Less: D&A | C30: =-C27*$B$19 -> -1447 | D30: =-D27*$B$19 -> -1591.7 | E30: =-E27*$B$19 -> -1734.953 | F30: =-F27*$B$19 -> -1873.7492 | G30: =-G27*$B$19 -> -2004.9117 | H30: =-H27*($B$20+$B$21) -> -1896.2419
A31: EBIT (lease cost excluded – deducted below) | C31: =C29+C30 -> 3893 | D31: =D29+D30 -> 4282.3 | E31: =E29+E30 -> 4667.707 | F31: =F29+F30 -> 5041.1236 | G31: =G29+G30 -> 5394.0022 | H31: =H29+H30 -> 5872.6177
A32: Less: Tax on EBIT | C32: =-MAX(0,C31)*$B$12 -> -979.8681 | D32: =-MAX(0,D31)*$B$12 -> -1077.8549 | E32: =-MAX(0,E31)*$B$12 -> -1174.8619 | F32: =-MAX(0,F31)*$B$12 -> -1268.8508 | G32: =-MAX(0,G31)*$B$12 -> -1357.6704 | H32: =-MAX(0,H31)*$B$12 -> -1478.1379
A33: Less: Capital expenditure | C33: =-C27*$B$20 -> -300 | D33: =-D27*$B$20 -> -330 | E33: =-E27*$B$20 -> -359.7 | F33: =-F27*$B$20 -> -388.476 | G33: =-G27*$B$20 -> -415.66932 | H33: =-H27*$B$20 -> -436.45279
A34: Less: Lease payments (principal + interest) | C34: =-C27*$B$21 -> -1003.4 | D34: =-D27*$B$21 -> -1103.74 | E34: =-E27*$B$21 -> -1203.0766 | F34: =-F27*$B$21 -> -1299.3227 | G34: =-G27*$B$21 -> -1390.2753 | H34: =-H27*$B$21 -> -1459.7891
A35: (Increase)/decrease in net working capital | C35: ='Working Capital'!G16 -> -775.58256 | D35: =-$B$17*(D27-C27) -> -2236.8183 | E35: =-$B$17*(E27-D27) -> -2214.4501 | F35: =-$B$17*(F27-E27) -> -2145.5561 | G35: =-$B$17*(G27-F27) -> -2027.5505 | H35: =-$B$17*(H27-G27) -> -1549.6279
A36: Free cash flow to firm (FCFF) | C36: =C29+C32+C33+C34+C35 -> 2281.1493 | D36: =D29+D32+D33+D34+D35 -> 1125.5868 | E36: =E29+E32+E33+E34+E35 -> 1450.5715 | F36: =F29+F32+F33+F34+F35 -> 1812.6672 | G36: =G29+G32+G33+G34+G35 -> 2207.7484 | H36: =H29+H32+H33+H34+H35 -> 2844.852
A37: Discount period (years) | C37: =1-0.5*$B$16 -> 0.5 | D37: =C37+1 -> 1.5 | E37: =D37+1 -> 2.5 | F37: =E37+1 -> 3.5 | G37: =F37+1 -> 4.5
A38: Discount factor | C38: =1/(1+$B$14)^C37 -> 0.92253121 | D38: =1/(1+$B$14)^D37 -> 0.78513294 | E38: =1/(1+$B$14)^E37 -> 0.66819825 | F38: =1/(1+$B$14)^F37 -> 0.56867936 | G38: =1/(1+$B$14)^G37 -> 0.48398244
A39: PV of FCFF | C39: =C36*C38 -> 2104.4315 | D39: =D36*D38 -> 883.7353 | E39: =E36*E38 -> 969.26932 | F39: =F36*F38 -> 1030.8264 | G39: =G36*G38 -> 1068.5115
A40: Check: FY27 EBITDA agrees to Summary (must be zero) | C40: =ROUND(C29-Summary!C12,2) -> 0
A41: Check: terminal FCFF agrees to closed form k-based formula (must be zero) | H41: =ROUND(H36-(H27*B22-B17*G27*H26),2) -> 0
A43: C. DCF valuation – enterprise value to equity value
A44: Sum of PV of FCFF FY27–FY31 | B44: =SUM(C39:G39) -> 6056.774
A45: Terminal value at FY31 (Gordon growth) = FCFF(T) ÷ (WACC – g) | B45: =H36/(B14-B15) -> 22758.816
A46: PV of terminal value | B46: =B45/(1+B14)^G37 -> 11014.867
A47: Enterprise value (DCF) | B47: =B44+B46 -> 17071.641
A48: Terminal value as % of enterprise value | B48: =B46/B47 -> 0.64521431
A49: Implied EV / FY27 EBITDA | B49: =B47/C29 -> 3.1969365
A50: Implied EV / FY27 net revenue | B50: =B47/C27 -> 0.39517688
A51: Add: Cash & cash equivalents (31-Mar-26) | B51: =Assumptions!B39 -> 4324.9
A52: Add: Other bank balances incl. lien FDs | B52: ='FY26 Actual'!D53 -> 1044.6
A53: Add: Current investments | B53: ='FY26 Actual'!D54 -> 425.8
A54: Less: Borrowings | B54: =-'FY26 Actual'!D56 -> 0
A55: Equity value (DCF) – INR Lakhs | B55: =B47+SUM(B51:B54) -> 22866.941
A56: Equity value (DCF) – INR Crore | B56: =B55/100 -> 228.66941
A57: Value per share (INR) – needs share count in B23 | B57: =IF(N(B23)>0,B55/B23,"n/a – enter shares") -> n/a – enter shares
A58: Memo: Lease liabilities (not deducted – lease payments already in FCFF) | B58: ='FY26 Actual'!D55 -> 3745.1
A60: D. Market cross-checks (FY27E metrics) | B60: Multiple – Low | C60: Base | D60: High | E60: Metric (INR Lakhs) | F60: Equity – Low | G60: Base | H60: High
A61: EV / FY27E EBITDA (after ECL) | B61: 6 | C61: 8 | D61: 10 | E61: =C29 -> 5340 | F61: =B61*$E61+SUM($B$51:$B$54) -> 37835.3 | G61: =C61*$E61+SUM($B$51:$B$54) -> 48515.3 | H61: =D61*$E61+SUM($B$51:$B$54) -> 59195.3 | I61: Assumption – small-cap Indian IT services/software range 6–10x; discount to large caps for size, FY26 loss, receivable quality
A62: EV / FY27E net revenue | B62: 0.6 | C62: 0.8 | D62: 1 | E62: =C27 -> 43200 | F62: =B62*$E62+SUM($B$51:$B$54) -> 31715.3 | G62: =C62*$E62+SUM($B$51:$B$54) -> 40355.3 | H62: =D62*$E62+SUM($B$51:$B$54) -> 48995.3 | I62: Assumption – consistent with ~12% EBITDA margin at 6–10x EBITDA
A63: Price / Book (31-Mar-26 equity) | B63: 0.8 | C63: 1 | D63: 1.2 | E63: ='FY26 Actual'!D57 -> 27672.1 | F63: =B63*$E63 -> 22137.68 | G63: =C63*$E63 -> 27672.1 | H63: =D63*$E63 -> 33206.52 | I63: Assumption – book equity INR 27,672 lakhs; includes large receivable/unbilled balances so ~1.0x applied
A64: DCF (low = WACC +1% / g –0.5%; high = WACC –1% / g +0.5%; base per section C) | F64: =C83 -> 21654.324 | G64: =B55 -> 22866.941 | H64: =E81 -> 24361.454
A66: E. Valuation summary – weighted equity value | B66: Weight | C66: Low | D66: Base | E66: High | F66: Base – INR Crore
A67: DCF (FCFF) | B67: 0.5 | C67: =F64 -> 21654.324 | D67: =G64 -> 22866.941 | E67: =H64 -> 24361.454 | F67: =D67/100 -> 228.66941
A68: EV / EBITDA | B68: 0.3 | C68: =F61 -> 37835.3 | D68: =G61 -> 48515.3 | E68: =H61 -> 59195.3 | F68: =D68/100 -> 485.153
A69: EV / Net revenue | B69: 0.1 | C69: =F62 -> 31715.3 | D69: =G62 -> 40355.3 | E69: =H62 -> 48995.3 | F69: =D69/100 -> 403.553
A70: Price / Book | B70: 0.1 | C70: =F63 -> 22137.68 | D70: =G63 -> 27672.1 | E70: =H63 -> 33206.52 | F70: =D70/100 -> 276.721
A71: Weighted equity value – INR Lakhs | B71: =SUM(B67:B70) -> 1 | C71: =SUMPRODUCT($B$67:$B$70,C67:C70) -> 27563.05 | D71: =SUMPRODUCT($B$67:$B$70,D67:D70) -> 32790.801 | E71: =SUMPRODUCT($B$67:$B$70,E67:E70) -> 38159.499 | F71: =D71/100 -> 327.90801
A72: Check: weights total 100% (must be zero) | B72: =ROUND(B71-1,6) -> 0
A73: Weighted value per share (INR) | D73: =IF(N(B23)>0,D71/B23,"n/a – enter shares") -> n/a – enter shares
A74: Implied EV / FY27 EBITDA at weighted equity value | D74: =(D71-SUM(B51:B54))/C29 -> 5.0553372
A75: Weighted value as multiple of book equity | D75: =D71/'FY26 Actual'!D57 -> 1.1849769
A77: F. DCF equity value sensitivity (INR Lakhs) – WACC (rows) vs terminal growth (columns); higher g adds NWC investment so value is only mildly sensitive to g
A79: WACC ↓ / g → | B79: =$B$15+(-0.01) -> 0.04 | C79: =$B$15+(-0.005) -> 0.045 | D79: =$B$15+(0) -> 0.05 | E79: =$B$15+(0.005) -> 0.055 | F79: =$B$15+(0.01) -> 0.06
A80: =$B$14+(-0.02) -> 0.155 | B80: =SUMPRODUCT($C$36:$G$36/(1+$A80)^$C$37:$G$37)+($G$27*(1+B$79)*$B$22-$B$17*$G$27*B$79)/($A80-B$79)/(1+$A80)^$G$37+SUM($B$51:$B$54) -> 26238.546 | C80: =SUMPRODUCT($C$36:$G$36/(1+$A80)^$C$37:$G$37)+($G$27*(1+C$79)*$B$22-$B$17*$G$27*C$79)/($A80-C$79)/(1+$A80)^$G$37+SUM($B$51:$B$54) -> 26244.763 | D80: =SUMPRODUCT($C$36:$G$36/(1+$A80)^$C$37:$G$37)+($G$27*(1+D$79)*$B$22-$B$17*$G$27*D$79)/($A80-D$79)/(1+$A80)^$G$37+SUM($B$51:$B$54) -> 26251.571 | E80: =SUMPRODUCT($C$36:$G$36/(1+$A80)^$C$37:$G$37)+($G$27*(1+E$79)*$B$22-$B$17*$G$27*E$79)/($A80-E$79)/(1+$A80)^$G$37+SUM($B$51:$B$54) -> 26259.061 | F80: =SUMPRODUCT($C$36:$G$36/(1+$A80)^$C$37:$G$37)+($G$27*(1+F$79)*$B$22-$B$17*$G$27*F$79)/($A80-F$79)/(1+$A80)^$G$37+SUM($B$51:$B$54) -> 26267.339
A81: =$B$14+(-0.01) -> 0.165 | B81: =SUMPRODUCT($C$36:$G$36/(1+$A81)^$C$37:$G$37)+($G$27*(1+B$79)*$B$22-$B$17*$G$27*B$79)/($A81-B$79)/(1+$A81)^$G$37+SUM($B$51:$B$54) -> 24492.036 | C81: =SUMPRODUCT($C$36:$G$36/(1+$A81)^$C$37:$G$37)+($G$27*(1+C$79)*$B$22-$B$17*$G$27*C$79)/($A81-C$79)/(1+$A81)^$G$37+SUM($B$51:$B$54) -> 24452.136 | D81: =SUMPRODUCT($C$36:$G$36/(1+$A81)^$C$37:$G$37)+($G$27*(1+D$79)*$B$22-$B$17*$G$27*D$79)/($A81-D$79)/(1+$A81)^$G$37+SUM($B$51:$B$54) -> 24408.766 | E81: =SUMPRODUCT($C$36:$G$36/(1+$A81)^$C$37:$G$37)+($G$27*(1+E$79)*$B$22-$B$17*$G$27*E$79)/($A81-E$79)/(1+$A81)^$G$37+SUM($B$51:$B$54) -> 24361.454 | F81: =SUMPRODUCT($C$36:$G$36/(1+$A81)^$C$37:$G$37)+($G$27*(1+F$79)*$B$22-$B$17*$G$27*F$79)/($A81-F$79)/(1+$A81)^$G$37+SUM($B$51:$B$54) -> 24309.635
A82: =$B$14+(0) -> 0.175 | B82: =SUMPRODUCT($C$36:$G$36/(1+$A82)^$C$37:$G$37)+($G$27*(1+B$79)*$B$22-$B$17*$G$27*B$79)/($A82-B$79)/(1+$A82)^$G$37+SUM($B$51:$B$54) -> 23012.083 | C82: =SUMPRODUCT($C$36:$G$36/(1+$A82)^$C$37:$G$37)+($G$27*(1+C$79)*$B$22-$B$17*$G$27*C$79)/($A82-C$79)/(1+$A82)^$G$37+SUM($B$51:$B$54) -> 22942.303 | D82: =SUMPRODUCT($C$36:$G$36/(1+$A82)^$C$37:$G$37)+($G$27*(1+D$79)*$B$22-$B$17*$G$27*D$79)/($A82-D$79)/(1+$A82)^$G$37+SUM($B$51:$B$54) -> 22866.941 | E82: =SUMPRODUCT($C$36:$G$36/(1+$A82)^$C$37:$G$37)+($G$27*(1+E$79)*$B$22-$B$17*$G$27*E$79)/($A82-E$79)/(1+$A82)^$G$37+SUM($B$51:$B$54) -> 22785.299 | F82: =SUMPRODUCT($C$36:$G$36/(1+$A82)^$C$37:$G$37)+($G$27*(1+F$79)*$B$22-$B$17*$G$27*F$79)/($A82-F$79)/(1+$A82)^$G$37+SUM($B$51:$B$54) -> 22696.557
A83: =$B$14+(0.01) -> 0.185 | B83: =SUMPRODUCT($C$36:$G$36/(1+$A83)^$C$37:$G$37)+($G$27*(1+B$79)*$B$22-$B$17*$G$27*B$79)/($A83-B$79)/(1+$A83)^$G$37+SUM($B$51:$B$54) -> 21743.154 | C83: =SUMPRODUCT($C$36:$G$36/(1+$A83)^$C$37:$G$37)+($G$27*(1+C$79)*$B$22-$B$17*$G$27*C$79)/($A83-C$79)/(1+$A83)^$G$37+SUM($B$51:$B$54) -> 21654.324 | D83: =SUMPRODUCT($C$36:$G$36/(1+$A83)^$C$37:$G$37)+($G$27*(1+D$79)*$B$22-$B$17*$G$27*D$79)/($A83-D$79)/(1+$A83)^$G$37+SUM($B$51:$B$54) -> 21558.914 | E83: =SUMPRODUCT($C$36:$G$36/(1+$A83)^$C$37:$G$37)+($G$27*(1+E$79)*$B$22-$B$17*$G$27*E$79)/($A83-E$79)/(1+$A83)^$G$37+SUM($B$51:$B$54) -> 21456.165 | F83: =SUMPRODUCT($C$36:$G$36/(1+$A83)^$C$37:$G$37)+($G$27*(1+F$79)*$B$22-$B$17*$G$27*F$79)/($A83-F$79)/(1+$A83)^$G$37+SUM($B$51:$B$54) -> 21345.195
A84: =$B$14+(0.02) -> 0.195 | B84: =SUMPRODUCT($C$36:$G$36/(1+$A84)^$C$37:$G$37)+($G$27*(1+B$79)*$B$22-$B$17*$G$27*B$79)/($A84-B$79)/(1+$A84)^$G$37+SUM($B$51:$B$54) -> 20644.07 | C84: =SUMPRODUCT($C$36:$G$36/(1+$A84)^$C$37:$G$37)+($G$27*(1+C$79)*$B$22-$B$17*$G$27*C$79)/($A84-C$79)/(1+$A84)^$G$37+SUM($B$51:$B$54) -> 20543.528 | D84: =SUMPRODUCT($C$36:$G$36/(1+$A84)^$C$37:$G$37)+($G$27*(1+D$79)*$B$22-$B$17*$G$27*D$79)/($A84-D$79)/(1+$A84)^$G$37+SUM($B$51:$B$54) -> 20436.052 | E84: =SUMPRODUCT($C$36:$G$36/(1+$A84)^$C$37:$G$37)+($G$27*(1+E$79)*$B$22-$B$17*$G$27*E$79)/($A84-E$79)/(1+$A84)^$G$37+SUM($B$51:$B$54) -> 20320.899 | F84: =SUMPRODUCT($C$36:$G$36/(1+$A84)^$C$37:$G$37)+($G$27*(1+F$79)*$B$22-$B$17*$G$27*F$79)/($A84-F$79)/(1+$A84)^$G$37+SUM($B$51:$B$54) -> 20197.216
A86: G. Methodology, key assumptions and limitations
A87: 1. Method: primary = 5-year DCF of free cash flow to firm (FY27 budget + FY28–FY31) with Gordon-growth terminal value; cross-checked with EV/EBITDA, EV/Revenue and P/B. Final value is a weighted blend (weights in section E).
A88: 2. FY27 = management budget (net revenue 43,200; EBITDA after ECL 5,340 = 12% of gross revenue) and FY27 working-capital cash impact are linked from the existing sheets. FY28 growth 10% is linked to the Apr–Sep 27 projection assumption; FY29–FY31 growth fades 9% / 8% / 7% (analyst assumption). Terminal growth 5%.
A89: 3. EBITDA margin is held at the FY27 budget level (12.36% of net revenue). FY26 EBITDA was negative (–2,619) due to 3,647 of ECL/write-offs; the FY27 budget is a significant turnaround, so the valuation is highly sensitive to delivery of the budget – see Sensitivity sheet and low case in section E.
A90: 4. FCFF = EBITDA – tax on EBIT – capex – lease payments – increase in NWC. Lease payments are deducted as operating cash cost, therefore lease liabilities (3,745) are NOT deducted again as debt. Other income (274.8, largely interest) is excluded from FCFF because the related cash/investments are added at book value in the equity bridge.
A91: 5. Incremental NWC beyond FY27 = FY27 NWC % of net revenue (≈52%, driven by ~140 receivable days + ~115 unbilled days) × revenue growth. Working capital is a major cash drag; faster collections would increase value.
A92: 6. Terminal year: D&A set equal to capex + lease payments (steady state) so that tax shield is not overstated; terminal NWC investment at growth g.
A93: 7. Equity bridge: + cash & equivalents, other bank balances (incl. lien FDs) and current investments at book; – borrowings (nil). Not adjusted for: share of loss of equity-accounted investee, non-controlling interests, contingent liabilities, tax assets/DTA, and potential haircut on lien-marked deposits (data not in workbook).
A94: 8. Cost of equity 17.5% = Rf 6.8% + 1.1 × ERP 7.0% + 3.0% specific premium; company is debt-free so WACC = cost of equity. Rf, ERP, beta and multiples are analyst assumptions (not sourced from live market data) – refresh with current market data before relying on the output.
A95: 9. Per-share value requires share count (input B23). Valuation date is 31-Mar-26; cash flows from FY27 discounted from that date. This is an indicative internal valuation, not a certified valuation report.

Sheet Assumptions
A1: Infrasoft Technologies Limited (Kiya.ai) – Consolidated
A2: Key Assumptions – Budget FY 2026-27 and Projection Apr-27 to Sep-27
A3: Going concern assessment for the year ended 31 March 2026 | All amounts in INR Lakhs unless stated
A5: Parameter | B5: Value | C5: Unit | D5: Basis / Source
A6: A. Revenue – FY 2026-27 Budget
A7: Gross revenue FY 2026-27 | B7: 44500 | C7: INR Lakhs | D7: Management budget (as instructed)
A8: Net revenue FY 2026-27 | B8: 43200 | C8: INR Lakhs | D8: Management budget (as instructed)
A9: Channel partner cost (Gross – Net) | B9: =B7-B8 -> 1300 | C9: INR Lakhs | D9: Formula: difference between gross and net revenue
A10: Channel partner cost as % of gross revenue | B10: =IF(B7=0,0,B9/B7) -> 0.029213483 | C10: % | D10: Used to phase channel partner cost with monthly revenue
A11: Revenue mix – Products | B11: ='FY26 Actual'!E43 -> 0.68366815 | C11: % | D11: FY 2025-26 actual segment mix (Note 39 – Segment reporting)
A12: Revenue mix – Services | B12: =1-B11 -> 0.31633185 | C12: % | D12: Balancing
A14: B. Profitability target
A15: EBITDA (after ECL / write-offs) as % of gross revenue | B15: 0.12 | C15: % | D15: Management target (as instructed)
A16: Target EBITDA FY 2026-27 | B16: =B7*B15 -> 5340 | C16: INR Lakhs | D16: Formula
A17: ECL provision & write-offs as % of gross revenue | B17: 0.03 | C17: % | D17: Assumption – FY26 actual was 9.6% of revenue (one-off UBR/bad-debt clean-up); collections focus expected to normalise to ~3%
A18: ECL provision & write-offs FY 2026-27 | B18: =B7*B17 -> 1335 | C18: INR Lakhs | D18: Formula
A20: C. Cost adjustment to achieve target EBITDA
A21: Permissible operating cost FY27 (Net revenue – EBITDA – ECL) | B21: =B8-B16-B18 -> 36525 | C21: INR Lakhs | D21: Formula: cost envelope that delivers target EBITDA
A22: FY 2025-26 actual operating cost (excl. ECL / write-offs) | B22: ='Global PNL'!C44 -> 36952.7 | C22: INR Lakhs | D22: Link: CoR + G&A + S&M per FY26 audited financials (mapped)
A23: Cost adjustment factor applied to each FY26 cost line | B23: =IF(B22=0,0,B21/B22) -> 0.98842574 | C23: x | D23: Formula: each cost line FY27 = FY26 actual × factor (pro-rata)
A24: Implied change in operating cost vs FY26 | B24: =B23-1 -> -0.011574256 | C24: % | D24: Formula
A26: D. Below-EBITDA items
A27: Other income FY 2026-27 | B27: ='FY26 Actual'!D8 -> 274.8 | C27: INR Lakhs | D27: Held at FY26 actual level
A28: Depreciation & amortisation FY 2026-27 | B28: ='FY26 Actual'!D14 -> 1447 | C28: INR Lakhs | D28: Held at FY26 actual level (no major capex planned)
A29: Finance cost FY 2026-27 | B29: ='FY26 Actual'!D13 -> 272.2 | C29: INR Lakhs | D29: Held at FY26 actual level (lease interest)
A30: Effective tax rate | B30: 0.2517 | C30: % | D30: Sec 115BAA rate (22% + 10% SC + 4% cess); applied only on positive PBT
A32: E. Cash flow & working capital
A33: Capital expenditure FY 2026-27 | B33: 300 | C33: INR Lakhs | D33: Assumption – FY26 actual capex INR 150.9 lakhs; provision for laptops/servers
A34: Lease payments (principal + interest) FY 2026-27 | B34: ='FY26 Actual'!D60+'FY26 Actual'!D61 -> 1003.4 | C34: INR Lakhs | D34: Held at FY26 actual (Cash flow statement, financing activities)
A35: Trade receivable days (on net revenue) – target | B35: 140 | C35: Days | D35: Assumption – FY26 actual shown in Working Capital sheet (~154 days)
A36: Unbilled revenue (contract asset) days – target | B36: 115 | C36: Days | D36: Assumption – FY26 actual ~124 days
A37: Unearned revenue as % of net revenue | B37: 0.1 | C37: % | D37: Assumption – FY26 actual ~10.2%
A38: Trade payable days (on non-salary costs) | B38: 95 | C38: Days | D38: Assumption – FY26 actual ~102 days
A39: Opening cash & cash equivalents – 1 April 2026 | B39: ='FY26 Actual'!D52 -> 4324.9 | C39: INR Lakhs | D39: Link: Balance sheet 31 March 2026 (Note 12)
A41: F. Projection Apr-27 to Sep-27
A42: Increase over FY 2026-27 on annualised basis | B42: 0.1 | C42: % | D42: As instructed – each monthly line = FY27 annual × (1 + 10%) / 12
A44: G. Cost-line allocation keys (for mapping FY26 audited numbers to MIS heads)
A45: Salaries – Direct staff (share of salaries) | B45: 0.822 | C45: % | D45: Per FY25-26 budget structure in prior-year going concern working (21,750 / 26,461)
A46: Salaries – Support staff (share of salaries) | B46: 0.099 | C46: % | D46: Per prior-year working (2,613 / 26,461)
A47: Salaries – Sales & marketing (share of salaries) | B47: =1-B45-B46 -> 0.079 | C47: % | D47: Balancing
A48: Travel – Project (share of travel) | B48: 0.618 | C48: % | D48: Per prior-year working (1,605 / 2,597)
A49: Travel – G&A (share of travel) | B49: 0.07 | C49: % | D49: Per prior-year working (181 / 2,597)
A50: Travel – Sales & marketing (share of travel) | B50: =1-B48-B49 -> 0.312 | C50: % | D50: Balancing
A52: H. Sensitivity levers
A53: Revenue decline (stress) | B53: 0.05 | C53: % | D53: Stress test – consistent with prior-year working
A54: Cost increase (stress) | B54: 0.02 | C54: % | D54: Stress test – consistent with prior-year working
A56: I. Monthly revenue phasing FY 2026-27 (seasonality)
A57: Month | B57: 46113 | C57: 46143 | D57: 46174 | E57: 46204 | F57: 46235 | G57: 46266 | H57: 46296 | I57: 46327 | J57: 46357 | K57: 46388 | L57: 46419 | M57: 46447 | N57: Total
A58: Phasing % of annual revenue | B58: 0.0745 | C58: 0.0483 | D58: 0.0627 | E58: 0.0713 | F58: 0.0756 | G58: 0.0803 | H58: 0.0858 | I58: 0.0868 | J58: 0.089 | K58: 0.1043 | L58: 0.1086 | M58: =1-SUM(B58:L58) -> 0.1128 | N58: =SUM(B58:M58) -> 1
A59: Basis: monthly seasonality of FY25-26 budget in prior-year going concern working (back-ended revenue; Q4 ~30%). Must total 100%.
A60: Phasing check (must be zero) | B60: =ROUND(N58-1,4) -> 0
A62: Legend: blue text on yellow = input (editable); green = link to another sheet; black = formula.

Sheet FY26 Actual
A1: Infrasoft Technologies Limited (Kiya.ai) – Consolidated
A2: FY 2025-26 Audited Consolidated Financials – Source Data
A3: Source: Mar 26_CFS Infrasoft.xlsx (SoPL March 26, BS MARCH 26, Notes 25-32, Cash Flow, Note 39) | INR million converted to INR Lakhs (×10)
A5: Particulars | B5: Source reference | C5: FY26 (INR Mn) | D5: FY26 (INR Lakhs) | E5: FY25 (INR Mn) | F5: FY25 (INR Lakhs)
A6: Revenue from operations – Products | B6: Note 25 / Note 39 | C6: 2596.64 | D6: =C6*10 -> 25966.4 | E6: 2821.58 | F6: =E6*10 -> 28215.8
A7: Revenue from operations – Services | B7: Note 25 / Note 39 | C7: 1201.46 | D7: =C7*10 -> 12014.6 | E7: 1189.55 | F7: =E7*10 -> 11895.5
A8: Other income | B8: Note 26 | C8: 27.48 | D8: =C8*10 -> 274.8 | E8: 45.64 | F8: =E8*10 -> 456.4
A9: Salaries, wages and incentives | B9: Note 27 | C9: 2236.61 | D9: =C9*10 -> 22366.1 | E9: 2317.64 | F9: =E9*10 -> 23176.4
A10: Contribution to gratuity | B10: Note 27 | C10: 131.28 | D10: =C10*10 -> 1312.8 | E10: 23.13 | F10: =E10*10 -> 231.3
A11: Contribution to PF and other funds | B11: Note 27 | C11: 91.25 | D11: =C11*10 -> 912.5 | E11: 91.37 | F11: =E11*10 -> 913.7
A12: Staff welfare expenses | B12: Note 27 | C12: 10.03 | D12: =C12*10 -> 100.3 | E12: 13.54 | F12: =E12*10 -> 135.4
A13: Finance costs | B13: Note 28 | C13: 27.22 | D13: =C13*10 -> 272.2 | E13: 29.73 | F13: =E13*10 -> 297.3
A14: Depreciation and amortisation | B14: Note 29 | C14: 144.7 | D14: =C14*10 -> 1447 | E14: 155.62 | F14: =E14*10 -> 1556.2
A15: Software development & maintenance services | B15: Note 30 | C15: 513.77 | D15: =C15*10 -> 5137.7 | E15: 417.16 | F15: =E15*10 -> 4171.6
A16: Manpower cost | B16: Note 30 | C16: 104.19 | D16: =C16*10 -> 1041.9 | E16: 99.43 | F16: =E16*10 -> 994.3
A17: Computer hardware | B17: Note 30 | C17: 98.1 | D17: =C17*10 -> 981 | E17: 4.42 | F17: =E17*10 -> 44.2
... A40: Tax expense / (credit) | B40: SoPL / Note 33 | C40: -97.6 | D40: =C40*10 -> -976 | E40: 69.86 | F40: =E40*10 -> 698.6
A41: Total revenue from operations | C41: =SUM(C6:C7) -> 3798.1 | D41: =SUM(D6:D7) -> 37981 | E41: =SUM(E6:E7) -> 4011.13 | F41: =SUM(F6:F7) -> 40111.3
A42: Total other expenses (Note 30) – check vs FS 1,590.84 / 1,243.26 mn | C42: =SUM(C15:C38) -> 1590.83 | D42: =SUM(D15:D38) -> 15908.3 | E42: =SUM(E15:E38) -> 1243.26 | F42: =SUM(F15:F38) -> 12432.6
A43: Revenue mix – Products (% of revenue) | E43: =IF(C41=0,0,C6/C41) -> 0.68366815
A44: Loss before tax (after share of associate) – derived | B44: FS: (432.78) / 182.48 mn | C44: =C41+C8-SUM(C9:C14)-C42-C39 -> -432.76 | D44: =D41+D8-SUM(D9:D14)-D42-D39 -> -4327.6 | E44: =E41+E8-SUM(E9:E14)-E42-E39 -> 182.48 | F44: =F41+F8-SUM(F9:F14)-F42-F39 -> 1824.8
A47: Balance sheet items – 31 March 2026
A48: Trade receivables (incl. unbilled dues) | B48: BS / Note 11 | C48: 1599.1 | D48: =C48*10 -> 15991 | E48: 1869.42 | F48: =E48*10 -> 18694.2
A49: Unbilled revenue – contract assets | B49: Note 25(b) / Note 15 | C49: 1292.49 | D49: =C49*10 -> 12924.9 | E49: 1235.84 | F49: =E49*10 -> 12358.4
A50: Unearned revenue – contract liability | B50: Note 25(b) / Note 22 | C50: 387.81 | D50: =C50*10 -> 3878.1 | E50: 375.46 | F50: =E50*10 -> 3754.6
A51: Trade payables (MSME + others) | B51: BS / Note 21 | C51: 344.52 | D51: =C51*10 -> 3445.2 | E51: 219.31 | F51: =E51*10 -> 2193.1
A52: Cash and cash equivalents | B52: BS / Note 12 | C52: 432.49 | D52: =C52*10 -> 4324.9 | E52: 290.8 | F52: =E52*10 -> 2908
A53: Other bank balances (incl. lien FDs) | B53: BS / Note 13 | C53: 104.46 | D53: =C53*10 -> 1044.6 | E53: 131.29 | F53: =E53*10 -> 1312.9
A54: Current investments | B54: BS / Note 10 | C54: 42.58 | D54: =C54*10 -> 425.8 | E54: 41.1 | F54: =E54*10 -> 411
A55: Lease liabilities (current + non-current) | B55: BS / Note 19 | C55: 374.51 | D55: =C55*10 -> 3745.1 | E55: 397 | F55: =E55*10 -> 3970
A56: Borrowings | B56: BS / Note 18 | C56: 0 | D56: =C56*10 -> 0 | E56: 50 | F56: =E56*10 -> 500
A57: Total equity | B57: BS | C57: 2767.21 | D57: =C57*10 -> 27672.1 | E57: 2915.33 | F57: =E57*10 -> 29153.3
A58: Cash flow items – FY 2025-26
A59: Net cash from operating activities | B59: Cash flow statement | C59: 275.34 | D59: =C59*10 -> 2753.4 | E59: 59.92 | F59: =E59*10 -> 599.2
A60: Principal payment of lease obligations | B60: Cash flow statement | C60: 73.57 | D60: =C60*10 -> 735.7 | E60: 74.45 | F60: =E60*10 -> 744.5
A61: Interest paid on lease liabilities | B61: Cash flow statement | C61: 26.77 | D61: =C61*10 -> 267.7 | E61: 29.43 | F61: =E61*10 -> 294.3
A62: Purchase of property, plant and equipment | B62: Cash flow statement | C62: 15.09 | D62: =C62*10 -> 150.9 | E62: 38.08 | F62: =E62*10 -> 380.8
A64: Note: Channel partner cost for FY 2025-26 is not separately disclosed in the audited financials and is embedded in 'Software development & maintenance services'. FY26 gross revenue is therefore presented equal to revenue from operations.

Sheet Global PNL
A1: Infrasoft Technologies Limited (Kiya.ai) – Consolidated
A2: Income Statement – FY26 Actual | FY 2026-27 Budget | Projection Apr-27 to Sep-27
A3: Going concern assessment for the year ended 31 March 2026 | All amounts in INR Lakhs unless stated
B5: INR Lakhs | C5: FY 2025-26 Actual | D5: % of Gross Rev | E5: 46113 | F5: 46143 | G5: 46174 | H5: 46204 | I5: 46235 | J5: 46266 | K5: 46296 | L5: 46327 | M5: 46357 | N5: 46388 | O5: 46419 | P5: 46447 | Q5: FY 2026-27 Budget | R5: % of Gross Rev | S5: Var vs FY26 | T5: Var % | V5: 46478 | W5: 46508 | X5: 46539 | Y5: 46569 | Z5: 46600 | AA5: 46631 | AB5: Apr-Sep 27 Total | AC5: Annualised FY28 | AD5: Growth vs FY27
B6: (A) Audited (B) Budget (P) Projection | C6: (A) | E6: (B) | F6: (B) | G6: (B) | H6: (B) | I6: (B) | J6: (B) | K6: (B) | L6: (B) | M6: (B) | N6: (B) | O6: (B) | P6: (B) | Q6: (B) | V6: (P) | W6: (P) | X6: (P) | Y6: (P) | Z6: (P) | AA6: (P) | AB6: (P) | AC6: (P)
B8: Revenue
B9: Products (Omnichannel, RegTech, Core Banking) | C9: ='FY26 Actual'!D6 -> 25966.4 | D9: =IF($C$11=0,0,C9/$C$11) -> 0.68366815 | E9: =Assumptions!$B$7*Assumptions!$B$11*Assumptions!B$58 -> 2266.5308 | F9: =Assumptions!$B$7*Assumptions!$B$11*Assumptions!C$58 -> 1469.4421 | G9: =Assumptions!$B$7*Assumptions!$B$11*Assumptions!D$58 -> 1907.5367 | H9: =Assumptions!$B$7*Assumptions!$B$11*Assumptions!E$58 -> 2169.1765 | I9: =Assumptions!$B$7*Assumptions!$B$11*Assumptions!F$58 -> 2299.9964 | J9: =Assumptions!$B$7*Assumptions!$B$11*Assumptions!G$58 -> 2442.9856 | K9: =Assumptions!$B$7*Assumptions!$B$11*Assumptions!H$58 -> 2610.3134 | L9: =Assumptions!$B$7*Assumptions!$B$11*Assumptions!I$58 -> 2640.7366 | ... P9: =Assumptions!$B$7*Assumptions!$B$11*Assumptions!M$58 -> 3431.7406 | Q9: =SUM(E9:P9) -> 30423.233 | R9: =IF($Q$11=0,0,Q9/$Q$11) -> 0.68366815 | S9: =Q9-C9 -> 4456.8327 | T9: =IF(C9=0,0,S9/ABS(C9)) -> 0.17163845 | V9: =$Q9*(1+Assumptions!$B$42)/12 -> 2788.7963 | W9: =$Q9*(1+Assumptions!$B$42)/12 -> 2788.7963 | X9: =$Q9*(1+Assumptions!$B$42)/12 -> 2788.7963 | Y9: =$Q9*(1+Assumptions!$B$42)/12 -> 2788.7963 | Z9: =$Q9*(1+Assumptions!$B$42)/12 -> 2788.7963 | AA9: =$Q9*(1+Assumptions!$B$42)/12 -> 2788.7963 | AB9: =SUM(V9:AA9) -> 16732.778 | AC9: =AB9*12/6 -> 33465.556 | AD9: =IF(Q9=0,0,AC9/Q9-1) -> 0.1
B10: Services (Digital Engg. Services) | C10: ='FY26 Actual'!D7 -> 12014.6 | D10: =IF($C$11=0,0,C10/$C$11) -> 0.31633185 | E10: =Assumptions!$B$7*Assumptions!$B$12*Assumptions!B$58 -> 1048.7192 | F10: =Assumptions!$B$7*Assumptions!$B$12*Assumptions!C$58 -> 679.90786 | G10: =Assumptions!$B$7*Assumptions!$B$12*Assumptions!D$58 -> 882.61331 | H10: =Assumptions!$B$7*Assumptions!$B$12*Assumptions!E$58 -> 1003.6735 | I10: =Assumptions!$B$7*Assumptions!$B$12*Assumptions!F$58 -> 1064.2036 | J10: =Assumptions!$B$7*Assumptions!$B$12*Assumptions!G$58 -> 1130.3644 | K10: =Assumptions!$B$7*Assumptions!$B$12*Assumptions!H$58 -> 1207.7866 | L10: =Assumptions!$B$7*Assumptions!$B$12*Assumptions!I$58 -> 1221.8634 | ... P10: =Assumptions!$B$7*Assumptions!$B$12*Assumptions!M$58 -> 1587.8594 | Q10: =SUM(E10:P10) -> 14076.767 | R10: =IF($Q$11=0,0,Q10/$Q$11) -> 0.31633185 | S10: =Q10-C10 -> 2062.1673 | T10: =IF(C10=0,0,S10/ABS(C10)) -> 0.17163845 | V10: =$Q10*(1+Assumptions!$B$42)/12 -> 1290.3703 | W10: =$Q10*(1+Assumptions!$B$42)/12 -> 1290.3703 | X10: =$Q10*(1+Assumptions!$B$42)/12 -> 1290.3703 | Y10: =$Q10*(1+Assumptions!$B$42)/12 -> 1290.3703 | Z10: =$Q10*(1+Assumptions!$B$42)/12 -> 1290.3703 | AA10: =$Q10*(1+Assumptions!$B$42)/12 -> 1290.3703 | AB10: =SUM(V10:AA10) -> 7742.222 | AC10: =AB10*12/6 -> 15484.444 | AD10: =IF(Q10=0,0,AC10/Q10-1) -> 0.1
B11: Gross Revenue | C11: =SUM(C9:C10) -> 37981 | D11: =IF($C$11=0,0,C11/$C$11) -> 1 | E11: =SUM(E9:E10) -> 3315.25 | F11: =SUM(F9:F10) -> 2149.35 | G11: =SUM(G9:G10) -> 2790.15 | H11: =SUM(H9:H10) -> 3172.85 | I11: =SUM(I9:I10) -> 3364.2 | J11: =SUM(J9:J10) -> 3573.35 | K11: =SUM(K9:K10) -> 3818.1 | L11: =SUM(L9:L10) -> 3862.6 | ... Q11: =SUM(Q9:Q10) -> 44500 | R11: =IF($Q$11=0,0,Q11/$Q$11) -> 1 | S11: =Q11-C11 -> 6519 | T11: =IF(C11=0,0,S11/ABS(C11)) -> 0.17163845 | V11: =SUM(V9:V10) -> 4079.1667 | W11: =SUM(W9:W10) -> 4079.1667 | X11: =SUM(X9:X10) -> 4079.1667 | Y11: =SUM(Y9:Y10) -> 4079.1667 | Z11: =SUM(Z9:Z10) -> 4079.1667 | AA11: =SUM(AA9:AA10) -> 4079.1667 | AB11: =SUM(AB9:AB10) -> 24475 | AC11: =AB11*12/6 -> 48950 | AD11: =IF(Q11=0,0,AC11/Q11-1) -> 0.1
B12: Less: Channel partner cost | C12: 0 | D12: =IF($C$11=0,0,C12/$C$11) -> 0 | E12: =E11*Assumptions!$B$10 -> 96.85 | F12: =F11*Assumptions!$B$10 -> 62.79 | G12: =G11*Assumptions!$B$10 -> 81.51 | H12: =H11*Assumptions!$B$10 -> 92.69 | I12: =I11*Assumptions!$B$10 -> 98.28 | J12: =J11*Assumptions!$B$10 -> 104.39 | K12: =K11*Assumptions!$B$10 -> 111.54 | L12: =L11*Assumptions!$B$10 -> 112.84 | ... P12: =P11*Assumptions!$B$10 -> 146.64 | Q12: =SUM(E12:P12) -> 1300 | R12: =IF($Q$11=0,0,Q12/$Q$11) -> 0.029213483 | S12: =Q12-C12 -> 1300 | T12: =IF(C12=0,0,S12/ABS(C12)) -> 0 | V12: =$Q12*(1+Assumptions!$B$42)/12 -> 119.16667 | W12: =$Q12*(1+Assumptions!$B$42)/12 -> 119.16667 | X12: =$Q12*(1+Assumptions!$B$42)/12 -> 119.16667 | Y12: =$Q12*(1+Assumptions!$B$42)/12 -> 119.16667 | Z12: =$Q12*(1+Assumptions!$B$42)/12 -> 119.16667 | AA12: =$Q12*(1+Assumptions!$B$42)/12 -> 119.16667 | AB12: =SUM(V12:AA12) -> 715 | AC12: =AB12*12/6 -> 1430 | AD12: =IF(Q12=0,0,AC12/Q12-1) -> 0.1
B13: Net Revenue | C13: =C11-C12 -> 37981 | D13: =IF($C$11=0,0,C13/$C$11) -> 1 | E13: =E11-E12 -> 3218.4 | F13: =F11-F12 -> 2086.56 | G13: =G11-G12 -> 2708.64 | H13: =H11-H12 -> 3080.16 | I13: =I11-I12 -> 3265.92 | J13: =J11-J12 -> 3468.96 | K13: =K11-K12 -> 3706.56 | L13: =L11-L12 -> 3749.76 | ... Q13: =Q11-Q12 -> 43200 | R13: =IF($Q$11=0,0,Q13/$Q$11) -> 0.97078652 | S13: =Q13-C13 -> 5219 | T13: =IF(C13=0,0,S13/ABS(C13)) -> 0.13741081 | V13: =V11-V12 -> 3960 | W13: =W11-W12 -> 3960 | X13: =X11-X12 -> 3960 | Y13: =Y11-Y12 -> 3960 | Z13: =Z11-Z12 -> 3960 | AA13: =AA11-AA12 -> 3960 | AB13: =AB11-AB12 -> 23760 | AC13: =AB13*12/6 -> 47520 | AD13: =IF(Q13=0,0,AC13/Q13-1) -> 0.1
B15: Cost of Revenue
B16: Salaries - Direct Staff | C16: =('FY26 Actual'!D9+'FY26 Actual'!D10+'FY26 Actual'!D11)*Assumptions!$B$45 -> 20214.131 | D16: =IF($C$11=0,0,C16/$C$11) -> 0.53221692 | E16: =$C16*Assumptions!$B$23/12 -> 1665.0139 | F16: =$C16*Assumptions!$B$23/12 -> 1665.0139 | G16: =$C16*Assumptions!$B$23/12 -> 1665.0139 | H16: =$C16*Assumptions!$B$23/12 -> 1665.0139 | I16: =$C16*Assumptions!$B$23/12 -> 1665.0139 | J16: =$C16*Assumptions!$B$23/12 -> 1665.0139 | K16: =$C16*Assumptions!$B$23/12 -> 1665.0139 | L16: =$C16*Assumptions!$B$23/12 -> 1665.0139 | ... P16: =$C16*Assumptions!$B$23/12 -> 1665.0139 | Q16: =SUM(E16:P16) -> 19980.167 | R16: =IF($Q$11=0,0,Q16/$Q$11) -> 0.44899252 | S16: =Q16-C16 -> -233.96352 | T16: =IF(C16=0,0,S16/ABS(C16)) -> -0.011574256 | V16: =$Q16*(1+Assumptions!$B$42)/12 -> 1831.5153 | W16: =$Q16*(1+Assumptions!$B$42)/12 -> 1831.5153 | X16: =$Q16*(1+Assumptions!$B$42)/12 -> 1831.5153 | Y16: =$Q16*(1+Assumptions!$B$42)/12 -> 1831.5153 | Z16: =$Q16*(1+Assumptions!$B$42)/12 -> 1831.5153 | AA16: =$Q16*(1+Assumptions!$B$42)/12 -> 1831.5153 | AB16: =SUM(V16:AA16) -> 10989.092 | AC16: =AB16*12/6 -> 21978.184 | AD16: =IF(Q16=0,0,AC16/Q16-1) -> 0.1
B17: Retainers & Contractors | C17: ='FY26 Actual'!D16 -> 1041.9 | D17: =IF($C$11=0,0,C17/$C$11) -> 0.027432137 | E17: =$C17*Assumptions!$B$23/12 -> 85.820065 | F17: =$C17*Assumptions!$B$23/12 -> 85.820065 | G17: =$C17*Assumptions!$B$23/12 -> 85.820065 | H17: =$C17*Assumptions!$B$23/12 -> 85.820065 | I17: =$C17*Assumptions!$B$23/12 -> 85.820065 | J17: =$C17*Assumptions!$B$23/12 -> 85.820065 | K17: =$C17*Assumptions!$B$23/12 -> 85.820065 | L17: =$C17*Assumptions!$B$23/12 -> 85.820065 | ... P17: =$C17*Assumptions!$B$23/12 -> 85.820065 | Q17: =SUM(E17:P17) -> 1029.8408 | R17: =IF($Q$11=0,0,Q17/$Q$11) -> 0.02314249 | S17: =Q17-C17 -> -12.059217 | T17: =IF(C17=0,0,S17/ABS(C17)) -> -0.011574256 | V17: =$Q17*(1+Assumptions!$B$42)/12 -> 94.402072 | W17: =$Q17*(1+Assumptions!$B$42)/12 -> 94.402072 | X17: =$Q17*(1+Assumptions!$B$42)/12 -> 94.402072 | Y17: =$Q17*(1+Assumptions!$B$42)/12 -> 94.402072 | Z17: =$Q17*(1+Assumptions!$B$42)/12 -> 94.402072 | AA17: =$Q17*(1+Assumptions!$B$42)/12 -> 94.402072 | AB17: =SUM(V17:AA17) -> 566.41243 | AC17: =AB17*12/6 -> 1132.8249 | AD17: =IF(Q17=0,0,AC17/Q17-1) -> 0.1
B18: Project Travelling Cost | C18: ='FY26 Actual'!D23*Assumptions!$B$48 -> 1235.6292 | D18: =IF($C$11=0,0,C18/$C$11) -> 0.032532824 | E18: =$C18*Assumptions!$B$23/12 -> 101.77731 | F18: =$C18*Assumptions!$B$23/12 -> 101.77731 | G18: =$C18*Assumptions!$B$23/12 -> 101.77731 | H18: =$C18*Assumptions!$B$23/12 -> 101.77731 | I18: =$C18*Assumptions!$B$23/12 -> 101.77731 | J18: =$C18*Assumptions!$B$23/12 -> 101.77731 | K18: =$C18*Assumptions!$B$23/12 -> 101.77731 | L18: =$C18*Assumptions!$B$23/12 -> 101.77731 | ... P18: =$C18*Assumptions!$B$23/12 -> 101.77731 | Q18: =SUM(E18:P18) -> 1221.3277 | R18: =IF($Q$11=0,0,Q18/$Q$11) -> 0.027445567 | S18: =Q18-C18 -> -14.301488 | T18: =IF(C18=0,0,S18/ABS(C18)) -> -0.011574256 | V18: =$Q18*(1+Assumptions!$B$42)/12 -> 111.95504 | W18: =$Q18*(1+Assumptions!$B$42)/12 -> 111.95504 | X18: =$Q18*(1+Assumptions!$B$42)/12 -> 111.95504 | Y18: =$Q18*(1+Assumptions!$B$42)/12 -> 111.95504 | Z18: =$Q18*(1+Assumptions!$B$42)/12 -> 111.95504 | AA18: =$Q18*(1+Assumptions!$B$42)/12 -> 111.95504 | AB18: =SUM(V18:AA18) -> 671.73024 | AC18: =AB18*12/6 -> 1343.4605 | AD18: =IF(Q18=0,0,AC18/Q18-1) -> 0.1
B19: Hosting & Software Cost | C19: ='FY26 Actual'!D15 -> 5137.7 | D19: =IF($C$11=0,0,C19/$C$11) -> 0.13527027 | E19: =$C19*Assumptions!$B$23/12 -> 423.18625 | F19: =$C19*Assumptions!$B$23/12 -> 423.18625 | G19: =$C19*Assumptions!$B$23/12 -> 423.18625 | H19: =$C19*Assumptions!$B$23/12 -> 423.18625 | I19: =$C19*Assumptions!$B$23/12 -> 423.18625 | J19: =$C19*Assumptions!$B$23/12 -> 423.18625 | K19: =$C19*Assumptions!$B$23/12 -> 423.18625 | L19: =$C19*Assumptions!$B$23/12 -> 423.18625 | ... P19: =$C19*Assumptions!$B$23/12 -> 423.18625 | Q19: =SUM(E19:P19) -> 5078.2349 | R19: =IF($Q$11=0,0,Q19/$Q$11) -> 0.11411764 | S19: =Q19-C19 -> -59.465054 | T19: =IF(C19=0,0,S19/ABS(C19)) -> -0.011574256 | V19: =$Q19*(1+Assumptions!$B$42)/12 -> 465.50487 | W19: =$Q19*(1+Assumptions!$B$42)/12 -> 465.50487 | X19: =$Q19*(1+Assumptions!$B$42)/12 -> 465.50487 | Y19: =$Q19*(1+Assumptions!$B$42)/12 -> 465.50487 | Z19: =$Q19*(1+Assumptions!$B$42)/12 -> 465.50487 | AA19: =$Q19*(1+Assumptions!$B$42)/12 -> 465.50487 | AB19: =SUM(V19:AA19) -> 2793.0292 | AC19: =AB19*12/6 -> 5586.0584 | AD19: =IF(Q19=0,0,AC19/Q19-1) -> 0.1
B20: Hardware & Database cost | C20: ='FY26 Actual'!D17 -> 981 | D20: =IF($C$11=0,0,C20/$C$11) -> 0.025828704 | E20: =$C20*Assumptions!$B$23/12 -> 80.803805 | F20: =$C20*Assumptions!$B$23/12 -> 80.803805 | G20: =$C20*Assumptions!$B$23/12 -> 80.803805 | H20: =$C20*Assumptions!$B$23/12 -> 80.803805 | I20: =$C20*Assumptions!$B$23/12 -> 80.803805 | J20: =$C20*Assumptions!$B$23/12 -> 80.803805 | K20: =$C20*Assumptions!$B$23/12 -> 80.803805 | L20: =$C20*Assumptions!$B$23/12 -> 80.803805 | ... P20: =$C20*Assumptions!$B$23/12 -> 80.803805 | Q20: =SUM(E20:P20) -> 969.64566 | R20: =IF($Q$11=0,0,Q20/$Q$11) -> 0.02178979 | S20: =Q20-C20 -> -11.354345 | T20: =IF(C20=0,0,S20/ABS(C20)) -> -0.011574256 | V20: =$Q20*(1+Assumptions!$B$42)/12 -> 88.884185 | W20: =$Q20*(1+Assumptions!$B$42)/12 -> 88.884185 | X20: =$Q20*(1+Assumptions!$B$42)/12 -> 88.884185 | Y20: =$Q20*(1+Assumptions!$B$42)/12 -> 88.884185 | Z20: =$Q20*(1+Assumptions!$B$42)/12 -> 88.884185 | AA20: =$Q20*(1+Assumptions!$B$42)/12 -> 88.884185 | AB20: =SUM(V20:AA20) -> 533.30511 | AC20: =AB20*12/6 -> 1066.6102 | AD20: =IF(Q20=0,0,AC20/Q20-1) -> 0.1
B21: Cost of Revenue | C21: =SUM(C16:C20) -> 28610.36 | D21: =IF($C$11=0,0,C21/$C$11) -> 0.75328085 | E21: =SUM(E16:E20) -> 2356.6014 | F21: =SUM(F16:F20) -> 2356.6014 | G21: =SUM(G16:G20) -> 2356.6014 | H21: =SUM(H16:H20) -> 2356.6014 | I21: =SUM(I16:I20) -> 2356.6014 | J21: =SUM(J16:J20) -> 2356.6014 | K21: =SUM(K16:K20) -> 2356.6014 | L21: =SUM(L16:L20) -> 2356.6014 | ... Q21: =SUM(Q16:Q20) -> 28279.216 | R21: =IF($Q$11=0,0,Q21/$Q$11) -> 0.63548801 | S21: =Q21-C21 -> -331.14362 | T21: =IF(C21=0,0,S21/ABS(C21)) -> -0.011574256 | V21: =SUM(V16:V20) -> 2592.2615 | W21: =SUM(W16:W20) -> 2592.2615 | X21: =SUM(X16:X20) -> 2592.2615 | Y21: =SUM(Y16:Y20) -> 2592.2615 | Z21: =SUM(Z16:Z20) -> 2592.2615 | AA21: =SUM(AA16:AA20) -> 2592.2615 | AB21: =SUM(AB16:AB20) -> 15553.569 | AC21: =AB21*12/6 -> 31107.138 | AD21: =IF(Q21=0,0,AC21/Q21-1) -> 0.1
B22: Gross Margin | C22: =C13-C21 -> 9370.64 | D22: =IF($C$11=0,0,C22/$C$11) -> 0.24671915 | E22: =E13-E21 -> 861.79864 | F22: =F13-F21 -> -270.04136 | G22: =G13-G21 -> 352.03864 | H22: =H13-H21 -> 723.55864 | I22: =I13-I21 -> 909.31864 | J22: =J13-J21 -> 1112.3586 | K22: =K13-K21 -> 1349.9586 | L22: =L13-L21 -> 1393.1586 | ... Q22: =Q13-Q21 -> 14920.784 | R22: =IF($Q$11=0,0,Q22/$Q$11) -> 0.33529851 | S22: =Q22-C22 -> 5550.1436 | T22: =IF(C22=0,0,S22/ABS(C22)) -> 0.59229077 | V22: =V13-V21 -> 1367.7385 | W22: =W13-W21 -> 1367.7385 | X22: =X13-X21 -> 1367.7385 | Y22: =Y13-Y21 -> 1367.7385 | Z22: =Z13-Z21 -> 1367.7385 | AA22: =AA13-AA21 -> 1367.7385 | AB22: =AB13-AB21 -> 8206.431 | AC22: =AB22*12/6 -> 16412.862 | AD22: =IF(Q22=0,0,AC22/Q22-1) -> 0.1
B23: GM % (of net revenue) | C23: =IF(C13=0,0,C22/C13) -> 0.24671915 | E23: =IF(E13=0,0,E22/E13) -> 0.26777238 | F23: =IF(F13=0,0,F22/F13) -> -0.12941941 | G23: =IF(G13=0,0,G22/G13) -> 0.12996878 | H23: =IF(H13=0,0,H22/H13) -> 0.23490943 | I23: =IF(I13=0,0,I22/I13) -> 0.27842649 | J23: =IF(J13=0,0,J22/J13) -> 0.32066055 | K23: =IF(K13=0,0,K22/K13) -> 0.36420795 | L23: =IF(L13=0,0,L22/L13) -> 0.37153275 | ... Q23: =IF(Q13=0,0,Q22/Q13) -> 0.34538851 | V23: =IF(V13=0,0,V22/V13) -> 0.34538851 | W23: =IF(W13=0,0,W22/W13) -> 0.34538851 | X23: =IF(X13=0,0,X22/X13) -> 0.34538851 | Y23: =IF(Y13=0,0,Y22/Y13) -> 0.34538851 | Z23: =IF(Z13=0,0,Z22/Z13) -> 0.34538851 | AA23: =IF(AA13=0,0,AA22/AA13) -> 0.34538851 | AB23: =IF(AB13=0,0,AB22/AB13) -> 0.34538851 | AC23: =IF(AC13=0,0,AC22/AC13) -> 0.34538851
B25: General & Administration Expenses
B26: Salaries - Support Staff | C26: =('FY26 Actual'!D9+'FY26 Actual'!D10+'FY26 Actual'!D11)*Assumptions!$B$46 -> 2434.5486 | D26: =IF($C$11=0,0,C26/$C$11) -> 0.064099118 | E26: =$C26*Assumptions!$B$23/12 -> 200.53088 | F26: =$C26*Assumptions!$B$23/12 -> 200.53088 | G26: =$C26*Assumptions!$B$23/12 -> 200.53088 | H26: =$C26*Assumptions!$B$23/12 -> 200.53088 | I26: =$C26*Assumptions!$B$23/12 -> 200.53088 | J26: =$C26*Assumptions!$B$23/12 -> 200.53088 | K26: =$C26*Assumptions!$B$23/12 -> 200.53088 | L26: =$C26*Assumptions!$B$23/12 -> 200.53088 | ... P26: =$C26*Assumptions!$B$23/12 -> 200.53088 | Q26: =SUM(E26:P26) -> 2406.3705 | R26: =IF($Q$11=0,0,Q26/$Q$11) -> 0.054075742 | S26: =Q26-C26 -> -28.178088 | T26: =IF(C26=0,0,S26/ABS(C26)) -> -0.011574256 | V26: =$Q26*(1+Assumptions!$B$42)/12 -> 220.58396 | W26: =$Q26*(1+Assumptions!$B$42)/12 -> 220.58396 | X26: =$Q26*(1+Assumptions!$B$42)/12 -> 220.58396 | Y26: =$Q26*(1+Assumptions!$B$42)/12 -> 220.58396 | Z26: =$Q26*(1+Assumptions!$B$42)/12 -> 220.58396 | AA26: =$Q26*(1+Assumptions!$B$42)/12 -> 220.58396 | AB26: =SUM(V26:AA26) -> 1323.5038 | AC26: =AB26*12/6 -> 2647.0076 | AD26: =IF(Q26=0,0,AC26/Q26-1) -> 0.1
B27: Staff Welfare | C27: ='FY26 Actual'!D12 -> 100.3 | D27: =IF($C$11=0,0,C27/$C$11) -> 0.0026407941 | E27: =$C27*Assumptions!$B$23/12 -> 8.2615918 | F27: =$C27*Assumptions!$B$23/12 -> 8.2615918 | G27: =$C27*Assumptions!$B$23/12 -> 8.2615918 | H27: =$C27*Assumptions!$B$23/12 -> 8.2615918 | I27: =$C27*Assumptions!$B$23/12 -> 8.2615918 | J27: =$C27*Assumptions!$B$23/12 -> 8.2615918 | K27: =$C27*Assumptions!$B$23/12 -> 8.2615918 | L27: =$C27*Assumptions!$B$23/12 -> 8.2615918 | ... P27: =$C27*Assumptions!$B$23/12 -> 8.2615918 | Q27: =SUM(E27:P27) -> 99.139102 | R27: =IF($Q$11=0,0,Q27/$Q$11) -> 0.002227845 | S27: =Q27-C27 -> -1.1608979 | T27: =IF(C27=0,0,S27/ABS(C27)) -> -0.011574256 | V27: =$Q27*(1+Assumptions!$B$42)/12 -> 9.087751 | W27: =$Q27*(1+Assumptions!$B$42)/12 -> 9.087751 | X27: =$Q27*(1+Assumptions!$B$42)/12 -> 9.087751 | Y27: =$Q27*(1+Assumptions!$B$42)/12 -> 9.087751 | Z27: =$Q27*(1+Assumptions!$B$42)/12 -> 9.087751 | AA27: =$Q27*(1+Assumptions!$B$42)/12 -> 9.087751 | AB27: =SUM(V27:AA27) -> 54.526506 | AC27: =AB27*12/6 -> 109.05301 | AD27: =IF(Q27=0,0,AC27/Q27-1) -> 0.1
B28: Recruitment & Training | C28: ='FY26 Actual'!D37 -> 96.1 | D28: =IF($C$11=0,0,C28/$C$11) -> 0.0025302125 | E28: =$C28*Assumptions!$B$23/12 -> 7.9156428 | F28: =$C28*Assumptions!$B$23/12 -> 7.9156428 | G28: =$C28*Assumptions!$B$23/12 -> 7.9156428 | H28: =$C28*Assumptions!$B$23/12 -> 7.9156428 | I28: =$C28*Assumptions!$B$23/12 -> 7.9156428 | J28: =$C28*Assumptions!$B$23/12 -> 7.9156428 | K28: =$C28*Assumptions!$B$23/12 -> 7.9156428 | L28: =$C28*Assumptions!$B$23/12 -> 7.9156428 | ... P28: =$C28*Assumptions!$B$23/12 -> 7.9156428 | Q28: =SUM(E28:P28) -> 94.987714 | R28: =IF($Q$11=0,0,Q28/$Q$11) -> 0.0021345554 | S28: =Q28-C28 -> -1.112286 | T28: =IF(C28=0,0,S28/ABS(C28)) -> -0.011574256 | V28: =$Q28*(1+Assumptions!$B$42)/12 -> 8.7072071 | W28: =$Q28*(1+Assumptions!$B$42)/12 -> 8.7072071 | X28: =$Q28*(1+Assumptions!$B$42)/12 -> 8.7072071 | Y28: =$Q28*(1+Assumptions!$B$42)/12 -> 8.7072071 | Z28: =$Q28*(1+Assumptions!$B$42)/12 -> 8.7072071 | AA28: =$Q28*(1+Assumptions!$B$42)/12 -> 8.7072071 | AB28: =SUM(V28:AA28) -> 52.243243 | AC28: =AB28*12/6 -> 104.48649 | AD28: =IF(Q28=0,0,AC28/Q28-1) -> 0.1
B29: Travelling & Visa Expenses | C29: ='FY26 Actual'!D23*Assumptions!$B$49 -> 139.958 | D29: =IF($C$11=0,0,C29/$C$11) -> 0.0036849477 | E29: =$C29*Assumptions!$B$23/12 -> 11.528174 | F29: =$C29*Assumptions!$B$23/12 -> 11.528174 | G29: =$C29*Assumptions!$B$23/12 -> 11.528174 | H29: =$C29*Assumptions!$B$23/12 -> 11.528174 | I29: =$C29*Assumptions!$B$23/12 -> 11.528174 | J29: =$C29*Assumptions!$B$23/12 -> 11.528174 | K29: =$C29*Assumptions!$B$23/12 -> 11.528174 | L29: =$C29*Assumptions!$B$23/12 -> 11.528174 | ... P29: =$C29*Assumptions!$B$23/12 -> 11.528174 | Q29: =SUM(E29:P29) -> 138.33809 | R29: =IF($Q$11=0,0,Q29/$Q$11) -> 0.0031087211 | S29: =Q29-C29 -> -1.6199097 | T29: =IF(C29=0,0,S29/ABS(C29)) -> -0.011574256 | V29: =$Q29*(1+Assumptions!$B$42)/12 -> 12.680992 | W29: =$Q29*(1+Assumptions!$B$42)/12 -> 12.680992 | X29: =$Q29*(1+Assumptions!$B$42)/12 -> 12.680992 | Y29: =$Q29*(1+Assumptions!$B$42)/12 -> 12.680992 | Z29: =$Q29*(1+Assumptions!$B$42)/12 -> 12.680992 | AA29: =$Q29*(1+Assumptions!$B$42)/12 -> 12.680992 | AB29: =SUM(V29:AA29) -> 76.08595 | AC29: =AB29*12/6 -> 152.1719 | AD29: =IF(Q29=0,0,AC29/Q29-1) -> 0.1
B30: Legal & Professional (incl. audit, directors' fees) | C30: ='FY26 Actual'!D26+'FY26 Actual'!D22+'FY26 Actual'!D27 -> 385.2 | D30: =IF($C$11=0,0,C30/$C$11) -> 0.010141913 | E30: =$C30*Assumptions!$B$23/12 -> 31.728466 | F30: =$C30*Assumptions!$B$23/12 -> 31.728466 | G30: =$C30*Assumptions!$B$23/12 -> 31.728466 | H30: =$C30*Assumptions!$B$23/12 -> 31.728466 | I30: =$C30*Assumptions!$B$23/12 -> 31.728466 | J30: =$C30*Assumptions!$B$23/12 -> 31.728466 | K30: =$C30*Assumptions!$B$23/12 -> 31.728466 | L30: =$C30*Assumptions!$B$23/12 -> 31.728466 | ... P30: =$C30*Assumptions!$B$23/12 -> 31.728466 | Q30: =SUM(E30:P30) -> 380.7416 | R30: =IF($Q$11=0,0,Q30/$Q$11) -> 0.0085559909 | S30: =Q30-C30 -> -4.4584033 | T30: =IF(C30=0,0,S30/ABS(C30)) -> -0.011574256 | V30: =$Q30*(1+Assumptions!$B$42)/12 -> 34.901313 | W30: =$Q30*(1+Assumptions!$B$42)/12 -> 34.901313 | X30: =$Q30*(1+Assumptions!$B$42)/12 -> 34.901313 | Y30: =$Q30*(1+Assumptions!$B$42)/12 -> 34.901313 | Z30: =$Q30*(1+Assumptions!$B$42)/12 -> 34.901313 | AA30: =$Q30*(1+Assumptions!$B$42)/12 -> 34.901313 | AB30: =SUM(V30:AA30) -> 209.40788 | AC30: =AB30*12/6 -> 418.81576 | AD30: =IF(Q30=0,0,AC30/Q30-1) -> 0.1
B31: Software & Technology cost | C31: ='FY26 Actual'!D30+'FY26 Actual'!D24 -> 472.4 | D31: =IF($C$11=0,0,C31/$C$11) -> 0.012437798 | E31: =$C31*Assumptions!$B$23/12 -> 38.911027 | F31: =$C31*Assumptions!$B$23/12 -> 38.911027 | G31: =$C31*Assumptions!$B$23/12 -> 38.911027 | H31: =$C31*Assumptions!$B$23/12 -> 38.911027 | I31: =$C31*Assumptions!$B$23/12 -> 38.911027 | J31: =$C31*Assumptions!$B$23/12 -> 38.911027 | K31: =$C31*Assumptions!$B$23/12 -> 38.911027 | L31: =$C31*Assumptions!$B$23/12 -> 38.911027 | ... P31: =$C31*Assumptions!$B$23/12 -> 38.911027 | Q31: =SUM(E31:P31) -> 466.93232 | R31: =IF($Q$11=0,0,Q31/$Q$11) -> 0.010492861 | S31: =Q31-C31 -> -5.4676784 | T31: =IF(C31=0,0,S31/ABS(C31)) -> -0.011574256 | V31: =$Q31*(1+Assumptions!$B$42)/12 -> 42.802129 | W31: =$Q31*(1+Assumptions!$B$42)/12 -> 42.802129 | X31: =$Q31*(1+Assumptions!$B$42)/12 -> 42.802129 | Y31: =$Q31*(1+Assumptions!$B$42)/12 -> 42.802129 | Z31: =$Q31*(1+Assumptions!$B$42)/12 -> 42.802129 | AA31: =$Q31*(1+Assumptions!$B$42)/12 -> 42.802129 | AB31: =SUM(V31:AA31) -> 256.81278 | AC31: =AB31*12/6 -> 513.62555 | AD31: =IF(Q31=0,0,AC31/Q31-1) -> 0.1
B32: Other Establishment & Support O/H | C32: ='FY26 Actual'!D18+'FY26 Actual'!D19+'FY26 Actual'!D20+'FY26 Actual'!D21+'FY26 Actual'!D28+'FY26 Actual'!D29+'FY26 Actual'!D35+'FY26 Actual'!D36+'FY26 Actual'!D38 -> 1897.5 | D32: =IF($C$11=0,0,C32/$C$11) -> 0.04995919 | E32: =$C32*Assumptions!$B$23/12 -> 156.29482 | F32: =$C32*Assumptions!$B$23/12 -> 156.29482 | G32: =$C32*Assumptions!$B$23/12 -> 156.29482 | H32: =$C32*Assumptions!$B$23/12 -> 156.29482 | I32: =$C32*Assumptions!$B$23/12 -> 156.29482 | J32: =$C32*Assumptions!$B$23/12 -> 156.29482 | K32: =$C32*Assumptions!$B$23/12 -> 156.29482 | L32: =$C32*Assumptions!$B$23/12 -> 156.29482 | ... P32: =$C32*Assumptions!$B$23/12 -> 156.29482 | Q32: =SUM(E32:P32) -> 1875.5378 | R32: =IF($Q$11=0,0,Q32/$Q$11) -> 0.042146918 | S32: =Q32-C32 -> -21.96215 | T32: =IF(C32=0,0,S32/ABS(C32)) -> -0.011574256 | V32: =$Q32*(1+Assumptions!$B$42)/12 -> 171.9243 | W32: =$Q32*(1+Assumptions!$B$42)/12 -> 171.9243 | X32: =$Q32*(1+Assumptions!$B$42)/12 -> 171.9243 | Y32: =$Q32*(1+Assumptions!$B$42)/12 -> 171.9243 | Z32: =$Q32*(1+Assumptions!$B$42)/12 -> 171.9243 | AA32: =$Q32*(1+Assumptions!$B$42)/12 -> 171.9243 | AB32: =SUM(V32:AA32) -> 1031.5458 | AC32: =AB32*12/6 -> 2063.0916 | AD32: =IF(Q32=0,0,AC32/Q32-1) -> 0.1
B33: General & Administration Expenses | C33: =SUM(C26:C32) -> 5526.0066 | D33: =IF($C$11=0,0,C33/$C$11) -> 0.14549397 | E33: =SUM(E26:E32) -> 455.1706 | F33: =SUM(F26:F32) -> 455.1706 | G33: =SUM(G26:G32) -> 455.1706 | H33: =SUM(H26:H32) -> 455.1706 | I33: =SUM(I26:I32) -> 455.1706 | J33: =SUM(J26:J32) -> 455.1706 | K33: =SUM(K26:K32) -> 455.1706 | L33: =SUM(L26:L32) -> 455.1706 | ... Q33: =SUM(Q26:Q32) -> 5462.0472 | R33: =IF($Q$11=0,0,Q33/$Q$11) -> 0.12274263 | S33: =Q33-C33 -> -63.959414 | T33: =IF(C33=0,0,S33/ABS(C33)) -> -0.011574256 | V33: =SUM(V26:V32) -> 500.68766 | W33: =SUM(W26:W32) -> 500.68766 | X33: =SUM(X26:X32) -> 500.68766 | Y33: =SUM(Y26:Y32) -> 500.68766 | Z33: =SUM(Z26:Z32) -> 500.68766 | AA33: =SUM(AA26:AA32) -> 500.68766 | AB33: =SUM(AB26:AB32) -> 3004.126 | AC33: =AB33*12/6 -> 6008.2519 | AD33: =IF(Q33=0,0,AC33/Q33-1) -> 0.1
B34: % to gross revenue | C34: =IF(C11=0,0,C33/C11) -> 0.14549397 | E34: =IF(E11=0,0,E33/E11) -> 0.13729601 | F34: =IF(F11=0,0,F33/F11) -> 0.21177128 | G34: =IF(G11=0,0,G33/G11) -> 0.16313481 | H34: =IF(H11=0,0,H33/H11) -> 0.14345796 | I34: =IF(I11=0,0,I33/I11) -> 0.13529832 | J34: =IF(J11=0,0,J33/J11) -> 0.12737924 | K34: =IF(K11=0,0,K33/K11) -> 0.1192139 | L34: =IF(L11=0,0,L33/L11) -> 0.11784047 | ... Q34: =IF(Q11=0,0,Q33/Q11) -> 0.12274263 | V34: =IF(V11=0,0,V33/V11) -> 0.12274263 | W34: =IF(W11=0,0,W33/W11) -> 0.12274263 | X34: =IF(X11=0,0,X33/X11) -> 0.12274263 | Y34: =IF(Y11=0,0,Y33/Y11) -> 0.12274263 | Z34: =IF(Z11=0,0,Z33/Z11) -> 0.12274263 | AA34: =IF(AA11=0,0,AA33/AA11) -> 0.12274263 | AB34: =IF(AB11=0,0,AB33/AB11) -> 0.12274263 | AC34: =IF(AC11=0,0,AC33/AC11) -> 0.12274263
B36: Sales & Marketing Expenses
B37: Salaries - Sales & Marketing | C37: =('FY26 Actual'!D9+'FY26 Actual'!D10+'FY26 Actual'!D11)*Assumptions!$B$47 -> 1942.7206 | D37: =IF($C$11=0,0,C37/$C$11) -> 0.051149801 | E37: =$C37*Assumptions!$B$23/12 -> 160.01959 | F37: =$C37*Assumptions!$B$23/12 -> 160.01959 | G37: =$C37*Assumptions!$B$23/12 -> 160.01959 | H37: =$C37*Assumptions!$B$23/12 -> 160.01959 | I37: =$C37*Assumptions!$B$23/12 -> 160.01959 | J37: =$C37*Assumptions!$B$23/12 -> 160.01959 | K37: =$C37*Assumptions!$B$23/12 -> 160.01959 | L37: =$C37*Assumptions!$B$23/12 -> 160.01959 | ... P37: =$C37*Assumptions!$B$23/12 -> 160.01959 | Q37: =SUM(E37:P37) -> 1920.2351 | R37: =IF($Q$11=0,0,Q37/$Q$11) -> 0.04315135 | S37: =Q37-C37 -> -22.485545 | T37: =IF(C37=0,0,S37/ABS(C37)) -> -0.011574256 | V37: =$Q37*(1+Assumptions!$B$42)/12 -> 176.02155 | W37: =$Q37*(1+Assumptions!$B$42)/12 -> 176.02155 | X37: =$Q37*(1+Assumptions!$B$42)/12 -> 176.02155 | Y37: =$Q37*(1+Assumptions!$B$42)/12 -> 176.02155 | Z37: =$Q37*(1+Assumptions!$B$42)/12 -> 176.02155 | AA37: =$Q37*(1+Assumptions!$B$42)/12 -> 176.02155 | AB37: =SUM(V37:AA37) -> 1056.1293 | AC37: =AB37*12/6 -> 2112.2586 | AD37: =IF(Q37=0,0,AC37/Q37-1) -> 0.1
B38: Selling & Marketing exp (business promotion) | C38: ='FY26 Actual'!D25 -> 249.8 | D38: =IF($C$11=0,0,C38/$C$11) -> 0.0065769727 | E38: =$C38*Assumptions!$B$23/12 -> 20.575729 | F38: =$C38*Assumptions!$B$23/12 -> 20.575729 | G38: =$C38*Assumptions!$B$23/12 -> 20.575729 | H38: =$C38*Assumptions!$B$23/12 -> 20.575729 | I38: =$C38*Assumptions!$B$23/12 -> 20.575729 | J38: =$C38*Assumptions!$B$23/12 -> 20.575729 | K38: =$C38*Assumptions!$B$23/12 -> 20.575729 | L38: =$C38*Assumptions!$B$23/12 -> 20.575729 | ... P38: =$C38*Assumptions!$B$23/12 -> 20.575729 | Q38: =SUM(E38:P38) -> 246.90875 | R38: =IF($Q$11=0,0,Q38/$Q$11) -> 0.0055485113 | S38: =Q38-C38 -> -2.8912491 | T38: =IF(C38=0,0,S38/ABS(C38)) -> -0.011574256 | V38: =$Q38*(1+Assumptions!$B$42)/12 -> 22.633302 | W38: =$Q38*(1+Assumptions!$B$42)/12 -> 22.633302 | X38: =$Q38*(1+Assumptions!$B$42)/12 -> 22.633302 | Y38: =$Q38*(1+Assumptions!$B$42)/12 -> 22.633302 | Z38: =$Q38*(1+Assumptions!$B$42)/12 -> 22.633302 | AA38: =$Q38*(1+Assumptions!$B$42)/12 -> 22.633302 | AB38: =SUM(V38:AA38) -> 135.79981 | AC38: =AB38*12/6 -> 271.59963 | AD38: =IF(Q38=0,0,AC38/Q38-1) -> 0.1
B39: Travelling exp | C39: ='FY26 Actual'!D23*Assumptions!$B$50 -> 623.8128 | D39: =IF($C$11=0,0,C39/$C$11) -> 0.016424338 | E39: =$C39*Assumptions!$B$23/12 -> 51.382719 | F39: =$C39*Assumptions!$B$23/12 -> 51.382719 | G39: =$C39*Assumptions!$B$23/12 -> 51.382719 | H39: =$C39*Assumptions!$B$23/12 -> 51.382719 | I39: =$C39*Assumptions!$B$23/12 -> 51.382719 | J39: =$C39*Assumptions!$B$23/12 -> 51.382719 | K39: =$C39*Assumptions!$B$23/12 -> 51.382719 | L39: =$C39*Assumptions!$B$23/12 -> 51.382719 | ... P39: =$C39*Assumptions!$B$23/12 -> 51.382719 | Q39: =SUM(E39:P39) -> 616.59263 | R39: =IF($Q$11=0,0,Q39/$Q$11) -> 0.013856014 | S39: =Q39-C39 -> -7.2201689 | T39: =IF(C39=0,0,S39/ABS(C39)) -> -0.011574256 | V39: =$Q39*(1+Assumptions!$B$42)/12 -> 56.520991 | W39: =$Q39*(1+Assumptions!$B$42)/12 -> 56.520991 | X39: =$Q39*(1+Assumptions!$B$42)/12 -> 56.520991 | Y39: =$Q39*(1+Assumptions!$B$42)/12 -> 56.520991 | Z39: =$Q39*(1+Assumptions!$B$42)/12 -> 56.520991 | AA39: =$Q39*(1+Assumptions!$B$42)/12 -> 56.520991 | AB39: =SUM(V39:AA39) -> 339.12595 | AC39: =AB39*12/6 -> 678.25189 | AD39: =IF(Q39=0,0,AC39/Q39-1) -> 0.1
B40: Sales & Marketing Expenses | C40: =SUM(C37:C39) -> 2816.3334 | D40: =IF($C$11=0,0,C40/$C$11) -> 0.074151112 | E40: =SUM(E37:E39) -> 231.97804 | F40: =SUM(F37:F39) -> 231.97804 | G40: =SUM(G37:G39) -> 231.97804 | H40: =SUM(H37:H39) -> 231.97804 | I40: =SUM(I37:I39) -> 231.97804 | J40: =SUM(J37:J39) -> 231.97804 | K40: =SUM(K37:K39) -> 231.97804 | L40: =SUM(L37:L39) -> 231.97804 | ... Q40: =SUM(Q37:Q39) -> 2783.7364 | R40: =IF($Q$11=0,0,Q40/$Q$11) -> 0.062555875 | S40: =Q40-C40 -> -32.596963 | T40: =IF(C40=0,0,S40/ABS(C40)) -> -0.011574256 | V40: =SUM(V37:V39) -> 255.17584 | W40: =SUM(W37:W39) -> 255.17584 | X40: =SUM(X37:X39) -> 255.17584 | Y40: =SUM(Y37:Y39) -> 255.17584 | Z40: =SUM(Z37:Z39) -> 255.17584 | AA40: =SUM(AA37:AA39) -> 255.17584 | AB40: =SUM(AB37:AB39) -> 1531.055 | AC40: =AB40*12/6 -> 3062.1101 | AD40: =IF(Q40=0,0,AC40/Q40-1) -> 0.1
B41: % to gross revenue | C41: =IF(C11=0,0,C40/C11) -> 0.074151112 | E41: =IF(E11=0,0,E40/E11) -> 0.069973015 | F41: =IF(F11=0,0,F40/F11) -> 0.10792939 | G41: =IF(G11=0,0,G40/G11) -> 0.08314178 | H41: =IF(H11=0,0,H40/H11) -> 0.073113458 | I41: =IF(I11=0,0,I40/I11) -> 0.068954889 | J41: =IF(J11=0,0,J40/J11) -> 0.064918924 | K41: =IF(K11=0,0,K40/K11) -> 0.060757454 | L41: =IF(L11=0,0,L40/L11) -> 0.060057484 | ... Q41: =IF(Q11=0,0,Q40/Q11) -> 0.062555875 | V41: =IF(V11=0,0,V40/V11) -> 0.062555875 | W41: =IF(W11=0,0,W40/W11) -> 0.062555875 | X41: =IF(X11=0,0,X40/X11) -> 0.062555875 | Y41: =IF(Y11=0,0,Y40/Y11) -> 0.062555875 | Z41: =IF(Z11=0,0,Z40/Z11) -> 0.062555875 | AA41: =IF(AA11=0,0,AA40/AA11) -> 0.062555875 | AB41: =IF(AB11=0,0,AB40/AB11) -> 0.062555875 | AC41: =IF(AC11=0,0,AC40/AC11) -> 0.062555875
B43: EBITDA
B44: Total operating cost (CoR + G&A + S&M) | C44: =C21+C33+C40 -> 36952.7 | D44: =IF($C$11=0,0,C44/$C$11) -> 0.97292594 | E44: =E21+E33+E40 -> 3043.75 | F44: =F21+F33+F40 -> 3043.75 | G44: =G21+G33+G40 -> 3043.75 | H44: =H21+H33+H40 -> 3043.75 | I44: =I21+I33+I40 -> 3043.75 | J44: =J21+J33+J40 -> 3043.75 | K44: =K21+K33+K40 -> 3043.75 | L44: =L21+L33+L40 -> 3043.75 | ... Q44: =Q21+Q33+Q40 -> 36525 | R44: =IF($Q$11=0,0,Q44/$Q$11) -> 0.82078652 | S44: =Q44-C44 -> -427.7 | T44: =IF(C44=0,0,S44/ABS(C44)) -> -0.011574256 | V44: =V21+V33+V40 -> 3348.125 | W44: =W21+W33+W40 -> 3348.125 | X44: =X21+X33+X40 -> 3348.125 | Y44: =Y21+Y33+Y40 -> 3348.125 | Z44: =Z21+Z33+Z40 -> 3348.125 | AA44: =AA21+AA33+AA40 -> 3348.125 | AB44: =AB21+AB33+AB40 -> 20088.75 | AC44: =AB44*12/6 -> 40177.5 | AD44: =IF(Q44=0,0,AC44/Q44-1) -> 0.1
B45: EBITDA before w/off | C45: =C13-C44 -> 1028.3 | D45: =IF($C$11=0,0,C45/$C$11) -> 0.027074063 | E45: =E13-E44 -> 174.65 | F45: =F13-F44 -> -957.19 | G45: =G13-G44 -> -335.11 | H45: =H13-H44 -> 36.41 | I45: =I13-I44 -> 222.17 | J45: =J13-J44 -> 425.21 | K45: =K13-K44 -> 662.81 | L45: =L13-L44 -> 706.01 | ... Q45: =Q13-Q44 -> 6675 | R45: =IF($Q$11=0,0,Q45/$Q$11) -> 0.15 | S45: =Q45-C45 -> 5646.7 | T45: =IF(C45=0,0,S45/ABS(C45)) -> 5.4912963 | V45: =V13-V44 -> 611.875 | W45: =W13-W44 -> 611.875 | X45: =X13-X44 -> 611.875 | Y45: =Y13-Y44 -> 611.875 | Z45: =Z13-Z44 -> 611.875 | AA45: =AA13-AA44 -> 611.875 | AB45: =AB13-AB44 -> 3671.25 | AC45: =AB45*12/6 -> 7342.5 | AD45: =IF(Q45=0,0,AC45/Q45-1) -> 0.1
B46: EBITDA % (before w/off) – of gross revenue | C46: =IF(C11=0,0,C45/C11) -> 0.027074063 | E46: =IF(E11=0,0,E45/E11) -> 0.052680793 | F46: =IF(F11=0,0,F45/F11) -> -0.44533929 | G46: =IF(G11=0,0,G45/G11) -> -0.12010465 | H46: =IF(H11=0,0,H45/H11) -> 0.011475487 | I46: =IF(I11=0,0,I45/I11) -> 0.066039474 | J46: =IF(J11=0,0,J45/J11) -> 0.11899478 | K46: =IF(K11=0,0,K45/K11) -> 0.17359682 | L46: =IF(L11=0,0,L45/L11) -> 0.18278103 | ... Q46: =IF(Q11=0,0,Q45/Q11) -> 0.15 | V46: =IF(V11=0,0,V45/V11) -> 0.15 | W46: =IF(W11=0,0,W45/W11) -> 0.15 | X46: =IF(X11=0,0,X45/X11) -> 0.15 | Y46: =IF(Y11=0,0,Y45/Y11) -> 0.15 | Z46: =IF(Z11=0,0,Z45/Z11) -> 0.15 | AA46: =IF(AA11=0,0,AA45/AA11) -> 0.15 | AB46: =IF(AB11=0,0,AB45/AB11) -> 0.15 | AC46: =IF(AC11=0,0,AC45/AC11) -> 0.15
B47: ECL Provision, Bad debts & UBR write-off | C47: ='FY26 Actual'!D31+'FY26 Actual'!D32+'FY26 Actual'!D33+'FY26 Actual'!D34 -> 3647.3 | D47: =IF($C$11=0,0,C47/$C$11) -> 0.096029594 | E47: =Assumptions!$B$18/12 -> 111.25 | F47: =Assumptions!$B$18/12 -> 111.25 | G47: =Assumptions!$B$18/12 -> 111.25 | H47: =Assumptions!$B$18/12 -> 111.25 | I47: =Assumptions!$B$18/12 -> 111.25 | J47: =Assumptions!$B$18/12 -> 111.25 | K47: =Assumptions!$B$18/12 -> 111.25 | L47: =Assumptions!$B$18/12 -> 111.25 | ... P47: =Assumptions!$B$18/12 -> 111.25 | Q47: =SUM(E47:P47) -> 1335 | R47: =IF($Q$11=0,0,Q47/$Q$11) -> 0.03 | S47: =Q47-C47 -> -2312.3 | T47: =IF(C47=0,0,S47/ABS(C47)) -> -0.63397582 | V47: =$Q47*(1+Assumptions!$B$42)/12 -> 122.375 | W47: =$Q47*(1+Assumptions!$B$42)/12 -> 122.375 | X47: =$Q47*(1+Assumptions!$B$42)/12 -> 122.375 | Y47: =$Q47*(1+Assumptions!$B$42)/12 -> 122.375 | Z47: =$Q47*(1+Assumptions!$B$42)/12 -> 122.375 | AA47: =$Q47*(1+Assumptions!$B$42)/12 -> 122.375 | AB47: =SUM(V47:AA47) -> 734.25 | AC47: =AB47*12/6 -> 1468.5 | AD47: =IF(Q47=0,0,AC47/Q47-1) -> 0.1
B48: EBITDA after w/off | C48: =C45-C47 -> -2619 | D48: =IF($C$11=0,0,C48/$C$11) -> -0.06895553 | E48: =E45-E47 -> 63.4 | F48: =F45-F47 -> -1068.44 | G48: =G45-G47 -> -446.36 | H48: =H45-H47 -> -74.84 | I48: =I45-I47 -> 110.92 | J48: =J45-J47 -> 313.96 | K48: =K45-K47 -> 551.56 | L48: =L45-L47 -> 594.76 | ... Q48: =Q45-Q47 -> 5340 | R48: =IF($Q$11=0,0,Q48/$Q$11) -> 0.12 | S48: =Q48-C48 -> 7959 | T48: =IF(C48=0,0,S48/ABS(C48)) -> 3.0389462 | V48: =V45-V47 -> 489.5 | W48: =W45-W47 -> 489.5 | X48: =X45-X47 -> 489.5 | Y48: =Y45-Y47 -> 489.5 | Z48: =Z45-Z47 -> 489.5 | AA48: =AA45-AA47 -> 489.5 | AB48: =AB45-AB47 -> 2937 | AC48: =AB48*12/6 -> 5874 | AD48: =IF(Q48=0,0,AC48/Q48-1) -> 0.1
B49: EBITDA % (after w/off) – of gross revenue | C49: =IF(C11=0,0,C48/C11) -> -0.06895553 | E49: =IF(E11=0,0,E48/E11) -> 0.019123746 | F49: =IF(F11=0,0,F48/F11) -> -0.49709912 | G49: =IF(G11=0,0,G48/G11) -> -0.15997706 | H49: =IF(H11=0,0,H48/H11) -> -0.023587626 | I49: =IF(I11=0,0,I48/I11) -> 0.032970691 | J49: =IF(J11=0,0,J48/J11) -> 0.08786153 | K49: =IF(K11=0,0,K48/K11) -> 0.14445929 | L49: =IF(L11=0,0,L48/L11) -> 0.15397919 | ... Q49: =IF(Q11=0,0,Q48/Q11) -> 0.12 | V49: =IF(V11=0,0,V48/V11) -> 0.12 | W49: =IF(W11=0,0,W48/W11) -> 0.12 | X49: =IF(X11=0,0,X48/X11) -> 0.12 | Y49: =IF(Y11=0,0,Y48/Y11) -> 0.12 | Z49: =IF(Z11=0,0,Z48/Z11) -> 0.12 | AA49: =IF(AA11=0,0,AA48/AA11) -> 0.12 | AB49: =IF(AB11=0,0,AB48/AB11) -> 0.12 | AC49: =IF(AC11=0,0,AC48/AC11) -> 0.12
B50: Check: FY27 EBITDA vs 12% target (should be zero) | Q50: =ROUND(Q48-Assumptions!$B$16,2) -> 0
B52: Below EBITDA
B53: Other income | C53: ='FY26 Actual'!D8 -> 274.8 | D53: =IF($C$11=0,0,C53/$C$11) -> 0.0072351965 | E53: =Assumptions!$B$27/12 -> 22.9 | F53: =Assumptions!$B$27/12 -> 22.9 | G53: =Assumptions!$B$27/12 -> 22.9 | H53: =Assumptions!$B$27/12 -> 22.9 | I53: =Assumptions!$B$27/12 -> 22.9 | J53: =Assumptions!$B$27/12 -> 22.9 | K53: =Assumptions!$B$27/12 -> 22.9 | L53: =Assumptions!$B$27/12 -> 22.9 | ... P53: =Assumptions!$B$27/12 -> 22.9 | Q53: =SUM(E53:P53) -> 274.8 | R53: =IF($Q$11=0,0,Q53/$Q$11) -> 0.0061752809 | S53: =Q53-C53 -> 0 | T53: =IF(C53=0,0,S53/ABS(C53)) -> 0 | V53: =$Q53*(1+Assumptions!$B$42)/12 -> 25.19 | W53: =$Q53*(1+Assumptions!$B$42)/12 -> 25.19 | X53: =$Q53*(1+Assumptions!$B$42)/12 -> 25.19 | Y53: =$Q53*(1+Assumptions!$B$42)/12 -> 25.19 | Z53: =$Q53*(1+Assumptions!$B$42)/12 -> 25.19 | AA53: =$Q53*(1+Assumptions!$B$42)/12 -> 25.19 | AB53: =SUM(V53:AA53) -> 151.14 | AC53: =AB53*12/6 -> 302.28 | AD53: =IF(Q53=0,0,AC53/Q53-1) -> 0.1
B54: Depreciation & amortisation | C54: ='FY26 Actual'!D14 -> 1447 | D54: =IF($C$11=0,0,C54/$C$11) -> 0.038097996 | E54: =Assumptions!$B$28/12 -> 120.58333 | F54: =Assumptions!$B$28/12 -> 120.58333 | G54: =Assumptions!$B$28/12 -> 120.58333 | H54: =Assumptions!$B$28/12 -> 120.58333 | I54: =Assumptions!$B$28/12 -> 120.58333 | J54: =Assumptions!$B$28/12 -> 120.58333 | K54: =Assumptions!$B$28/12 -> 120.58333 | L54: =Assumptions!$B$28/12 -> 120.58333 | ... P54: =Assumptions!$B$28/12 -> 120.58333 | Q54: =SUM(E54:P54) -> 1447 | R54: =IF($Q$11=0,0,Q54/$Q$11) -> 0.032516854 | S54: =Q54-C54 -> 0 | T54: =IF(C54=0,0,S54/ABS(C54)) -> 0 | V54: =$Q54*(1+Assumptions!$B$42)/12 -> 132.64167 | W54: =$Q54*(1+Assumptions!$B$42)/12 -> 132.64167 | X54: =$Q54*(1+Assumptions!$B$42)/12 -> 132.64167 | Y54: =$Q54*(1+Assumptions!$B$42)/12 -> 132.64167 | Z54: =$Q54*(1+Assumptions!$B$42)/12 -> 132.64167 | AA54: =$Q54*(1+Assumptions!$B$42)/12 -> 132.64167 | AB54: =SUM(V54:AA54) -> 795.85 | AC54: =AB54*12/6 -> 1591.7 | AD54: =IF(Q54=0,0,AC54/Q54-1) -> 0.1
B55: Finance cost | C55: ='FY26 Actual'!D13 -> 272.2 | D55: =IF($C$11=0,0,C55/$C$11) -> 0.0071667413 | E55: =Assumptions!$B$29/12 -> 22.683333 | F55: =Assumptions!$B$29/12 -> 22.683333 | G55: =Assumptions!$B$29/12 -> 22.683333 | H55: =Assumptions!$B$29/12 -> 22.683333 | I55: =Assumptions!$B$29/12 -> 22.683333 | J55: =Assumptions!$B$29/12 -> 22.683333 | K55: =Assumptions!$B$29/12 -> 22.683333 | L55: =Assumptions!$B$29/12 -> 22.683333 | ... P55: =Assumptions!$B$29/12 -> 22.683333 | Q55: =SUM(E55:P55) -> 272.2 | R55: =IF($Q$11=0,0,Q55/$Q$11) -> 0.0061168539 | S55: =Q55-C55 -> 0 | T55: =IF(C55=0,0,S55/ABS(C55)) -> 0 | V55: =$Q55*(1+Assumptions!$B$42)/12 -> 24.951667 | W55: =$Q55*(1+Assumptions!$B$42)/12 -> 24.951667 | X55: =$Q55*(1+Assumptions!$B$42)/12 -> 24.951667 | Y55: =$Q55*(1+Assumptions!$B$42)/12 -> 24.951667 | Z55: =$Q55*(1+Assumptions!$B$42)/12 -> 24.951667 | AA55: =$Q55*(1+Assumptions!$B$42)/12 -> 24.951667 | AB55: =SUM(V55:AA55) -> 149.71 | AC55: =AB55*12/6 -> 299.42 | AD55: =IF(Q55=0,0,AC55/Q55-1) -> 0.1
B56: Share of loss of equity-accounted investee | C56: ='FY26 Actual'!D39 -> 264.2 | D56: =IF($C$11=0,0,C56/$C$11) -> 0.0069561096 | E56: =0 -> 0 | F56: =0 -> 0 | G56: =0 -> 0 | H56: =0 -> 0 | I56: =0 -> 0 | J56: =0 -> 0 | K56: =0 -> 0 | L56: =0 -> 0 | ... P56: =0 -> 0 | Q56: =SUM(E56:P56) -> 0 | R56: =IF($Q$11=0,0,Q56/$Q$11) -> 0 | S56: =Q56-C56 -> -264.2 | T56: =IF(C56=0,0,S56/ABS(C56)) -> -1 | V56: =0 -> 0 | W56: =0 -> 0 | X56: =0 -> 0 | Y56: =0 -> 0 | Z56: =0 -> 0 | AA56: =0 -> 0 | AB56: =SUM(V56:AA56) -> 0 | AC56: =AB56*12/6 -> 0 | AD56: =IF(Q56=0,0,AC56/Q56-1) -> 0
B57: Profit / (Loss) before tax | C57: =C48+C53-C54-C55-C56 -> -4327.6 | D57: =IF($C$11=0,0,C57/$C$11) -> -0.11394118 | E57: =E48+E53-E54-E55-E56 -> -56.966667 | F57: =F48+F53-F54-F55-F56 -> -1188.8067 | G57: =G48+G53-G54-G55-G56 -> -566.72667 | H57: =H48+H53-H54-H55-H56 -> -195.20667 | I57: =I48+I53-I54-I55-I56 -> -9.4466667 | J57: =J48+J53-J54-J55-J56 -> 193.59333 | K57: =K48+K53-K54-K55-K56 -> 431.19333 | L57: =L48+L53-L54-L55-L56 -> 474.39333 | ... Q57: =Q48+Q53-Q54-Q55-Q56 -> 3895.6 | R57: =IF($Q$11=0,0,Q57/$Q$11) -> 0.087541573 | S57: =Q57-C57 -> 8223.2 | T57: =IF(C57=0,0,S57/ABS(C57)) -> 1.9001756 | V57: =V48+V53-V54-V55-V56 -> 357.09667 | W57: =W48+W53-W54-W55-W56 -> 357.09667 | X57: =X48+X53-X54-X55-X56 -> 357.09667 | Y57: =Y48+Y53-Y54-Y55-Y56 -> 357.09667 | Z57: =Z48+Z53-Z54-Z55-Z56 -> 357.09667 | AA57: =AA48+AA53-AA54-AA55-AA56 -> 357.09667 | AB57: =AB48+AB53-AB54-AB55-AB56 -> 2142.58 | AC57: =AB57*12/6 -> 4285.16 | AD57: =IF(Q57=0,0,AC57/Q57-1) -> 0.1
B58: Tax expense / (credit) | C58: ='FY26 Actual'!D40 -> -976 | D58: =IF($C$11=0,0,C58/$C$11) -> -0.025697059 | E58: =MAX(0,$Q$57)*Assumptions!$B$30/12 -> 81.71021 | F58: =MAX(0,$Q$57)*Assumptions!$B$30/12 -> 81.71021 | G58: =MAX(0,$Q$57)*Assumptions!$B$30/12 -> 81.71021 | H58: =MAX(0,$Q$57)*Assumptions!$B$30/12 -> 81.71021 | I58: =MAX(0,$Q$57)*Assumptions!$B$30/12 -> 81.71021 | J58: =MAX(0,$Q$57)*Assumptions!$B$30/12 -> 81.71021 | K58: =MAX(0,$Q$57)*Assumptions!$B$30/12 -> 81.71021 | L58: =MAX(0,$Q$57)*Assumptions!$B$30/12 -> 81.71021 | ... P58: =MAX(0,$Q$57)*Assumptions!$B$30/12 -> 81.71021 | Q58: =SUM(E58:P58) -> 980.52252 | R58: =IF($Q$11=0,0,Q58/$Q$11) -> 0.022034214 | S58: =Q58-C58 -> 1956.5225 | T58: =IF(C58=0,0,S58/ABS(C58)) -> 2.0046337 | V58: =MAX(0,V57)*Assumptions!$B$30 -> 89.881231 | W58: =MAX(0,W57)*Assumptions!$B$30 -> 89.881231 | X58: =MAX(0,X57)*Assumptions!$B$30 -> 89.881231 | Y58: =MAX(0,Y57)*Assumptions!$B$30 -> 89.881231 | Z58: =MAX(0,Z57)*Assumptions!$B$30 -> 89.881231 | AA58: =MAX(0,AA57)*Assumptions!$B$30 -> 89.881231 | AB58: =SUM(V58:AA58) -> 539.28739 | AC58: =AB58*12/6 -> 1078.5748 | AD58: =IF(Q58=0,0,AC58/Q58-1) -> 0.1
B59: Profit / (Loss) after tax | C59: =C57-C58 -> -3351.6 | D59: =IF($C$11=0,0,C59/$C$11) -> -0.088244122 | E59: =E57-E58 -> -138.67688 | F59: =F57-F58 -> -1270.5169 | G59: =G57-G58 -> -648.43688 | H59: =H57-H58 -> -276.91688 | I59: =I57-I58 -> -91.156877 | J59: =J57-J58 -> 111.88312 | K59: =K57-K58 -> 349.48312 | L59: =L57-L58 -> 392.68312 | ... Q59: =Q57-Q58 -> 2915.0775 | R59: =IF($Q$11=0,0,Q59/$Q$11) -> 0.065507359 | S59: =Q59-C59 -> 6266.6775 | T59: =IF(C59=0,0,S59/ABS(C59)) -> 1.869757 | V59: =V57-V58 -> 267.21544 | W59: =W57-W58 -> 267.21544 | X59: =X57-X58 -> 267.21544 | Y59: =Y57-Y58 -> 267.21544 | Z59: =Z57-Z58 -> 267.21544 | AA59: =AA57-AA58 -> 267.21544 | AB59: =AB57-AB58 -> 1603.2926 | AC59: =AB59*12/6 -> 3206.5852 | AD59: =IF(Q59=0,0,AC59/Q59-1) -> 0.1
B60: PAT % of gross revenue | C60: =IF(C11=0,0,C59/C11) -> -0.088244122 | E60: =IF(E11=0,0,E59/E11) -> -0.041829991 | F60: =IF(F11=0,0,F59/F11) -> -0.59111679 | G60: =IF(G11=0,0,G59/G11) -> -0.23240216 | H60: =IF(H11=0,0,H59/H11) -> -0.087277015 | I60: =IF(I11=0,0,I59/I11) -> -0.027096153 | J60: =IF(J11=0,0,J59/J11) -> 0.03131043 | K60: =IF(K11=0,0,K59/K11) -> 0.091533256 | L60: =IF(L11=0,0,L59/L11) -> 0.1016629 | ... Q60: =IF(Q11=0,0,Q59/Q11) -> 0.065507359 | V60: =IF(V11=0,0,V59/V11) -> 0.065507359 | W60: =IF(W11=0,0,W59/W11) -> 0.065507359 | X60: =IF(X11=0,0,X59/X11) -> 0.065507359 | Y60: =IF(Y11=0,0,Y59/Y11) -> 0.065507359 | Z60: =IF(Z11=0,0,Z59/Z11) -> 0.065507359 | AA60: =IF(AA11=0,0,AA59/AA11) -> 0.065507359 | AB60: =IF(AB11=0,0,AB59/AB11) -> 0.065507359 | AC60: =IF(AC11=0,0,AC59/AC11) -> 0.065507359
B62: Reconciliation checks
B63: FY26 PBT vs audited FS (INR (4,327.8) lakhs) – difference | C63: =ROUND(C57-'FY26 Actual'!D44,2) -> 0
B64: FY27 net revenue vs budget input – difference | Q64: =ROUND(Q13-Assumptions!$B$8,2) -> 0
B65: Apr-Sep 27 gross revenue vs FY27 × 110% × 6/12 – difference | AB65: =ROUND(AB11-Q11*(1+Assumptions!$B$42)/2,2) -> 0
B67: Notes:
B68: 1. FY 2025-26 actuals are the audited consolidated numbers mapped to MIS heads; salaries and travel are allocated using the keys in Assumptions (section G).
B69: 2. FY 2026-27: gross revenue INR 44,500 lakhs and net revenue INR 43,200 lakhs; the INR 1,300 lakhs difference is channel partner cost.
B70: 3. Every FY27 operating cost line = FY26 actual × the cost adjustment factor (Assumptions B23), so that EBITDA after ECL/write-offs = 12% of gross revenue.
B71: 4. Revenue is phased by month using the seasonality in Assumptions row 58; operating costs and ECL are spread evenly over the months.
B72: 5. Apr-27 to Sep-27: each month = FY27 annual × 110% / 12 (a 10% increase on an annualised basis). Tax is at 25.17% on positive PBT.

Sheet Working Capital
A1: Infrasoft Technologies Limited (Kiya.ai) – Consolidated
A2: Projected Working Capital – Days Basis
A3: Going concern assessment for the year ended 31 March 2026 | All amounts in INR Lakhs unless stated
A5: Particulars | B5: 31-Mar-26 Actual | C5: FY26 Actual Days / % | D5: Target Days / % | E5: Basis amount FY27 | F5: 31-Mar-27 Budget | G5: Change FY27 (cash impact) | H5: Monthly impact Apr-26 to Mar-27 | I5: Basis amount FY28 (annualised) | J5: 30-Sep-27 Projected | K5: Change Apr-Sep 27 (cash impact) | L5: Monthly impact Apr-27 to Sep-27
A7: Basis amounts
A8: Net revenue | B8: ='Global PNL'!C13 -> 37981 | E8: ='Global PNL'!Q13 -> 43200 | I8: ='Global PNL'!AC13 -> 47520
A9: Non-salary costs (opex excl. salaries & welfare + channel partner cost) | B9: ='Global PNL'!C44-'Global PNL'!C16-'Global PNL'!C26-'Global PNL'!C27-'Global PNL'!C37+'Global PNL'!C12 -> 12261 | E9: ='Global PNL'!Q44-'Global PNL'!Q16-'Global PNL'!Q26-'Global PNL'!Q27-'Global PNL'!Q37+'Global PNL'!Q12 -> 13419.088 | I9: ='Global PNL'!AC44-'Global PNL'!AC16-'Global PNL'!AC26-'Global PNL'!AC27-'Global PNL'!AC37+'Global PNL'!AC12 -> 14760.997
A11: Working capital items
A12: Trade receivables | B12: ='FY26 Actual'!D48 -> 15991 | C12: =IF(B8=0,0,B12/B8*365) -> 153.6746 | D12: =Assumptions!$B$35 -> 140 | E12: =E8 -> 43200 | F12: =E8*D12/365 -> 16569.863 | G12: =B12-F12 -> -578.86301 | H12: =G12/12 -> -48.238584 | I12: =I8 -> 47520 | J12: =I8*D12/365 -> 18226.849 | K12: =F12-J12 -> -1656.9863 | L12: =K12/6 -> -276.16438
A13: Unbilled revenue (contract assets) | B13: ='FY26 Actual'!D49 -> 12924.9 | C13: =IF(B8=0,0,B13/B8*365) -> 124.20917 | D13: =Assumptions!$B$36 -> 115 | E13: =E8 -> 43200 | F13: =E8*D13/365 -> 13610.959 | G13: =B13-F13 -> -686.0589 | H13: =G13/12 -> -57.171575 | I13: =I8 -> 47520 | J13: =I8*D13/365 -> 14972.055 | K13: =F13-J13 -> -1361.0959 | L13: =K13/6 -> -226.84932
A14: Unearned revenue (contract liability) | B14: ='FY26 Actual'!D50 -> 3878.1 | C14: =IF(B8=0,0,B14/B8) -> 0.10210632 | D14: =Assumptions!$B$37 -> 0.1 | E14: =E8 -> 43200 | F14: =E8*D14 -> 4320 | G14: =F14-B14 -> 441.9 | H14: =G14/12 -> 36.825 | I14: =I8 -> 47520 | J14: =I8*D14 -> 4752 | K14: =J14-F14 -> 432 | L14: =K14/6 -> 72
A15: Trade payables | B15: ='FY26 Actual'!D51 -> 3445.2 | C15: =IF(B9=0,0,B15/B9*365) -> 102.5608 | D15: =Assumptions!$B$38 -> 95 | E15: =E9 -> 13419.088 | F15: =E9*D15/365 -> 3492.6394 | G15: =F15-B15 -> 47.439356 | H15: =G15/12 -> 3.9532796 | I15: =I9 -> 14760.997 | J15: =I9*D15/365 -> 3841.9033 | K15: =J15-F15 -> 349.26394 | L15: =K15/6 -> 58.210656
A16: Net working capital cash impact | G16: =SUM(G12:G15) -> -775.58256 | H16: =SUM(H12:H15) -> -64.63188 | K16: =SUM(K12:K15) -> -2236.8183 | L16: =SUM(L12:L15) -> -372.80304
A18: Positive = cash inflow; negative = cash outflow. The change in each balance is spread evenly across the months (consistent with the prior-year working). Balances at 30-Sep-27 are based on annualised Apr-Sep 27 volumes.

Sheet Global Cashflow
A1: Infrasoft Technologies Limited (Kiya.ai) – Consolidated
A2: Month-on-Month Cash Flow – April 2026 to September 2027 (12 months from date of approval of FS: 25-Sep-2026)
A3: Going concern assessment for the year ended 31 March 2026 | All amounts in INR Lakhs unless stated
B5: INR Lakhs | C5: 46113 | D5: 46143 | E5: 46174 | F5: 46204 | G5: 46235 | H5: 46266 | I5: 46296 | J5: 46327 | K5: 46357 | L5: 46388 | M5: 46419 | N5: 46447 | O5: FY 2026-27 | P5: 46478 | Q5: 46508 | R5: 46539 | S5: 46569 | T5: 46600 | U5: 46631 | V5: Apr-Sep 27 | W5: 18 months
B6: Opening cash and cash equivalents | C6: =Assumptions!$B$39 -> 4324.9 | D6: =C28 -> 4156.2412 | E6: =D28 -> 2855.7425 | F6: =E28 -> 2177.3237 | G6: =F28 -> 1870.425 | H6: =G28 -> 1749.2862 | I6: =H28 -> 1831.1875 | J6: =I28 -> 2150.6887 | K6: =J28 -> 2513.3899 | ... N6: =M28 -> 5394.2937 | O6: =C6 -> 4324.9 | P6: =O28 -> 6880.1949 | Q6: =P28 -> 6821.084 | R6: =Q28 -> 6761.973 | S6: =R28 -> 6702.8621 | T6: =S28 -> 6643.7512 | U6: =T28 -> 6584.6402 | V6: =P6 -> 6880.1949 | W6: =C6 -> 4324.9
B7: Add: EBITDA (after ECL / write-offs) | C7: ='Global PNL'!E48 -> 63.4 | D7: ='Global PNL'!F48 -> -1068.44 | E7: ='Global PNL'!G48 -> -446.36 | F7: ='Global PNL'!H48 -> -74.84 | G7: ='Global PNL'!I48 -> 110.92 | H7: ='Global PNL'!J48 -> 313.96 | I7: ='Global PNL'!K48 -> 551.56 | J7: ='Global PNL'!L48 -> 594.76 | ... N7: ='Global PNL'!P48 -> 1717.96 | O7: =SUM(C7:N7) -> 5340 | P7: ='Global PNL'!V48 -> 489.5 | Q7: ='Global PNL'!W48 -> 489.5 | R7: ='Global PNL'!X48 -> 489.5 | S7: ='Global PNL'!Y48 -> 489.5 | T7: ='Global PNL'!Z48 -> 489.5 | U7: ='Global PNL'!AA48 -> 489.5 | V7: =SUM(P7:U7) -> 2937 | W7: =O7+V7 -> 8277
B8: Add: Other income | C8: ='Global PNL'!E53 -> 22.9 | D8: ='Global PNL'!F53 -> 22.9 | E8: ='Global PNL'!G53 -> 22.9 | F8: ='Global PNL'!H53 -> 22.9 | G8: ='Global PNL'!I53 -> 22.9 | H8: ='Global PNL'!J53 -> 22.9 | I8: ='Global PNL'!K53 -> 22.9 | J8: ='Global PNL'!L53 -> 22.9 | ... N8: ='Global PNL'!P53 -> 22.9 | O8: =SUM(C8:N8) -> 274.8 | P8: ='Global PNL'!V53 -> 25.19 | Q8: ='Global PNL'!W53 -> 25.19 | R8: ='Global PNL'!X53 -> 25.19 | S8: ='Global PNL'!Y53 -> 25.19 | T8: ='Global PNL'!Z53 -> 25.19 | U8: ='Global PNL'!AA53 -> 25.19 | V8: =SUM(P8:U8) -> 151.14 | W8: =O8+V8 -> 425.94
B9: Adjustments for changes in working capital
B10: (Increase) / decrease in Trade receivables | C10: ='Working Capital'!$H$12 -> -48.238584 | D10: ='Working Capital'!$H$12 -> -48.238584 | E10: ='Working Capital'!$H$12 -> -48.238584 | F10: ='Working Capital'!$H$12 -> -48.238584 | G10: ='Working Capital'!$H$12 -> -48.238584 | H10: ='Working Capital'!$H$12 -> -48.238584 | I10: ='Working Capital'!$H$12 -> -48.238584 | J10: ='Working Capital'!$H$12 -> -48.238584 | ... N10: ='Working Capital'!$H$12 -> -48.238584 | O10: =SUM(C10:N10) -> -578.86301 | P10: ='Working Capital'!$L$12 -> -276.16438 | Q10: ='Working Capital'!$L$12 -> -276.16438 | R10: ='Working Capital'!$L$12 -> -276.16438 | S10: ='Working Capital'!$L$12 -> -276.16438 | T10: ='Working Capital'!$L$12 -> -276.16438 | U10: ='Working Capital'!$L$12 -> -276.16438 | V10: =SUM(P10:U10) -> -1656.9863 | W10: =O10+V10 -> -2235.8493
B11: (Increase) / decrease in Unbilled revenue | C11: ='Working Capital'!$H$13 -> -57.171575 | D11: ='Working Capital'!$H$13 -> -57.171575 | E11: ='Working Capital'!$H$13 -> -57.171575 | F11: ='Working Capital'!$H$13 -> -57.171575 | G11: ='Working Capital'!$H$13 -> -57.171575 | H11: ='Working Capital'!$H$13 -> -57.171575 | I11: ='Working Capital'!$H$13 -> -57.171575 | J11: ='Working Capital'!$H$13 -> -57.171575 | ... N11: ='Working Capital'!$H$13 -> -57.171575 | O11: =SUM(C11:N11) -> -686.0589 | P11: ='Working Capital'!$L$13 -> -226.84932 | Q11: ='Working Capital'!$L$13 -> -226.84932 | R11: ='Working Capital'!$L$13 -> -226.84932 | S11: ='Working Capital'!$L$13 -> -226.84932 | T11: ='Working Capital'!$L$13 -> -226.84932 | U11: ='Working Capital'!$L$13 -> -226.84932 | V11: =SUM(P11:U11) -> -1361.0959 | W11: =O11+V11 -> -2047.1548
B12: Increase / (decrease) in Unearned revenue | C12: ='Working Capital'!$H$14 -> 36.825 | D12: ='Working Capital'!$H$14 -> 36.825 | E12: ='Working Capital'!$H$14 -> 36.825 | F12: ='Working Capital'!$H$14 -> 36.825 | G12: ='Working Capital'!$H$14 -> 36.825 | H12: ='Working Capital'!$H$14 -> 36.825 | I12: ='Working Capital'!$H$14 -> 36.825 | J12: ='Working Capital'!$H$14 -> 36.825 | ... N12: ='Working Capital'!$H$14 -> 36.825 | O12: =SUM(C12:N12) -> 441.9 | P12: ='Working Capital'!$L$14 -> 72 | Q12: ='Working Capital'!$L$14 -> 72 | R12: ='Working Capital'!$L$14 -> 72 | S12: ='Working Capital'!$L$14 -> 72 | T12: ='Working Capital'!$L$14 -> 72 | U12: ='Working Capital'!$L$14 -> 72 | V12: =SUM(P12:U12) -> 432 | W12: =O12+V12 -> 873.9
B13: Increase / (decrease) in Trade payables | C13: ='Working Capital'!$H$15 -> 3.9532796 | D13: ='Working Capital'!$H$15 -> 3.9532796 | E13: ='Working Capital'!$H$15 -> 3.9532796 | F13: ='Working Capital'!$H$15 -> 3.9532796 | G13: ='Working Capital'!$H$15 -> 3.9532796 | H13: ='Working Capital'!$H$15 -> 3.9532796 | I13: ='Working Capital'!$H$15 -> 3.9532796 | J13: ='Working Capital'!$H$15 -> 3.9532796 | ... N13: ='Working Capital'!$H$15 -> 3.9532796 | O13: =SUM(C13:N13) -> 47.439356 | P13: ='Working Capital'!$L$15 -> 58.210656 | Q13: ='Working Capital'!$L$15 -> 58.210656 | R13: ='Working Capital'!$L$15 -> 58.210656 | S13: ='Working Capital'!$L$15 -> 58.210656 | T13: ='Working Capital'!$L$15 -> 58.210656 | U13: ='Working Capital'!$L$15 -> 58.210656 | V13: =SUM(P13:U13) -> 349.26394 | W13: =O13+V13 -> 396.70329
B14: Net cash generated from operations | C14: =SUM(C7:C13) -> 21.66812 | D14: =SUM(D7:D13) -> -1110.1719 | E14: =SUM(E7:E13) -> -488.09188 | F14: =SUM(F7:F13) -> -116.57188 | G14: =SUM(G7:G13) -> 69.18812 | H14: =SUM(H7:H13) -> 272.22812 | I14: =SUM(I7:I13) -> 509.82812 | J14: =SUM(J7:J13) -> 553.02812 | ... N14: =SUM(N7:N13) -> 1676.2281 | O14: =SUM(C14:N14) -> 4839.2174 | P14: =SUM(P7:P13) -> 141.88696 | Q14: =SUM(Q7:Q13) -> 141.88696 | R14: =SUM(R7:R13) -> 141.88696 | S14: =SUM(S7:S13) -> 141.88696 | T14: =SUM(T7:T13) -> 141.88696 | U14: =SUM(U7:U13) -> 141.88696 | V14: =SUM(P14:U14) -> 851.32174 | W14: =O14+V14 -> 5690.5392
B15: Less: Income taxes paid | C15: =-'Global PNL'!E58 -> -81.71021 | D15: =-'Global PNL'!F58 -> -81.71021 | E15: =-'Global PNL'!G58 -> -81.71021 | F15: =-'Global PNL'!H58 -> -81.71021 | G15: =-'Global PNL'!I58 -> -81.71021 | H15: =-'Global PNL'!J58 -> -81.71021 | I15: =-'Global PNL'!K58 -> -81.71021 | J15: =-'Global PNL'!L58 -> -81.71021 | ... N15: =-'Global PNL'!P58 -> -81.71021 | O15: =SUM(C15:N15) -> -980.52252 | P15: =-'Global PNL'!V58 -> -89.881231 | Q15: =-'Global PNL'!W58 -> -89.881231 | R15: =-'Global PNL'!X58 -> -89.881231 | S15: =-'Global PNL'!Y58 -> -89.881231 | T15: =-'Global PNL'!Z58 -> -89.881231 | U15: =-'Global PNL'!AA58 -> -89.881231 | V15: =SUM(P15:U15) -> -539.28739 | W15: =O15+V15 -> -1519.8099
B16: Cash inflow / (outflow) from operating activities [A] | C16: =C14+C15 -> -60.04209 | D16: =D14+D15 -> -1191.8821 | E16: =E14+E15 -> -569.80209 | F16: =F14+F15 -> -198.28209 | G16: =G14+G15 -> -12.52209 | H16: =H14+H15 -> 190.51791 | I16: =I14+I15 -> 428.11791 | J16: =J14+J15 -> 471.31791 | ... N16: =N14+N15 -> 1594.5179 | O16: =SUM(C16:N16) -> 3858.6949 | P16: =P14+P15 -> 52.005726 | Q16: =Q14+Q15 -> 52.005726 | R16: =R14+R15 -> 52.005726 | S16: =S14+S15 -> 52.005726 | T16: =T14+T15 -> 52.005726 | U16: =U14+U15 -> 52.005726 | V16: =SUM(P16:U16) -> 312.03436 | W16: =O16+V16 -> 4170.7293
B18: Less: Capital expenditure | C18: =-Assumptions!$B$33/12 -> -25 | D18: =-Assumptions!$B$33/12 -> -25 | E18: =-Assumptions!$B$33/12 -> -25 | F18: =-Assumptions!$B$33/12 -> -25 | G18: =-Assumptions!$B$33/12 -> -25 | H18: =-Assumptions!$B$33/12 -> -25 | I18: =-Assumptions!$B$33/12 -> -25 | J18: =-Assumptions!$B$33/12 -> -25 | ... N18: =-Assumptions!$B$33/12 -> -25 | O18: =SUM(C18:N18) -> -300 | P18: =-Assumptions!$B$33*(1+Assumptions!$B$42)/12 -> -27.5 | Q18: =-Assumptions!$B$33*(1+Assumptions!$B$42)/12 -> -27.5 | R18: =-Assumptions!$B$33*(1+Assumptions!$B$42)/12 -> -27.5 | S18: =-Assumptions!$B$33*(1+Assumptions!$B$42)/12 -> -27.5 | T18: =-Assumptions!$B$33*(1+Assumptions!$B$42)/12 -> -27.5 | U18: =-Assumptions!$B$33*(1+Assumptions!$B$42)/12 -> -27.5 | V18: =SUM(P18:U18) -> -165 | W18: =O18+V18 -> -465
B19: Cash inflow / (outflow) from investing activities [B] | C19: =C18 -> -25 | D19: =D18 -> -25 | E19: =E18 -> -25 | F19: =F18 -> -25 | G19: =G18 -> -25 | H19: =H18 -> -25 | I19: =I18 -> -25 | J19: =J18 -> -25 | ... N19: =N18 -> -25 | O19: =SUM(C19:N19) -> -300 | P19: =P18 -> -27.5 | Q19: =Q18 -> -27.5 | R19: =R18 -> -27.5 | S19: =S18 -> -27.5 | T19: =T18 -> -27.5 | U19: =U18 -> -27.5 | V19: =SUM(P19:U19) -> -165 | W19: =O19+V19 -> -465
B21: Less: Lease payments (principal + interest) | C21: =-Assumptions!$B$34/12 -> -83.616667 | D21: =-Assumptions!$B$34/12 -> -83.616667 | E21: =-Assumptions!$B$34/12 -> -83.616667 | F21: =-Assumptions!$B$34/12 -> -83.616667 | G21: =-Assumptions!$B$34/12 -> -83.616667 | H21: =-Assumptions!$B$34/12 -> -83.616667 | I21: =-Assumptions!$B$34/12 -> -83.616667 | J21: =-Assumptions!$B$34/12 -> -83.616667 | ... N21: =-Assumptions!$B$34/12 -> -83.616667 | O21: =SUM(C21:N21) -> -1003.4 | P21: =-Assumptions!$B$34/12 -> -83.616667 | Q21: =-Assumptions!$B$34/12 -> -83.616667 | R21: =-Assumptions!$B$34/12 -> -83.616667 | S21: =-Assumptions!$B$34/12 -> -83.616667 | T21: =-Assumptions!$B$34/12 -> -83.616667 | U21: =-Assumptions!$B$34/12 -> -83.616667 | V21: =SUM(P21:U21) -> -501.7 | W21: =O21+V21 -> -1505.1
B22: Less: Dividend paid | C22: =0 -> 0 | D22: =0 -> 0 | E22: =0 -> 0 | F22: =0 -> 0 | G22: =0 -> 0 | H22: =0 -> 0 | I22: =0 -> 0 | J22: =0 -> 0 | ... N22: =0 -> 0 | O22: =SUM(C22:N22) -> 0 | P22: =0 -> 0 | Q22: =0 -> 0 | R22: =0 -> 0 | S22: =0 -> 0 | T22: =0 -> 0 | U22: =0 -> 0 | V22: =SUM(P22:U22) -> 0 | W22: =O22+V22 -> 0
B23: Cash inflow / (outflow) from financing activities [C] | C23: =C21+C22 -> -83.616667 | D23: =D21+D22 -> -83.616667 | E23: =E21+E22 -> -83.616667 | F23: =F21+F22 -> -83.616667 | G23: =G21+G22 -> -83.616667 | H23: =H21+H22 -> -83.616667 | I23: =I21+I22 -> -83.616667 | J23: =J21+J22 -> -83.616667 | ... N23: =N21+N22 -> -83.616667 | O23: =SUM(C23:N23) -> -1003.4 | P23: =P21+P22 -> -83.616667 | Q23: =Q21+Q22 -> -83.616667 | R23: =R21+R22 -> -83.616667 | S23: =S21+S22 -> -83.616667 | T23: =T21+T22 -> -83.616667 | U23: =U21+U22 -> -83.616667 | V23: =SUM(P23:U23) -> -501.7 | W23: =O23+V23 -> -1505.1
B25: Net cash inflow / (outflow) for the month [A + B + C] | C25: =C16+C19+C23 -> -168.65876 | D25: =D16+D19+D23 -> -1300.4988 | E25: =E16+E19+E23 -> -678.41876 | F25: =F16+F19+F23 -> -306.89876 | G25: =G16+G19+G23 -> -121.13876 | H25: =H16+H19+H23 -> 81.901243 | I25: =I16+I19+I23 -> 319.50124 | J25: =J16+J19+J23 -> 362.70124 | ... N25: =N16+N19+N23 -> 1485.9012 | O25: =SUM(C25:N25) -> 2555.2949 | P25: =P16+P19+P23 -> -59.11094 | Q25: =Q16+Q19+Q23 -> -59.11094 | R25: =R16+R19+R23 -> -59.11094 | S25: =S16+S19+S23 -> -59.11094 | T25: =T16+T19+T23 -> -59.11094 | U25: =U16+U19+U23 -> -59.11094 | V25: =SUM(P25:U25) -> -354.66564 | W25: =O25+V25 -> 2200.6293
B28: Closing cash and cash equivalents | C28: =C6+C25 -> 4156.2412 | D28: =D6+D25 -> 2855.7425 | E28: =E6+E25 -> 2177.3237 | F28: =F6+F25 -> 1870.425 | G28: =G6+G25 -> 1749.2862 | H28: =H6+H25 -> 1831.1875 | I28: =I6+I25 -> 2150.6887 | J28: =J6+J25 -> 2513.3899 | ... N28: =N6+N25 -> 6880.1949 | O28: =N28 -> 6880.1949 | P28: =P6+P25 -> 6821.084 | Q28: =Q6+Q25 -> 6761.973 | R28: =R6+R25 -> 6702.8621 | S28: =S6+S25 -> 6643.7512 | T28: =T6+T25 -> 6584.6402 | U28: =U6+U25 -> 6525.5293 | V28: =U28 -> 6525.5293 | W28: =U28 -> 6525.5293
B30: Key going-concern indicators
B31: Minimum month-end cash balance over 18 months | C31: =MIN(C28:U28) -> 1749.2862
B32: Month of minimum cash balance | C32: =INDEX(C5:U5,MATCH(C31,C28:U28,0)) -> 46235
B33: Number of months with negative closing cash | C33: =COUNTIF(C28:U28,"<0") -> 0
B34: Average monthly cash outflow (opex + ECL + lease + tax, FY27) | C34: =('Global PNL'!Q44+'Global PNL'!Q47+Assumptions!$B$34+'Global PNL'!Q58+'Global PNL'!Q12)/12 -> 3428.6602
B35: Cash cover at 31-Mar-26 (months of outflows) | C35: =IF(C34=0,0,Assumptions!$B$39/C34) -> 1.2613965
B36: Net cash generated over 18 months | C36: =W25 -> 2200.6293
B38: Note: Opening cash excludes lien-marked fixed deposits and current investments (INR 1,470 lakhs at 31-Mar-26), which provide additional headroom. Undrawn overdraft limits are not considered.

Sheet Sensitivity
A1: Infrasoft Technologies Limited (Kiya.ai) – Consolidated
A2: Sensitivity Analysis – FY 2026-27
A3: Going concern assessment for the year ended 31 March 2026 | All amounts in INR Lakhs unless stated
A5: Particulars | B5: Base Budget | C5: Revenue decline | D5: Cost increase | E5: Combined stress
A6: Stress applied | B6: - | C6: =Assumptions!$B$53 -> 0.05 | D6: =Assumptions!$B$54 -> 0.02 | E6: Both
A7: Gross revenue | B7: ='Global PNL'!Q11*(1-0*Assumptions!$B$53) -> 44500 | C7: ='Global PNL'!Q11*(1-1*Assumptions!$B$53) -> 42275 | D7: ='Global PNL'!Q11*(1-0*Assumptions!$B$53) -> 44500 | E7: ='Global PNL'!Q11*(1-1*Assumptions!$B$53) -> 42275
A8: Less: Channel partner cost | B8: =B7*Assumptions!$B$10 -> 1300 | C8: =C7*Assumptions!$B$10 -> 1235 | D8: =D7*Assumptions!$B$10 -> 1300 | E8: =E7*Assumptions!$B$10 -> 1235
A9: Net revenue | B9: =B7-B8 -> 43200 | C9: =C7-C8 -> 41040 | D9: =D7-D8 -> 43200 | E9: =E7-E8 -> 41040
A10: Operating cost (CoR + G&A + S&M) | B10: ='Global PNL'!Q44*(1+0*Assumptions!$B$54) -> 36525 | C10: ='Global PNL'!Q44*(1+0*Assumptions!$B$54) -> 36525 | D10: ='Global PNL'!Q44*(1+1*Assumptions!$B$54) -> 37255.5 | E10: ='Global PNL'!Q44*(1+1*Assumptions!$B$54) -> 37255.5
A11: ECL provision & write-offs | B11: =B7*Assumptions!$B$17 -> 1335 | C11: =C7*Assumptions!$B$17 -> 1268.25 | D11: =D7*Assumptions!$B$17 -> 1335 | E11: =E7*Assumptions!$B$17 -> 1268.25
A12: EBITDA (after w/off) | B12: =B9-B10-B11 -> 5340 | C12: =C9-C10-C11 -> 3246.75 | D12: =D9-D10-D11 -> 4609.5 | E12: =E9-E10-E11 -> 2516.25
A13: EBITDA % of gross revenue | B13: =IF(B7=0,0,B12/B7) -> 0.12 | C13: =IF(C7=0,0,C12/C7) -> 0.07680071 | D13: =IF(D7=0,0,D12/D7) -> 0.10358427 | E13: =IF(E7=0,0,E12/E7) -> 0.059520993
A14: Add: Other income | B14: =Assumptions!$B$27 -> 274.8 | C14: =Assumptions!$B$27 -> 274.8 | D14: =Assumptions!$B$27 -> 274.8 | E14: =Assumptions!$B$27 -> 274.8
A15: Less: Depreciation & amortisation | B15: =Assumptions!$B$28 -> 1447 | C15: =Assumptions!$B$28 -> 1447 | D15: =Assumptions!$B$28 -> 1447 | E15: =Assumptions!$B$28 -> 1447
A16: Less: Finance cost | B16: =Assumptions!$B$29 -> 272.2 | C16: =Assumptions!$B$29 -> 272.2 | D16: =Assumptions!$B$29 -> 272.2 | E16: =Assumptions!$B$29 -> 272.2
A17: Profit before tax | B17: =B12+B14-B15-B16 -> 3895.6 | C17: =C12+C14-C15-C16 -> 1802.35 | D17: =D12+D14-D15-D16 -> 3165.1 | E17: =E12+E14-E15-E16 -> 1071.85
A18: Tax | B18: =MAX(0,B17)*Assumptions!$B$30 -> 980.52252 | C18: =MAX(0,C17)*Assumptions!$B$30 -> 453.6515 | D18: =MAX(0,D17)*Assumptions!$B$30 -> 796.65567 | E18: =MAX(0,E17)*Assumptions!$B$30 -> 269.78465
A19: Profit after tax | B19: =B17-B18 -> 2915.0775 | C19: =C17-C18 -> 1348.6985 | D19: =D17-D18 -> 2368.4443 | E19: =E17-E18 -> 802.06536
A20: Add: D&A and finance cost (lease interest paid within lease payments) | B20: =B15+B16 -> 1719.2 | C20: =C15+C16 -> 1719.2 | D20: =D15+D16 -> 1719.2 | E20: =E15+E16 -> 1719.2
A21: Add / (Less): Working capital changes | B21: ='Working Capital'!$G$16 -> -775.58256 | C21: ='Working Capital'!$G$16 -> -775.58256 | D21: ='Working Capital'!$G$16 -> -775.58256 | E21: ='Working Capital'!$G$16 -> -775.58256
A22: Less: Capex | B22: =-Assumptions!$B$33 -> -300 | C22: =-Assumptions!$B$33 -> -300 | D22: =-Assumptions!$B$33 -> -300 | E22: =-Assumptions!$B$33 -> -300
A23: Less: Lease payments | B23: =-Assumptions!$B$34 -> -1003.4 | C23: =-Assumptions!$B$34 -> -1003.4 | D23: =-Assumptions!$B$34 -> -1003.4 | E23: =-Assumptions!$B$34 -> -1003.4
A24: Free cash flow FY 2026-27 | B24: =SUM(B19:B23) -> 2555.2949 | C24: =SUM(C19:C23) -> 988.91594 | D24: =SUM(D19:D23) -> 2008.6618 | E24: =SUM(E19:E23) -> 442.28279
A25: Opening cash 1-Apr-26 | B25: =Assumptions!$B$39 -> 4324.9 | C25: =Assumptions!$B$39 -> 4324.9 | D25: =Assumptions!$B$39 -> 4324.9 | E25: =Assumptions!$B$39 -> 4324.9
A26: Closing cash 31-Mar-27 | B26: =B24+B25 -> 6880.1949 | C26: =C24+C25 -> 5313.8159 | D26: =D24+D25 -> 6333.5618 | E26: =E24+E25 -> 4767.1828
A27: Headroom vs base closing cash (%) | B27: =IF($B$26=0,0,B26/$B$26) -> 1 | C27: =IF($B$26=0,0,C26/$B$26) -> 0.77233509 | D27: =IF($B$26=0,0,D26/$B$26) -> 0.92054976 | E27: =IF($B$26=0,0,E26/$B$26) -> 0.69288485
A28: Check: base closing cash vs Global Cashflow (should be zero) | B28: =ROUND(B26-'Global Cashflow'!O28,2) -> 0
A29: Break-even analysis
A30: Revenue decline that reduces FY27 EBITDA to nil (costs held constant) | B30: =IF(B7*(1-Assumptions!$B$10-Assumptions!$B$17)=0,0,B12/(B7*(1-Assumptions!$B$10-Assumptions!$B$17))) -> 0.12755285
A31: Revenue decline that exhausts cash by 31-Mar-27 (approx., costs constant) | B31: =IF(B7*(1-Assumptions!$B$10-Assumptions!$B$17)=0,0,B26/(B7*(1-Assumptions!$B$10-Assumptions!$B$17))) -> 0.16434241
A33: Working capital change held at base budget in all scenarios. Tax recomputed on stressed PBT. Break-even ignores tax shield and working-capital release on lower revenue (conservative).

Sheet YoY Trend
A1: Infrasoft Technologies Limited (Kiya.ai) – Consolidated
A2: Year-on-Year Trend – Revenue and EBITDA (Consolidated)
A3: Going concern assessment for the year ended 31 March 2026 | All amounts in INR Lakhs unless stated
A5: INR Lakhs | B5: FY 2023-24 (A) | C5: FY 2024-25 (A) | D5: FY 2025-26 (A) | E5: FY 2026-27 (B) | F5: FY 2027-28 (P, annualised H1)
A6: Revenue from operations (net revenue) | B6: 38559 | C6: ='FY26 Actual'!F41 -> 40111.3 | D6: ='Global PNL'!C13 -> 37981 | E6: ='Global PNL'!Q13 -> 43200 | F6: ='Global PNL'!AC13 -> 47520
A7: Revenue growth % | C7: =IF(B6=0,0,C6/B6-1) -> 0.040257787 | D7: =IF(C6=0,0,D6/C6-1) -> -0.053109722 | E7: =IF(D6=0,0,E6/D6-1) -> 0.13741081 | F7: =IF(E6=0,0,F6/E6-1) -> 0.1
A8: EBITDA after ECL / write-offs (excl. other income) | B8: 2339.9 | C8: ='FY26 Actual'!F44+'FY26 Actual'!F14+'FY26 Actual'!F13-'FY26 Actual'!F8+'FY26 Actual'!F39 -> 3221.9 | D8: ='Global PNL'!C48 -> -2619 | E8: ='Global PNL'!Q48 -> 5340 | F8: ='Global PNL'!AC48 -> 5874
A9: EBITDA margin % (on revenue from operations) | B9: =IF(B6=0,0,B8/B6) -> 0.060683628 | C9: =IF(C6=0,0,C8/C6) -> 0.080323998 | D9: =IF(D6=0,0,D8/D6) -> -0.06895553 | E9: =IF(E6=0,0,E8/E6) -> 0.12361111 | F9: =IF(F6=0,0,F8/F6) -> 0.12361111
A10: EBITDA growth % | C10: =IF(B8=0,0,(C8-B8)/ABS(B8)) -> 0.37693919 | D10: =IF(C8=0,0,(D8-C8)/ABS(C8)) -> -1.8128744 | E10: =IF(D8=0,0,(E8-D8)/ABS(D8)) -> 3.0389462 | F10: =IF(E8=0,0,(F8-E8)/ABS(E8)) -> 0.1
A11: ECL provision & write-offs | B11: n/a | C11: ='FY26 Actual'!F31+'FY26 Actual'!F32+'FY26 Actual'!F33+'FY26 Actual'!F34 -> 1598.1 | D11: ='Global PNL'!C47 -> 3647.3 | E11: ='Global PNL'!Q47 -> 1335 | F11: ='Global PNL'!AC47 -> 1468.5
A12: EBITDA before ECL / write-offs | B12: n/a | C12: =C8+C11 -> 4820 | D12: =D8+D11 -> 1028.3 | E12: =E8+E11 -> 6675 | F12: =F8+F11 -> 7342.5
A14: Notes:
A15: 1. FY 2023-24 figures are from the prior-year going concern working (YoY Trend sheet). FY 2024-25 and FY 2025-26 are from audited consolidated FS (FY25 as comparatives in the FY26 FS).
A16: 2. FY 2025-26 EBITDA was hit by a one-time clean-up of receivables: ECL, bad-debt and unbilled revenue write-offs of about INR 3,647 lakhs. Before these, EBITDA was positive.
A17: 3. FY 2026-27 budget: net revenue grows about 14% on FY26, and operating costs are held broadly flat through the cost adjustment. This gives EBITDA of 12% of gross revenue.
A18: 4. For FY 2027-28, Apr-Sep 27 is projected at a 10% annualised increase on FY 2026-27.
