Workbook

Sheet Cover
A1: VOLTAS LIMITED
A2: Integrated Financial Model, DCF, Multiples & SoTP Valuation
A4: MODEL INFORMATION
A5: Company Name | B5: Voltas Limited
A6: NSE Ticker | B6: VOLTAS
A7: BSE Code | B7: 500575
A8: Industry | B8: Consumer Durables - Air Conditioning, Cooling & Engineering Projects
A9: Sector | B9: Tata Group
A10: Date of Valuation | B10: 19-Oct-2026
A11: Currency | B11: INR (Rs Crore, unless stated)
A12: FY Ending | B12: 31-March
A13: Model Type | B13: Three-Statement Model + DCF + Relative Valuation + SoTP
A14: Scenario (Live) | B14: Base case
A16: SEGMENT OVERVIEW (Voltas Ltd. Reporting Segments)
A17: 1. Unitary Cooling Products (Room Air Conditioners & Coolers) - RAC
A18: 2. Electro-Mechanical Projects & Services (EMPS) - Institutional & Government Projects
A19: 3. Engineering Products & Services (Mining & Construction Equipment, Water Management, Textile Machinery)
A20: 4. International Operations (Middle East, Africa, Southeast Asia - Electro-Mechanical Projects)
A22: WORKBOOK STATUS
A23: This workbook rebuilds the 21-page Voltas model report in Excel with live formulas (inputs in blue, formulas in black, cross-sheet links in green).
A24: Sheet "Checks" holds integrity checks and a tie-out of rebuilt outputs to the published report; sheet "Error_Log" lists the errors found in the published model and their valuation impact.
A25: Published figures are replicated first (including the errors); corrected values are shown alongside on DCF, Relative_Valuation and SoTP.
A26: Small (+/-1-4 Rs Cr) differences vs the report arise because the report displays rounded historical inputs; these are within the tolerances on the Checks sheet.

Sheet TOC
A1: TABLE OF CONTENTS
A3: # | B3: Worksheet | C3: Description
A4: 1 | B4: Cover | C4: Company & model information
A5: 2 | B5: TOC | C5: This page
A6: 3 | B6: Instructions | C6: Formatting conventions & how to use this model
A7: 4 | B7: Checks | C7: Integrity checks and tie-out to the published report (added)
A8: 5 | B8: Error_Log | C8: Errors found in the published model and valuation impact (added)
A9: 6 | B9: Hist_IS | C9: Historical Income Statement (FY23A-FY26A) & common-size
A10: 7 | B10: Hist_BS | C10: Historical Balance Sheet (FY23A-FY26A)
A11: 8 | B11: Hist_CF | C11: Historical Cash Flow Statement (FY23A-FY26A)
A12: 9 | B12: Assumptions | C12: Master assumptions - macro, segment drivers, margins
A13: 10 | B13: Revenue_Build | C13: Segment-wise revenue build-up (Volume x ASP)
A14: 11 | B14: Cost_Schedule | C14: Operating cost driver schedule
A15: 12 | B15: WC_Schedule | C15: Working capital schedule (days-based)
... A28: 25 | B28: SoTP | C28: Sum-of-the-Parts valuation with scenarios & sensitivities

Sheet Instructions
A1: INSTRUCTIONS - FORMATTING CONVENTIONS & HOW TO USE THIS MODEL
A3: Item | B3: Description
A4: Blue font | B4: Hard-coded input taken from the published report (historical data, assumptions, peer data).
A5: Blue font on peach fill | B5: Forecast / valuation assumption that can be changed (yellow-peach cells). Changing these flows through all sheets.
A6: Black font | B6: Formula on the same sheet.
A7: Green font | B7: Formula linking to another sheet.
A8: Units | B8: INR Crore unless stated; shares in crore; per-share values in Rs.
A9: Timeline | B9: Columns C-F = Mar-23A to Mar-26A (historical); columns G-K = Mar-27E to Mar-31E (forecast) on every time-series sheet.
A10: Flow of the model | B10: Assumptions -> Revenue_Build -> Cost_Schedule -> WC_Schedule / Capex_Dep / Debt_Schedule / Equity_Schedule -> Income_Statement -> Balance_Sheet -> Cash_Flow -> DCF.
A11: Valuation | B11: WACC (peer betas regressed in Market_Data) -> DCF; Relative_Valuation (peer trading multiples); Peer_Multiples -> SoTP.
A12: Published vs corrected | B12: Where the published model contains an error, the published logic is reproduced and a corrected figure is shown next to it (DCF section B, Relative_Valuation rows 29-41, SoTP column C). See Error_Log.
A13: Checks | B13: Review the Checks sheet after changing any input. "OK" = within tolerance; "REVIEW" = a known issue in the published model or source data (explained on the sheet).
A14: Scenario | B14: The "Scenario (Live)" label on the Cover is informational; scenarios are on the SoTP sheet (Low / Base / High).

Sheet Checks
A1: MODEL CHECKS & TIE-OUT TO THE PUBLISHED REPORT
A2: Status: OK = within tolerance. REVIEW = difference exceeds tolerance; for items marked "published issue" this is a genuine error/inconsistency in the published model (see Error_Log).
A4: A. INTEGRITY CHECKS
A5: # | B5: Check | C5: Value | D5: Tolerance | E5: Status | F5: Error_Log ref | G5: Comment
A6: 1 | B6: Revenue build total = historical income statement revenue (FY23-26, sum of abs differences) | C6: =SUMPRODUCT(ABS(Revenue_Build!C24:F24-Hist_IS!C12:F12)) -> 0 | D6: 0.01 | E6: =IF(ABS(C6)<=D6,"OK","REVIEW") -> OK | G6: Linked - must be zero
A7: 2 | B7: Historical balance sheets balance (FY23-26, sum of abs differences) | C7: =SUMPRODUCT(ABS(Hist_BS!C44:F44)) -> 1 | D7: 4 | E7: =IF(ABS(C7)<=D7,"OK","REVIEW") -> OK | F7: E-22 | G7: Source data rounding: +/-1 Cr in FY24 (report shows 14,510 vs 14,509 in FY26)
A8: 3 | B8: Forecast balance sheet balances (FY27-31, sum of abs differences) | C8: =SUMPRODUCT(ABS(Balance_Sheet!G43:K43)) -> 0 | D8: 0.5 | E8: =IF(ABS(C8)<=D8,"OK","REVIEW") -> OK | G8: Integrated model balances
A9: 4 | B9: Forecast cash flow closing cash = balance sheet cash (FY27-31) | C9: =SUMPRODUCT(ABS(Cash_Flow!G53:K53)) -> 0 | D9: 0.5 | E9: =IF(ABS(C9)<=D9,"OK","REVIEW") -> OK
A10: 5 | B10: Historical cash flow closing cash = historical balance sheet cash (FY23-26, sum of abs differences) | C10: =SUMPRODUCT(ABS(Hist_CF!C38:F38)) -> 121 | D10: 5 | E10: =IF(ABS(C10)<=D10,"OK","REVIEW") -> REVIEW | F10: E-04 | G10: Published issue: CF closing cash 693/814/650/741 vs BS 708/852/678/781
A11: 6 | B11: Historical cash flow opening cash = prior-year closing cash (FY24-26) | C11: =SUMPRODUCT(ABS(Hist_CF!D39:F39)) -> 2 | D11: 2 | E11: =IF(ABS(C11)<=D11,"OK","REVIEW") -> OK | F11: E-04 | G11: Rounding only
A12: 7 | B12: Cost_Schedule EBITDA = Income_Statement EBITDA (FY27-31) | C12: =SUMPRODUCT(ABS(Cost_Schedule!G18:K18-Income_Statement!G14:K14)) -> 0 | D12: 0.01 | E12: =IF(ABS(C12)<=D12,"OK","REVIEW") -> OK
A13: 8 | B13: PPE gross block roll-forward reconciles (FY23-26, sum of abs differences) | C13: =SUMPRODUCT(ABS(Capex_Dep!C13:F13)) -> 2 | D13: 3 | E13: =IF(ABS(C13)<=D13,"OK","REVIEW") -> OK | F13: E-08 | G13: Rounding in source data
A14: 9 | B14: EMPS order-book roll-forward FY26: opening + new orders - revenue - closing | C14: =Revenue_Build!F17 -> 447 | D14: 1 | E14: =IF(ABS(C14)<=D14,"OK","REVIEW") -> REVIEW | F14: E-07 | G14: Published issue: 447 Cr gap (closing OB 6,200 vs roll-forward 6,647)
A15: 10 | B15: EMPS FY26 execution rate: recomputed less hard-coded 39.5% | C15: =Revenue_Build!F16-Revenue_Build!F13 -> -0.016214953 | D15: 0.001 | E15: =IF(ABS(C15)<=D15,"OK","REVIEW") -> REVIEW | F15: E-07 | G15: Published issue: recomputed 37.9%
A16: 11 | B16: Other current assets days: used in WC_Schedule vs displayed on Assumptions page (sum abs diff, days) | C16: =SUMPRODUCT(ABS(Assumptions!G30:K30-Assumptions!G31:K31)) -> 187 | D16: 0.01 | E16: =IF(ABS(C16)<=D16,"OK","REVIEW") -> REVIEW | F16: E-05 | G16: Published issue: 25 days displayed, 60-67 days used
A17: 12 | B17: Peer market cap = CMP x shares (max relative difference) | C17: =SUMPRODUCT(ABS(Market_Data!O4:O8)/Market_Data!F4:F8) -> 4.9634827e-05 | D17: 0.001 | E17: =IF(ABS(C17)<=D17,"OK","REVIEW") -> OK | G17: Rounded share counts
A18: 13 | B18: Two WACCs: explicit-period WACC less terminal-value WACC | C18: =WACC!B44-WACC!B54 -> 0.0078286879 | D18: 0.0005 | E18: =IF(ABS(C18)<=D18,"OK","REVIEW") -> REVIEW | F18: E-03 | G18: Published issue: 13.6-13.7% vs 12.9%
A19: 14 | B19: Published FCFF overstated vs corrected FCFF (sum FY27-31) | C19: =SUM(Cash_Flow!G50:K50) -> 128.74421 | D19: 1 | E19: =IF(ABS(C19)<=D19,"OK","REVIEW") -> REVIEW | F19: E-01 | G19: Published issue: capex sign error
A20: 15 | B20: DCF section B (as published column) = DCF main value per share | C20: =DCF!B46-DCF!B30 -> 0 | D20: 0.001 | E20: =IF(ABS(C20)<=D20,"OK","REVIEW") -> OK
A21: 16 | B21: DCF sensitivity centre = DCF corrected value per share | C21: =DCF!B62 -> 0 | D21: 0.001 | E21: =IF(ABS(C21)<=D21,"OK","REVIEW") -> OK
A22: 17 | B22: Relative valuation weights total 100% | C22: =Relative_Valuation!L27 -> 0 | D22: 0.0001 | E22: =IF(ABS(C22)<=D22,"OK","REVIEW") -> OK
A23: 18 | B23: Relative valuation target price: as published less ex-Voltas | C23: =Relative_Valuation!L26-Relative_Valuation!L41 -> 36.695636 | D23: 0.5 | E23: =IF(ABS(C23)<=D23,"OK","REVIEW") -> REVIEW | F23: E-06 | G23: Published issue: peer stats include Voltas
A24: 19 | B24: SoTP base scenario = main result (value per share) | C24: =SoTP!C49 -> 0 | D24: 0.001 | E24: =IF(ABS(C24)<=D24,"OK","REVIEW") -> OK
A25: 20 | B25: SoTP sensitivity centre = base value per share | C25: =SoTP!C58 -> 0 | D25: 0.001 | E25: =IF(ABS(C25)<=D25,"OK","REVIEW") -> OK
A26: 21 | B26: SoTP segment EBIT vs model FY29E EBIT (relative difference) | C26: =SoTP!F17 -> 0.12312482 | D26: 0.02 | E26: =IF(ABS(C26)<=D26,"OK","REVIEW") -> REVIEW | F26: E-18 | G26: Published issue: segment EBIT 12% above model EBIT
A27: 22 | B27: SoTP discount factor: published less corrected | C27: =SoTP!B22-SoTP!C22 -> 0.21776351 | D27: 0.001 | E27: =IF(ABS(C27)<=D27,"OK","REVIEW") -> REVIEW | F27: E-20 | G27: Published issue: 1.000 although 1.9 years
A28: 23 | B28: Total debt: published (excl. current leases) less incl. current leases | C28: =Debt_Schedule!F23-Debt_Schedule!F25 -> -11 | D28: 0.5 | E28: =IF(ABS(C28)<=D28,"OK","REVIEW") -> REVIEW | F28: E-09 | G28: Published issue: current lease liabilities omitted
A29: 24 | B29: Net debt definitions: max less min across Ratios / DCF / Relative / SoTP | C29: =MAX(DCF!B27,Relative_Valuation!E6,SoTP!B25-SoTP!B24,Debt_Schedule!F26-Balance_Sheet!F39)-MIN(DCF!B27,Relative_Valuation!E6,SoTP!B25-SoTP!B24,Debt_Schedule!F26-Balance_Sheet!F39) -> 26 | D29: 2 | E29: =IF(ABS(C29)<=D29,"OK","REVIEW") -> REVIEW | F29: E-10 | G29: Published issue: 186 vs 201 vs 212 vs 211
B30: Checks passed / total | C30: =COUNTIF(E6:E29,"OK") -> 13 | D30: =COUNTA(E6:E29) -> 24
A32: B. TIE-OUT OF REBUILT MODEL TO THE PUBLISHED REPORT (published values keyed in from the PDF)
A33: # | B33: Item | C33: Published | D33: Rebuilt model | E33: Difference | F33: Tolerance | G33: Status
A34: 1 | B34: Revenue FY27E | C34: 16558 | D34: =Income_Statement!G6 -> 16557.061 | E34: =D34-C34 -> -0.9394 | F34: 2 | G34: =IF(ABS(E34)<=F34,"OK","REVIEW") -> OK
A35: 2 | B35: Revenue FY28E | C35: 19014 | D35: =Income_Statement!H6 -> 19013.776 | E35: =D35-C35 -> -0.2239786 | F35: 2 | G35: =IF(ABS(E35)<=F35,"OK","REVIEW") -> OK
A36: 3 | B36: Revenue FY29E | C36: 21432 | D36: =Income_Statement!I6 -> 21431.928 | E36: =D36-C36 -> -0.072344293 | F36: 2 | G36: =IF(ABS(E36)<=F36,"OK","REVIEW") -> OK
A37: 4 | B37: Revenue FY30E | C37: 23800 | D37: =Income_Statement!J6 -> 23799.898 | E37: =D37-C37 -> -0.10162553 | F37: 2 | G37: =IF(ABS(E37)<=F37,"OK","REVIEW") -> OK
A38: 5 | B38: Revenue FY31E | C38: 26484 | D38: =Income_Statement!K6 -> 26484.178 | E38: =D38-C38 -> 0.17811556 | F38: 2 | G38: =IF(ABS(E38)<=F38,"OK","REVIEW") -> OK
A39: 6 | B39: EBITDA FY27E | C39: 1043 | D39: =Income_Statement!G14 -> 1043.0948 | E39: =D39-C39 -> 0.0948178 | F39: 2 | G39: =IF(ABS(E39)<=F39,"OK","REVIEW") -> OK
A40: 7 | B40: EBITDA FY28E | C40: 1312 | D40: =Income_Statement!H14 -> 1311.9505 | E40: =D40-C40 -> -0.049454524 | F40: 2 | G40: =IF(ABS(E40)<=F40,"OK","REVIEW") -> OK
A41: 8 | B41: EBITDA FY29E | C41: 1543 | D41: =Income_Statement!I14 -> 1543.0988 | E41: =D41-C41 -> 0.098791211 | F41: 2 | G41: =IF(ABS(E41)<=F41,"OK","REVIEW") -> OK
A42: 9 | B42: EBITDA FY30E | C42: 1714 | D42: =Income_Statement!J14 -> 1713.5927 | E42: =D42-C42 -> -0.40731704 | F42: 2 | G42: =IF(ABS(E42)<=F42,"OK","REVIEW") -> OK
A43: 10 | B43: EBITDA FY31E | C43: 1933 | D43: =Income_Statement!K14 -> 1933.345 | E43: =D43-C43 -> 0.34500244 | F43: 2 | G43: =IF(ABS(E43)<=F43,"OK","REVIEW") -> OK
A44: 11 | B44: EBIT FY27E | C44: 950 | D44: =Income_Statement!G17 -> 950.29192 | E44: =D44-C44 -> 0.29192355 | F44: 2 | G44: =IF(ABS(E44)<=F44,"OK","REVIEW") -> OK
A45: 12 | B45: EBIT FY28E | C45: 1206 | D45: =Income_Statement!H17 -> 1206.2825 | E45: =D45-C45 -> 0.28248589 | F45: 2 | G45: =IF(ABS(E45)<=F45,"OK","REVIEW") -> OK
A46: 13 | B46: EBIT FY29E | C46: 1420 | D46: =Income_Statement!I17 -> 1420.0069 | E46: =D46-C46 -> 0.0068527795 | F46: 2 | G46: =IF(ABS(E46)<=F46,"OK","REVIEW") -> OK
A47: 14 | B47: EBIT FY30E | C47: 1575 | D47: =Income_Statement!J17 -> 1574.3972 | E47: =D47-C47 -> -0.60282307 | F47: 2 | G47: =IF(ABS(E47)<=F47,"OK","REVIEW") -> OK
A48: 15 | B48: EBIT FY31E | C48: 1776 | D48: =Income_Statement!K17 -> 1776.2297 | E48: =D48-C48 -> 0.22968238 | F48: 2 | G48: =IF(ABS(E48)<=F48,"OK","REVIEW") -> OK
A49: 16 | B49: PBT FY27E | C49: 1050 | D49: =Income_Statement!G23 -> 1049.4351 | E49: =D49-C49 -> -0.56493411 | F49: 2 | G49: =IF(ABS(E49)<=F49,"OK","REVIEW") -> OK
A50: 17 | B50: PBT FY28E | C50: 1314 | D50: =Income_Statement!H23 -> 1312.9547 | E50: =D50-C50 -> -1.0453138 | F50: 2 | G50: =IF(ABS(E50)<=F50,"OK","REVIEW") -> OK
A51: 18 | B51: PBT FY29E | C51: 1611 | D51: =Income_Statement!I23 -> 1610.4858 | E51: =D51-C51 -> -0.51423238 | F51: 2 | G51: =IF(ABS(E51)<=F51,"OK","REVIEW") -> OK
A52: 19 | B52: PBT FY30E | C52: 1770 | D52: =Income_Statement!J23 -> 1769.4558 | E52: =D52-C52 -> -0.54421534 | F52: 2 | G52: =IF(ABS(E52)<=F52,"OK","REVIEW") -> OK
A53: 20 | B53: PBT FY31E | C53: 2043 | D53: =Income_Statement!K23 -> 2042.4924 | E53: =D53-C53 -> -0.50764589 | F53: 2 | G53: =IF(ABS(E53)<=F53,"OK","REVIEW") -> OK
A54: 21 | B54: PAT FY27E | C54: 735 | D54: =Income_Statement!G25 -> 734.60455 | E54: =D54-C54 -> -0.39545388 | F54: 2 | G54: =IF(ABS(E54)<=F54,"OK","REVIEW") -> OK
A55: 22 | B55: PAT FY28E | C55: 919 | D55: =Income_Statement!H25 -> 919.06828 | E55: =D55-C55 -> 0.068280312 | F55: 2 | G55: =IF(ABS(E55)<=F55,"OK","REVIEW") -> OK
A56: 23 | B56: PAT FY29E | C56: 1128 | D56: =Income_Statement!I25 -> 1127.34 | E56: =D56-C56 -> -0.65996267 | F56: 2 | G56: =IF(ABS(E56)<=F56,"OK","REVIEW") -> OK
A57: 24 | B57: PAT FY30E | C57: 1239 | D57: =Income_Statement!J25 -> 1238.619 | E57: =D57-C57 -> -0.38095074 | F57: 2 | G57: =IF(ABS(E57)<=F57,"OK","REVIEW") -> OK
A58: 25 | B58: PAT FY31E | C58: 1430 | D58: =Income_Statement!K25 -> 1429.7446 | E58: =D58-C58 -> -0.25535212 | F58: 2 | G58: =IF(ABS(E58)<=F58,"OK","REVIEW") -> OK
A59: 26 | B59: Diluted EPS FY27E (Rs) | C59: 22.22 | D59: =Income_Statement!G30 -> 22.206909 | E59: =D59-C59 -> -0.013091109 | F59: 0.1 | G59: =IF(ABS(E59)<=F59,"OK","REVIEW") -> OK
A60: 27 | B60: Diluted EPS FY31E (Rs) | C60: 43.23 | D60: =Income_Statement!K30 -> 43.220818 | E60: =D60-C60 -> -0.0091823495 | F60: 0.15 | G60: =IF(ABS(E60)<=F60,"OK","REVIEW") -> OK
A61: 28 | B61: Total D&A FY27E | C61: 93 | D61: =Income_Statement!G16 -> 92.802894 | E61: =D61-C61 -> -0.19710575 | F61: 1 | G61: =IF(ABS(E61)<=F61,"OK","REVIEW") -> OK
A62: 29 | B62: Total D&A FY28E | C62: 106 | D62: =Income_Statement!H16 -> 105.66806 | E62: =D62-C62 -> -0.33194042 | F62: 1 | G62: =IF(ABS(E62)<=F62,"OK","REVIEW") -> OK
A63: 30 | B63: Total D&A FY29E | C63: 123 | D63: =Income_Statement!I16 -> 123.09194 | E63: =D63-C63 -> 0.091938431 | F63: 1 | G63: =IF(ABS(E63)<=F63,"OK","REVIEW") -> OK
A64: 31 | B64: Total D&A FY30E | C64: 139 | D64: =Income_Statement!J16 -> 139.19551 | E64: =D64-C64 -> 0.19550603 | F64: 1 | G64: =IF(ABS(E64)<=F64,"OK","REVIEW") -> OK
A65: 32 | B65: Total D&A FY31E | C65: 157 | D65: =Income_Statement!K16 -> 157.11532 | E65: =D65-C65 -> 0.11532006 | F65: 1 | G65: =IF(ABS(E65)<=F65,"OK","REVIEW") -> OK
A66: 33 | B66: Closing cash FY27E | C66: 1099 | D66: =Balance_Sheet!G39 -> 1098.3375 | E66: =D66-C66 -> -0.66250858 | F66: 5 | G66: =IF(ABS(E66)<=F66,"OK","REVIEW") -> OK
A67: 34 | B67: Closing cash FY28E | C67: 1302 | D67: =Balance_Sheet!H39 -> 1300.5778 | E67: =D67-C67 -> -1.422176 | F67: 5 | G67: =IF(ABS(E67)<=F67,"OK","REVIEW") -> OK
A68: 35 | B68: Closing cash FY29E | C68: 1993 | D68: =Balance_Sheet!I39 -> 1990.8047 | E68: =D68-C68 -> -2.1953393 | F68: 5 | G68: =IF(ABS(E68)<=F68,"OK","REVIEW") -> OK
A69: 36 | B69: Closing cash FY30E | C69: 2331 | D69: =Balance_Sheet!J39 -> 2328.1685 | E69: =D69-C69 -> -2.8314658 | F69: 5 | G69: =IF(ABS(E69)<=F69,"OK","REVIEW") -> OK
A70: 37 | B70: Closing cash FY31E | C70: 3369 | D70: =Balance_Sheet!K39 -> 3365.2083 | E70: =D70-C70 -> -3.7917124 | F70: 5 | G70: =IF(ABS(E70)<=F70,"OK","REVIEW") -> OK
A71: 38 | B71: Total assets FY27E | C71: 15545 | D71: =Balance_Sheet!G41 -> 15543.745 | E71: =D71-C71 -> -1.2547387 | F71: 5 | G71: =IF(ABS(E71)<=F71,"OK","REVIEW") -> OK
A72: 39 | B72: Total assets FY28E | C72: 17260 | D72: =Balance_Sheet!H41 -> 17257.935 | E72: =D72-C72 -> -2.065117 | F72: 5 | G72: =IF(ABS(E72)<=F72,"OK","REVIEW") -> OK
A73: 40 | B73: Total assets FY29E | C73: 19337 | D73: =Balance_Sheet!I41 -> 19334.172 | E73: =D73-C73 -> -2.8282449 | F73: 5 | G73: =IF(ABS(E73)<=F73,"OK","REVIEW") -> OK
A74: 41 | B74: Total assets FY30E | C74: 21392 | D74: =Balance_Sheet!J41 -> 21388.741 | E74: =D74-C74 -> -3.2591403 | F74: 5 | G74: =IF(ABS(E74)<=F74,"OK","REVIEW") -> OK
A75: 42 | B75: Total assets FY31E | C75: 23880 | D75: =Balance_Sheet!K41 -> 23875.94 | E75: =D75-C75 -> -4.0601566 | F75: 5 | G75: =IF(ABS(E75)<=F75,"OK","REVIEW") -> OK
A76: 43 | B76: Net working capital change FY27E | C76: -153 | D76: =WC_Schedule!G22 -> -152.6743 | E76: =D76-C76 -> 0.32570418 | F76: 1 | G76: =IF(ABS(E76)<=F76,"OK","REVIEW") -> OK
A77: 44 | B77: Net working capital change FY28E | C77: -474 | D77: =WC_Schedule!H22 -> -473.84612 | E77: =D77-C77 -> 0.15388115 | F77: 1 | G77: =IF(ABS(E77)<=F77,"OK","REVIEW") -> OK
A78: 45 | B78: Net working capital change FY29E | C78: -111 | D78: =WC_Schedule!I22 -> -110.73119 | E78: =D78-C78 -> 0.26881335 | F78: 1 | G78: =IF(ABS(E78)<=F78,"OK","REVIEW") -> OK
A79: 46 | B79: Net working capital change FY30E | C79: -656 | D79: =WC_Schedule!J22 -> -655.55447 | E79: =D79-C79 -> 0.44553291 | F79: 1 | G79: =IF(ABS(E79)<=F79,"OK","REVIEW") -> OK
A80: 47 | B80: Net working capital change FY31E | C80: -109 | D80: =WC_Schedule!K22 -> -108.88128 | E80: =D80-C80 -> 0.11871812 | F80: 1 | G80: =IF(ABS(E80)<=F80,"OK","REVIEW") -> OK
A81: 48 | B81: CFO FY27E | C81: 776 | D81: =Cash_Flow!G13 -> 775.73121 | E81: =D81-C81 -> -0.26878578 | F81: 2 | G81: =IF(ABS(E81)<=F81,"OK","REVIEW") -> OK
A82: 49 | B82: CFO FY28E | C82: 656 | D82: =Cash_Flow!H13 -> 655.46599 | E82: =D82-C82 -> -0.53401084 | F82: 2 | G82: =IF(ABS(E82)<=F82,"OK","REVIEW") -> OK
A83: 50 | B83: CFO FY29E | C83: 1247 | D83: =Cash_Flow!I13 -> 1246.8604 | E83: =D83-C83 -> -0.13957261 | F83: 2 | G83: =IF(ABS(E83)<=F83,"OK","REVIEW") -> OK
A84: 51 | B84: CFO FY30E | C84: 842 | D84: =Cash_Flow!J13 -> 841.25958 | E84: =D84-C84 -> -0.74041992 | F84: 2 | G84: =IF(ABS(E84)<=F84,"OK","REVIEW") -> OK
A85: 52 | B85: CFO FY31E | C85: 1611 | D85: =Cash_Flow!K13 -> 1610.3996 | E85: =D85-C85 -> -0.60042337 | F85: 2 | G85: =IF(ABS(E85)<=F85,"OK","REVIEW") -> OK
A86: 53 | B86: FCFF (as published) FY27E | C86: 400 | D86: =Cash_Flow!G43 -> 400.02539 | E86: =D86-C86 -> 0.025393479 | F86: 2 | G86: =IF(ABS(E86)<=F86,"OK","REVIEW") -> OK
A87: 54 | B87: FCFF (as published) FY28E | C87: 240 | D87: =Cash_Flow!H43 -> 240.44886 | E87: =D87-C87 -> 0.44885819 | F87: 2 | G87: =IF(ABS(E87)<=F87,"OK","REVIEW") -> OK
A88: 55 | B88: FCFF (as published) FY29E | C88: 676 | D88: =Cash_Flow!I43 -> 676.31386 | E88: =D88-C88 -> 0.31386283 | F88: 2 | G88: =IF(ABS(E88)<=F88,"OK","REVIEW") -> OK
A89: 56 | B89: FCFF (as published) FY30E | C89: 291 | D89: =Cash_Flow!J43 -> 290.60032 | E89: =D89-C89 -> -0.39967705 | F89: 2 | G89: =IF(ABS(E89)<=F89,"OK","REVIEW") -> OK
A90: 57 | B90: FCFF (as published) FY31E | C90: 963 | D90: =Cash_Flow!K43 -> 963.19101 | E90: =D90-C90 -> 0.19100721 | F90: 2 | G90: =IF(ABS(E90)<=F90,"OK","REVIEW") -> OK
A91: 58 | B91: FCFE FY27E | C91: 330 | D91: =Cash_Flow!G46 -> 329.42712 | E91: =D91-C91 -> -0.57288426 | F91: 2 | G91: =IF(ABS(E91)<=F91,"OK","REVIEW") -> OK
A92: 59 | B92: FCFE FY28E | C92: 210 | D92: =Cash_Flow!H46 -> 209.50329 | E92: =D92-C92 -> -0.49671403 | F92: 2 | G92: =IF(ABS(E92)<=F92,"OK","REVIEW") -> OK
A93: 60 | B93: FCFE FY29E | C93: 640 | D93: =Cash_Flow!I46 -> 639.91816 | E93: =D93-C93 -> -0.081837377 | F93: 2 | G93: =IF(ABS(E93)<=F93,"OK","REVIEW") -> OK
A94: 61 | B94: FCFE FY30E | C94: 278 | D94: =Cash_Flow!J46 -> 278.40308 | E94: =D94-C94 -> 0.40308192 | F94: 2 | G94: =IF(ABS(E94)<=F94,"OK","REVIEW") -> OK
A95: 62 | B95: FCFE FY31E | C95: 922 | D95: =Cash_Flow!K46 -> 922.06227 | E95: =D95-C95 -> 0.062273524 | F95: 2 | G95: =IF(ABS(E95)<=F95,"OK","REVIEW") -> OK
A96: 63 | B96: ROE FY27E | C96: 0.11 | D96: =Ratios!G11 -> 0.10964014 | E96: =D96-C96 -> -0.00035985861 | F96: 0.002 | G96: =IF(ABS(E96)<=F96,"OK","REVIEW") -> OK
A97: 64 | B97: ROCE FY27E | C97: 0.119 | D97: =Ratios!G12 -> 0.11903371 | E97: =D97-C97 -> 3.3709813e-05 | F97: 0.002 | G97: =IF(ABS(E97)<=F97,"OK","REVIEW") -> OK
A98: 65 | B98: EV/EBITDA FY27E (x) | C98: 32.6 | D98: =Ratios!G33 -> 32.634045 | E98: =D98-C98 -> 0.03404467 | F98: 0.2 | G98: =IF(ABS(E98)<=F98,"OK","REVIEW") -> OK
A99: 66 | B99: P/E FY27E (x) | C99: 46.5 | D99: =Ratios!G34 -> 46.517055 | E99: =D99-C99 -> 0.017054898 | F99: 0.2 | G99: =IF(ABS(E99)<=F99,"OK","REVIEW") -> OK
A100: 67 | B100: Levered beta - Voltas | C100: 0.93 | D100: =WACC!I6 -> 0.93220703 | E100: =D100-C100 -> 0.0022070269 | F100: 0.01 | G100: =IF(ABS(E100)<=F100,"OK","REVIEW") -> OK
A101: 68 | B101: Levered beta - Blue Star | C101: 1.18 | D101: =WACC!I7 -> 1.1809716 | E101: =D101-C101 -> 0.00097162548 | F101: 0.01 | G101: =IF(ABS(E101)<=F101,"OK","REVIEW") -> OK
A102: 69 | B102: Levered beta - Amber | C102: 1.63 | D102: =WACC!I8 -> 1.6316239 | E102: =D102-C102 -> 0.0016239078 | F102: 0.01 | G102: =IF(ABS(E102)<=F102,"OK","REVIEW") -> OK
...

Sheet Error_Log
A1: ERROR & INCONSISTENCY LOG - PUBLISHED VOLTAS MODEL (21-page report)
A2: Each item was found by rebuilding the model and cross-checking every page. Impact figures are live formulas where a numeric impact can be computed.
A4: VALUATION SUMMARY: AS PUBLISHED vs CORRECTED (Rs per share)
A5: Method | C5: As published (rebuilt) | D5: Corrected | E5: Change | F5: Corrections applied
A6: DCF (FCFF) | C6: =DCF!B30 -> 370.22886 | D6: =DCF!D46 -> 317.74893 | E6: =D6-C6 -> -52.47993 | F6: E-01 capex sign; E-03 single WACC
A7: Relative valuation (peer multiples) | C7: =Relative_Valuation!L26 -> 686.0162 | D7: =Relative_Valuation!L41 -> 649.32057 | E7: =D7-C7 -> -36.695636 | F7: E-06 exclude Voltas from peer statistics
A8: Sum-of-the-parts (base) | C8: =SoTP!B29 -> 1234.6871 | D8: =SoTP!C29 -> 965.28412 | E8: =D8-C8 -> -269.40302 | F8: E-20 discount operating value 1.9 yrs at cost of equity
A9: SoTP low | C9: =SoTP!B46 -> 848.57102 | D9: =SoTP!B48 -> 663.25 | E9: =D9-C9 -> -185.32102 | F9: as above
A10: SoTP high | C10: =SoTP!D46 -> 1456.5457 | D10: =SoTP!D48 -> 1138.8299 | E10: =D10-C10 -> -317.71571 | F10: as above
A11: Current market price (Rs) | C11: =Assumptions!$C$8 -> 1033
A12: Note: the report itself gives no blended target; DCF, multiples and SoTP differ widely (367 / 686 / 1,235) even before corrections - the DCF is heavily driven by terminal value (86% of EV) and working-capital build.
A14: DETAILED FINDINGS
A15: ID | B15: Sheet / location | C15: Severity | D15: Finding | E15: Evidence | F15: Impact (live) | G15: Impact unit / meaning | H15: Recommended fix | I15: Treatment in this workbook
A16: E-01 | B16: Cash_Flow - FCFF block (published p.14) -> DCF | C16: High | D16: FCFF deducts capex as (PPE capex - ROU additions) instead of (PPE capex + ROU additions). The cash-flow statement itself uses 225/259/356/324/360. | E16: Published capex 205/236/330/295/328 vs correct 225/259/356/324/360; FCFF overstated by 20/23/26/29/32 (130 over five years). | F16: =DCF!C49 -> -13.418157 | G16: Rs per share change in DCF value from fixing capex only | H16: Use Capex + ROU additions (= CFI capex) in the FCFF block. | I16: Replicated as published (row "as published"); corrected FCFF on Cash_Flow and DCF col C.
A17: E-02 | B17: DCF (published p.18) header | C17: Low | D17: Column headers read FY26E-FY30E but the cash flows are FY27E-FY31E (the PV line below even says FY27E-FY31E). | E17: Header FY26E..FY30E vs FCFF 400/240/676/291/963 = FY27E..FY31E. | H17: Relabel headers FY27E-FY31E. | I17: Headers corrected.
A18: E-03 | B18: WACC (p.17) / DCF (p.18) | C18: High | D18: Two different WACCs are used: 13.7% (beta 1.14) for the explicit period and a separate 12.9% (beta hard-coded 1.00) for the terminal value, which widens the TV and is not explained. | E18: Explicit discount factors imply 13.66%; TV = 1,034/(12.9% - 7.4%) = 18,809. | F18: =DCF!D46-DCF!C46 -> -39.061773 | G18: Rs per share change from using one WACC (after fixing E-01) | H18: Use a single WACC (or justify a lower terminal WACC) and link both to the same beta. | I18: Both reproduced; DCF section B shows effect.
A19: E-04 | B19: Hist_CF (p.5) vs Hist_BS (p.4) | C19: Medium | D19: Historical closing cash in the cash flow statement does not agree with balance sheet cash; FY26 opening cash (650) also differs from FY25 closing (649). | E19: CF closing 693/816/649/740 vs BS 708/852/678/781. | F19: =Hist_CF!F38 -> -40 | G19: FY26 difference, Rs Cr (CF less BS) | H19: Reconcile (bank overdrafts / other bank balances) or restate cash definition; forecast starts from BS cash 781. | I19: Reproduced; difference shown on Hist_CF and Checks.
A20: E-05 | B20: Assumptions (p.6) vs WC_Schedule (p.9) | C20: Medium | D20: Assumptions page shows Other Current Assets Days = 25.0 for every forecast year, but the working-capital schedule uses 67/63/61/61/60 days ("Forecast = Assumptions link" is broken). | E20: OCA FY27 3,039 = 16,558 x 67/365; at 25 days it would be 1,134. | F20: =WC_Schedule!G17-WC_Schedule!G6*Assumptions!G31/365 -> 1905.196 | G20: FY27 OCA balance higher than a 25-day assumption, Rs Cr (cash tied up) | H20: Link WC_Schedule to the assumption cell or correct the assumption page; decide which days are intended. | I20: Inputs set to the days actually used; displayed 25 kept as a memo row.
A21: E-06 | B21: Relative_Valuation (p.19) | C21: High | D21: Peer statistics (median/average/quartiles) include Voltas itself, so the EV/Revenue implied value equals the current price (circular) and medians are biased toward Voltas. | E21: Implied EV/Revenue value Rs 1,033.16 vs CMP 1,032.85. Ex-Voltas medians: EV/Rev 2.4x, EV/EBITDA 32.4x, P/E 65.3x. | F21: =Relative_Valuation!L41-Relative_Valuation!L26 -> -36.695636 | G21: Rs change in blended target price when Voltas is excluded | H21: Exclude the target company from peer statistics. | I21: Published calc reproduced; corrected block on Relative_Valuation rows 29-41.
A22: E-07 | B22: Revenue_Build (p.7) | C22: Medium | D22: EMPS FY26: execution rate hard-coded at 39.5% but actual revenue / (opening OB + new orders) is 37.9%; order book does not roll forward (6,500 + 4,200 - 4,053 = 6,647, not 6,200). Forecast opening OB of 6,200 may understate EMPS revenue. | E22: FY26 roll-forward gap 447 Cr; at 39% execution a 447 Cr higher opening OB adds ~174 Cr FY27 EMPS revenue. | F22: =Revenue_Build!F17 -> 447 | G22: Rs Cr gap in FY26 closing order book | H22: Confirm FY26 closing order book from reported data and make opening OB / execution rate consistent. | I22: Reproduced; check rows added on Revenue_Build.
A23: E-08 | B23: Capex_Dep (p.10) | C23: Low | D23: Two rows are both labelled "Less: Disposal"; the second one is added back in the roll-forward (it is an adjustment/transfer, not a disposal). | E23: Gross block FY26: 1,161 + 183 - 17 + 11 = 1,338; accumulated depn 341 + 70 - 15 + 7 = 403. | H23: Relabel second row "Add: other adjustments / transfers". | I23: Relabelled.
A24: E-09 | B24: Debt_Schedule (p.11) | C24: Low | D24: "Lease Liabilities (Total)" contains only non-current leases (15); current leases (11) are left out of Total Debt. The ST borrowings row labelled "% (Receivables + Inventories)" actually shows the rupee increase. FY26A total debt shows 981 vs 982 sum of components. | E24: Total debt incl. current leases FY26 = 993 vs 981-982 shown. | F24: =Debt_Schedule!F24 -> 11 | G24: Rs Cr debt omitted from published Total Debt | H24: Include current lease liabilities and fix labels. | I24: Memo row added (total incl. current leases).
A25: E-10 | B25: Ratios / DCF / Relative_Valuation / SoTP | C25: Medium | D25: Net debt is defined four different ways: Ratios 186 (LT+ST borrowings less cash), DCF 200, Relative 212 (Screener), SoTP 211 (992 less 781). Debt of 992 vs 982/967 also differs. | E25: 186 vs 200/201 vs 212 vs 211. | F25: =MAX(DCF!B27,Relative_Valuation!E6,SoTP!B25-SoTP!B24,Debt_Schedule!F26-Balance_Sheet!F39)-MIN(DCF!B27,Relative_Valuation!E6,SoTP!B25-SoTP!B24,Debt_Schedule!F26-Balance_Sheet!F39) -> 26 | G25: Rs Cr spread between highest and lowest net debt | H25: Adopt one definition (e.g. borrowings + leases - cash and liquid investments) across all valuation sheets. | I25: Each method kept as published.
A26: E-11 | B26: Cost_Schedule (p.8) | C26: Low | D26: The forecast line labelled "Sub-Contracting / Erection Charges (EMPS)" actually holds total Other Expenses (selling, admin, freight, power etc.); Hist_IS shows sub-contracting as blank. | E26: FY26: 1,589 = Other expenses on Hist_IS. | H26: Relabel as Other Expenses. | I26: Label clarified.
A27: E-12 | B27: Assumptions (p.6) - interest rates | C27: Low | D27: Average interest rates on LT (7.0%-6.7%) and ST debt (7.9%-7.5%) are inputs but are not used; finance cost is driven by "% of revenue". Implied interest on the debt schedule differs from the finance cost in the income statement. | E27: FY27 finance cost 101 vs rate-based estimate on average debt. | F27: =Income_Statement!G19-(AVERAGE(Debt_Schedule!F10,Debt_Schedule!G10)*Assumptions!G36+AVERAGE(Debt_Schedule!F15,Debt_Schedule!G15)*Assumptions!G37) -> 27.731305 | G27: FY27 Rs Cr: model finance cost less rate-based interest | H27: Drive finance cost off debt balances x rates (and leases) or remove unused inputs. | I27: Reproduced; inputs flagged "not used".
A28: E-13 | B28: Income_Statement / Cash_Flow (pp.12,14) | C28: Low | D28: Share of JV loss (-131 each year) is a non-cash charge but is not added back in CFO and NC investments stay flat, i.e. the model implicitly funds JV losses in cash inside operating cash flow. FCFF (EBIT-based) ignores this funding. | E28: JV loss -131 p.a. reduces cash by 655 over FY27-31. | F28: =-Income_Statement!G21 -> 131 | G28: Rs Cr per year of JV loss treated as cash | H28: Show JV funding in investing cash flow (or add back loss and reduce investment) and reflect it in valuation. | I28: Reproduced (no effect on balancing).
A29: E-14 | B29: DCF (p.18) - terminal growth | C29: Medium | D29: Terminal growth (7.4%) is linked to the risk-free rate; combined with the low terminal WACC the spread is only ~5.5% and terminal value is 86% of EV. Valuation is extremely sensitive to this. | E29: TV % of EV = 85.6%; each +1pt of g adds roughly Rs 40-55 per share at the corrected WACC (see DCF sensitivity). | F29: =DCF!B48 -> 0.85600968 | G29: Terminal value as % of EV | H29: Justify g separately from Rf (usually 4-6% for long-run nominal growth) and show sensitivity. | I29: Reproduced; sensitivity grid added on DCF.
A30: E-15 | B30: DCF (p.18) - equity bridge | C30: Medium | D30: Equity value deducts only net debt; non-current investments (2,307) and current investments (277) are ignored, while the JV funding burn is also excluded from FCFF. SoTP, by contrast, adds the JV at book value. | E30: Excluded investments 2,584 Cr = Rs 78 per share. | F30: =DCF!B50/DCF!B29 -> 78.113664 | G30: Rs per share of excluded investments (book) | H30: Add value of non-operating investments (and JV) consistently across DCF and SoTP. | I30: Memo only (not applied).
A31: E-16 | B31: Market_Data vs Relative_Valuation (pp.16,19) | C31: Medium | D31: Peer data differ between the WACC/Market_Data page and the Relative_Valuation page: Amber price 6,688.55 vs 6,668.00; Voltas net income 442.2 vs 370.0; LG 1,824.7 vs 1,685.0; Crompton -228.1 vs 516.0; sales and market caps also differ. | E31: Voltas NP 442.2 (12M) vs 370.0 (FY26); Amber price difference shown at right. | F31: =Market_Data!C7-Relative_Valuation!B8 -> 20.55 | G31: Rs per share Amber price difference | H31: Use a single dated data set for all peer analysis. | I31: Both data sets reproduced.
A32: E-17 | B32: Assumptions vs SoTP | C32: Low | D32: Forecast effective tax rate is 30%, SoTP uses 25% and WACC sheet uses 25%. | E32: 30% vs 25% (PAT used in SoTP is ~7% higher than at 30%). | F32: =Assumptions!G25-SoTP!B6 -> 0.05 | G32: Percentage-point difference in tax rate | H32: Use one tax-rate assumption (or document the reason). | I32: Reproduced.
A33: E-18 | B33: SoTP (p.21) - tie-out | C33: High | D33: Segment EBIT in the SoTP (1,595) does not reconcile to the model FY29E EBIT (1,420); the "for tie-out check" input is shown but never used. Overall margin 7.4% vs model 6.6% (unallocated costs not charged). | E33: SoTP EBIT 1,595 vs model 1,420: +175 Cr (+12.3%). | F33: =SoTP!E17 -> 174.83809 | G33: Rs Cr SoTP segment EBIT above model EBIT | H33: Reconcile segment margins to consolidated EBIT or allocate corporate costs. | I33: Tie-out row added (SoTP row 17).
A34: E-19 | B34: SoTP (p.21) - borrowings note | C34: Low | D34: Note says borrowings = term loan 423 + working-capital debt 544 + leases ~15 = 982, but 992 is deducted. | E34: 423 + 544 + 15 = 982 vs 992 used. | F34: =SoTP!B25-(423+544+15) -> 10 | G34: Rs Cr over-deduction | H34: Correct the amount or the note. | I34: Published 992 retained.
A35: E-20 | B35: SoTP (p.21) - discount factor | C35: High | D35: "Years from today to valuation date" = 1.9 but the discount factor is 1.000, so FY29E-based operating value is not discounted to today (the multiples are applied to FY29E earnings at Sep-28). | E35: Discount factor 1.000 vs 1/(1+13.8%)^1.9 = 0.78. | F35: =SoTP!C29-SoTP!B29 -> -269.40302 | G35: Rs per share change when discounted | H35: Apply the discount factor (e.g. at cost of equity) or explain why none is needed. | I35: Published reproduced; corrected column C added.
A36: E-21 | B36: SoTP (p.21) | C36: Low | D36: Revenue-share total shows 99.6% (excludes "Other Unallocated" 0.4%). | E36: Total should be 100%. | H36: Include Other in the total. | I36: Corrected.
A37: E-22 | B37: Hist_IS / Hist_BS / Hist_CF (pp.3-5) | C37: Low | D37: Source data are rounded to whole crores so statements do not foot exactly (e.g. FY26 total E&L 14,510 vs total assets 14,509; FY23 PBT 307 vs derived 306; closing equity+liabilities FY24-25 off by 1). | E37: Check rows added. | F37: =SUMPRODUCT(ABS(Hist_BS!C44:F44)) -> 1 | G37: Rs Cr sum of absolute BS differences FY23-26 | H37: Load unrounded statements. | I37: Totals computed by formula; differences of +/-1 vs report.
A38: E-23 | B38: Hist_IS / Relative / Market_Data | C38: Low | D38: Share count is shown as 33.1 (EPS), 33.09 (market data) and 33.08 (SoTP, DCF and ratios). | E38: 33.1 / 33.09 / 33.08. | H38: Use one share count. | I38: 33.08 used throughout.
A39: E-24 | B39: DCF / Cover - timing | C39: Medium | D39: Valuation date is 19-Oct-2026 but cash flows are discounted from 1-Apr-2026 (FY27 at 0.5 years) and the equity bridge uses 31-Mar-2026 net debt; roughly half of FY27 has already elapsed. | E39: Date of valuation 19-Oct-2026 vs period start 1-Apr-2026. | H39: Roll the valuation date forward (stub period) or state the valuation date as 31-Mar-2026. | I39: Not changed (flagged).
A40: E-25 | B40: Equity_Schedule / Cash_Flow | C40: Low | D40: Dividends are held flat at 132 Cr (Rs 4/share) vs 232 Cr paid in FY26 despite profit tripling. | E40: FY26 dividend 232 vs forecast 132. | F40: =-Hist_CF!F27-Equity_Schedule!G12 -> 99.68 | G40: Rs Cr lower dividends than FY26 | H40: Link dividends to a payout ratio. | I40: Reproduced (DPS Rs 4 assumption).
A41: E-26 | B41: Ratios (p.15) | C41: Low | D41: ROE uses average equity (FY24 onwards) whereas ROA, ROCE, asset and inventory turnover use closing balances; Net Debt/EBITDA excludes leases while Debt/Equity includes non-current leases. | E41: Mixed conventions. | H41: Use consistent average-balance conventions. | I41: Reproduced; conventions stated in labels.
A42: E-27 | B42: WACC (p.17) | C42: Low | D42: Pre-tax cost of debt displays 7.9% while Rf 7.4% + spread 0.6% = 8.0% (after-tax 6.0% is consistent with 8.0%). Rebuilt WACC 13.64% vs 13.7% shown; TV WACC 12.86% vs 12.9%. | F42: =WACC!B44-0.137 -> -0.00057131214 | G42: Rebuilt less published explicit WACC | H42: Show unrounded inputs. | I42: Rebuilt from displayed inputs; small variance (see Checks).
A43: E-28 | B43: Instructions / Market_Data | C43: Low | D43: The TOC lists an "Instructions" sheet and the "Market_Data" page, which are not legible in the PDF (Instructions not printed; weekly price table too small). | H43: Provide readable print area. | I43: Instructions rewritten; price history re-extracted from the PDF text and betas recomputed with SLOPE (they match the published betas).
A45: Findings by severity
B46: High | C46: =COUNTIF($C$16:$C$43,"High") -> 5
B47: Medium | C47: =COUNTIF($C$16:$C$43,"Medium") -> 8
B48: Low | C48: =COUNTIF($C$16:$C$43,"Low") -> 15

Sheet Hist_IS
A1: VOLTAS LIMITED - HISTORICAL INCOME STATEMENT
A2: INR Crore unless stated
C4: HISTORICAL
A5: Particulars | B5: Unit | C5: Mar-23A | D5: Mar-24A | E5: Mar-25A | F5: Mar-26A
A6: SEGMENT REVENUE (Rs Cr)
A7: Unitary Cooling Products (RAC) | B7: Rs Cr | C7: 6475 | D7: 8160 | E7: 10614 | F7: 9501
A8: Electro-Mechanical Projects & Services (EMPS) | B8: Rs Cr | C8: 2403 | D8: 3683 | E8: 4157 | F8: 4053
A9: Engineering Products & Services | B9: Rs Cr | C9: 522 | D9: 588 | E9: 569 | F9: 599
A10: International Operations | B10: Rs Cr
A11: Others / Unallocated | B11: Rs Cr | C11: 99 | D11: 50 | E11: 73 | F11: 92
A12: Total Revenue from Operations | C12: =SUM(C7:C11) -> 9499 | D12: =SUM(D7:D11) -> 12481 | E12: =SUM(E7:E11) -> 15413 | F12: =SUM(F7:F11) -> 14245
A13: OPERATING EXPENSES (Rs Cr)
A14: Cost of Materials Consumed | B14: Rs Cr | C14: 4808 | D14: 6778 | E14: 8126 | F14: 8256
A15: Purchase of Stock-in-Trade | B15: Rs Cr | C15: 2296 | D15: 3427 | E15: 4017 | F15: 3083
A16: Changes in Inventories | B16: Rs Cr | C16: 274 | D16: -391 | E16: -183 | F16: -270
A17: Employee Benefit Expense | B17: Rs Cr | C17: 667 | D17: 779 | E17: 890 | F17: 939
A18: Sub-contracting / Erection Charges (EMPS) | B18: Rs Cr
A19: Other Expenses (Selling, Admin, Freight, Power) | B19: Rs Cr | C19: 881 | D19: 1414 | E19: 1446 | F19: 1589
A20: Total Expenses (before D&A and Finance Cost) | C20: =SUM(C14:C19) -> 8926 | D20: =SUM(D14:D19) -> 12007 | E20: =SUM(E14:E19) -> 14296 | F20: =SUM(F14:F19) -> 13597
A22: EBITDA | C22: =C12-C20 -> 573 | D22: =D12-D20 -> 474 | E22: =E12-E20 -> 1117 | F22: =F12-F20 -> 648
A23: EBITDA Margin % | C23: =C22/C12 -> 0.060322139 | D23: =D22/D12 -> 0.037977726 | E23: =E22/E12 -> 0.07247129 | F23: =F22/F12 -> 0.045489645
A24: Depreciation & Amortization | B24: Rs Cr | C24: 40 | D24: 48 | E24: 62 | F24: 84
A25: EBIT | C25: =C22-C24 -> 533 | D25: =D22-D24 -> 426 | E25: =E22-E24 -> 1055 | F25: =F22-F24 -> 564
A26: Finance Costs | B26: Rs Cr | C26: 30 | D26: 56 | E26: 62 | F26: 87
A27: Other Income | B27: Rs Cr | C27: 168 | D27: 253 | E27: 324 | F27: 238
A28: Share of Profit from Associates / JV | B28: Rs Cr | C28: -121 | D28: -139 | E28: -126 | F28: -131
A29: Exceptional Items | B29: Rs Cr | C29: -244 | D29: 0 | E29: 0 | F29: -26
A30: Profit Before Tax (PBT) | C30: =C25-C26+C27+C28+C29 -> 306 | D30: =D25-D26+D27+D28+D29 -> 484 | E30: =E25-E26+E27+E28+E29 -> 1191 | F30: =F25-F26+F27+F28+F29 -> 558
A31: Tax Expense (Current + Deferred) | B31: Rs Cr | C31: 171 | D31: 238 | E31: 356 | F31: 187
A32: Effective Tax Rate % | C32: =C31/C30 -> 0.55882353 | D32: =D31/D30 -> 0.49173554 | E32: =E31/E30 -> 0.29890848 | F32: =F31/F30 -> 0.33512545
A33: Profit After Tax (PAT) | C33: =C30-C31 -> 135 | D33: =D30-D31 -> 246 | E33: =E30-E31 -> 835 | F33: =F30-F31 -> 371
A34: Non-Controlling / Minority Interest | B34: Rs Cr
A35: Net Profit Attributable to Owners | C35: =C33-N(C34) -> 135 | D35: =D33-N(D34) -> 246 | E35: =E33-N(E34) -> 835 | F35: =F33-N(F34) -> 371
A37: Weighted Avg. Diluted Shares Outstanding (Cr) | B37: Cr Shares | C37: =Assumptions!$C$9 -> 33.08 | D37: =Assumptions!$C$9 -> 33.08 | E37: =Assumptions!$C$9 -> 33.08 | F37: =Assumptions!$C$9 -> 33.08
A38: Diluted EPS (Rs) | C38: =C35/C37 -> 4.0810157 | D38: =D35/D37 -> 7.4365175 | E38: =E35/E37 -> 25.241838 | F38: =F35/F37 -> 11.215236
A39: COMMON-SIZE ANALYSIS (% of Total Revenue)
A40: Cost of Materials Consumed % | C40: =C14/C12 -> 0.50615854 | D40: =D14/D12 -> 0.54306546 | E40: =E14/E12 -> 0.52721728 | F40: =F14/F12 -> 0.57957178
A41: Employee Cost % | C41: =C17/C12 -> 0.070217918 | D41: =D17/D12 -> 0.062414871 | E41: =E17/E12 -> 0.057743463 | F41: =F17/F12 -> 0.065917866
A42: Other Expenses % | C42: =C19/C12 -> 0.092746605 | D42: =D19/D12 -> 0.1132922 | E42: =E19/E12 -> 0.093816908 | F42: =F19/F12 -> 0.11154791
A43: EBITDA Margin % | C43: =C22/C12 -> 0.060322139 | D43: =D22/D12 -> 0.037977726 | E43: =E22/E12 -> 0.07247129 | F43: =F22/F12 -> 0.045489645
A44: EBIT Margin % | C44: =C25/C12 -> 0.05611117 | D44: =D25/D12 -> 0.03413188 | E44: =E25/E12 -> 0.068448712 | F44: =F25/F12 -> 0.03959284
A45: PAT Margin % | C45: =C33/C12 -> 0.014212022 | D45: =D33/D12 -> 0.019709959 | E45: =E33/E12 -> 0.054175047 | F45: =F33/F12 -> 0.026044226

Sheet Hist_BS
A1: VOLTAS LIMITED - HISTORICAL BALANCE SHEET
A2: INR Crore unless stated
C4: HISTORICAL
A5: Particulars | B5: Unit | C5: Mar-23A | D5: Mar-24A | E5: Mar-25A | F5: Mar-26A
A6: EQUITY & LIABILITIES
A7: Share Capital | B7: Rs Cr | C7: 33 | D7: 33 | E7: 33 | F7: 33
A8: Other Equity (Reserves & Surplus) | B8: Rs Cr | C8: 5419 | D8: 5787 | E8: 6480 | F8: 6343
A9: Non-Controlling Interest | B9: Rs Cr | C9: 42 | D9: 34 | E9: 27 | F9: 23
A10: Total Equity | C10: =SUM(C7:C9) -> 5494 | D10: =SUM(D7:D9) -> 5854 | E10: =SUM(E7:E9) -> 6540 | F10: =SUM(F7:F9) -> 6399
A12: Long Term Borrowings | B12: Rs Cr | C12: 21 | D12: 228 | E12: 383 | F12: 376
A13: Lease Liabilities (Non-Current) | B13: Rs Cr | C13: 25 | D13: 21 | E13: 18 | F13: 15
A14: Deferred Tax Liabilities (Net) | B14: Rs Cr | C14: 5 | D14: 59 | E14: 58 | F14: 14
A15: Other Non-Current Liabilities & Provisions | B15: Rs Cr | C15: 114 | D15: 117 | E15: 147 | F15: 152
A16: Total Non-Current Liabilities | C16: =SUM(C12:C15) -> 165 | D16: =SUM(D12:D15) -> 425 | E16: =SUM(E12:E15) -> 606 | F16: =SUM(F12:F15) -> 557
A18: Short Term Borrowings | B18: Rs Cr | C18: 595 | D18: 485 | E18: 481 | F18: 591
A19: Lease Liabilities (Current) | B19: Rs Cr | C19: 9 | D19: 9 | E19: 11 | F19: 11
A20: Trade Payables | B20: Rs Cr | C20: 3013 | D20: 3856 | E20: 3893 | F20: 5228
A21: Other Current Liabilities & Provisions | B21: Rs Cr | C21: 1003 | D21: 1406 | E21: 1621 | F21: 1724
A22: Total Current Liabilities | C22: =SUM(C18:C21) -> 4620 | D22: =SUM(D18:D21) -> 5756 | E22: =SUM(E18:E21) -> 6006 | F22: =SUM(F18:F21) -> 7554
A23: TOTAL EQUITY & LIABILITIES | C23: =C10+C16+C22 -> 10279 | D23: =D10+D16+D22 -> 12035 | E23: =E10+E16+E22 -> 13152 | F23: =F10+F16+F22 -> 14510
A25: ASSETS
A26: Net Block - Property, Plant & Equipment | B26: Rs Cr | C26: 361 | D26: 390 | E26: 820 | F26: 935
A27: Capital Work in Progress | B27: Rs Cr | C27: 98 | D27: 368 | E27: 82 | F27: 22
A28: Right-of-Use Assets | B28: Rs Cr | C28: 36 | D28: 35 | E28: 34 | F28: 32
A29: Intangible Assets & Goodwill | B29: Rs Cr | C29: 79 | D29: 78 | E29: 76 | F29: 76
A30: Non-Current Investments | B30: Rs Cr | C30: 2531 | D30: 2768 | E30: 2638 | F30: 2307
A31: Deferred Tax Assets (Net) | B31: Rs Cr | C31: 36 | D31: 41 | E31: 44 | F31: 51
A32: Other Non-Current Assets | B32: Rs Cr | C32: 692 | D32: 632 | E32: 580 | F32: 758
A33: Total Non-Current Assets | C33: =SUM(C26:C32) -> 3833 | D33: =SUM(D26:D32) -> 4312 | E33: =SUM(E26:E32) -> 4274 | F33: =SUM(F26:F32) -> 4181
A35: Inventories | B35: Rs Cr | C35: 1592 | D35: 2135 | E35: 2715 | F35: 3433
A36: Trade Receivables | B36: Rs Cr | C36: 2192 | D36: 2533 | E36: 2511 | F36: 3035
A37: Cash & Cash Equivalents | B37: Rs Cr | C37: 708 | D37: 852 | E37: 678 | F37: 781
A38: Current Investments | B38: Rs Cr | C38: 307 | D38: 501 | E38: 399 | F38: 277
A39: Contract Assets | B39: Rs Cr | C39: 978 | D39: 744 | E39: 1300 | F39: 1867
A40: Other Current Assets (incl. Unbilled Revenue) | B40: Rs Cr | C40: 669 | D40: 959 | E40: 1275 | F40: 936
A41: Total Current Assets | C41: =SUM(C35:C40) -> 6446 | D41: =SUM(D35:D40) -> 7724 | E41: =SUM(E35:E40) -> 8878 | F41: =SUM(F35:F40) -> 10329
A42: TOTAL ASSETS | C42: =C33+C41 -> 10279 | D42: =D33+D41 -> 12036 | E42: =E33+E41 -> 13152 | F42: =F33+F41 -> 14510
A44: Check: Total Assets - Total Equity & Liabilities (rounding in source data) | C44: =C42-C23 -> 0 | D44: =D42-D23 -> 1 | E44: =E42-E23 -> 0 | F44: =F42-F23 -> 0

Sheet Hist_CF
A1: VOLTAS LIMITED - HISTORICAL CASH FLOW STATEMENT (Indirect Method)
A2: INR Crore unless stated
C4: HISTORICAL
A5: Particulars | B5: Unit | C5: Mar-23A | D5: Mar-24A | E5: Mar-25A | F5: Mar-26A
A6: CASH FLOW FROM OPERATING ACTIVITIES
A7: Profit Before Tax | C7: =Hist_IS!C30 -> 306 | D7: =Hist_IS!D30 -> 484 | E7: =Hist_IS!E30 -> 1191 | F7: =Hist_IS!F30 -> 558
A8: Add: Depreciation & Amortization | C8: =Hist_IS!C24 -> 40 | D8: =Hist_IS!D24 -> 48 | E8: =Hist_IS!E24 -> 62 | F8: =Hist_IS!F24 -> 84
A9: Add: Finance Costs | C9: =Hist_IS!C26 -> 30 | D9: =Hist_IS!D26 -> 56 | E9: =Hist_IS!E26 -> 62 | F9: =Hist_IS!F26 -> 87
A10: Other Non-Cash Adjustments | B10: Rs Cr | C10: 333 | D10: 304 | E10: -134 | F10: -95
A11: Changes in Working Capital | B11: Rs Cr | C11: -384 | D11: 80 | E11: -1094 | F11: -352
A12: Less: Direct Taxes Paid | B12: Rs Cr | C12: -166 | D12: -212 | E12: -311 | F12: -211
A13: Net Cash from Operating Activities (CFO) | C13: =SUM(C7:C12) -> 159 | D13: =SUM(D7:D12) -> 760 | E13: =SUM(E7:E12) -> -224 | F13: =SUM(F7:F12) -> 71
A15: CASH FLOW FROM INVESTING ACTIVITIES
A16: Purchase of PPE / Capex | B16: Rs Cr | C16: -180 | D16: -293 | E16: -208 | F16: -133
A17: Proceeds from Sale of Assets | B17: Rs Cr | C17: 2 | D17: 5 | E17: 17 | F17: 4
A18: Purchase/Sale of Investments (Net) | B18: Rs Cr | C18: 25 | D18: -318 | E18: 218 | F18: 306
A19: Interest & Dividend Received | B19: Rs Cr | C19: 71 | D19: 83 | E19: 131 | F19: 105
A20: Net Cash from Investing Activities (CFI) | C20: =SUM(C16:C19) -> -82 | D20: =SUM(D16:D19) -> -523 | E20: =SUM(E16:E19) -> 158 | F20: =SUM(F16:F19) -> 282
A22: CASH FLOW FROM FINANCING ACTIVITIES
A23: Proceeds from Borrowings | B23: Rs Cr | C23: 1504 | D23: 590 | E23: 454 | F23: 2112
A24: Repayment of Borrowings | B24: Rs Cr | C24: -1231 | D24: -493 | E24: -304 | F24: -2039
A25: Payment of Lease Liabilities | B25: Rs Cr | C25: -10 | D25: -18 | E25: -14 | F25: -14
A26: Interest Paid | B26: Rs Cr | C26: -25 | D26: -52 | E26: -54 | F26: -89
A27: Dividend Paid | B27: Rs Cr | C27: -183 | D27: -143 | E27: -182 | F27: -232
A28: Buyback of Shares / Other | B28: Rs Cr | C28: 0 | D28: 0 | E28: 0 | F28: 0
A29: Net Cash from Financing Activities (CFF) | C29: =SUM(C23:C28) -> 55 | D29: =SUM(D23:D28) -> -116 | E29: =SUM(E23:E28) -> -100 | F29: =SUM(F23:F28) -> -262
A31: Net Increase / (Decrease) in Cash | C31: =C13+C20+C29 -> 132 | D31: =D13+D20+D29 -> 121 | E31: =E13+E20+E29 -> -166 | F31: =F13+F20+F29 -> 91
A32: Opening Cash & Cash Equivalents | B32: Rs Cr | C32: 561 | D32: 693 | E32: 816 | F32: 650
A33: Closing Cash & Cash Equivalents | C33: =C32+C31 -> 693 | D33: =D32+D31 -> 814 | E33: =E32+E31 -> 650 | F33: =F32+F31 -> 741
A35: Free Cash Flow to Firm proxy (CFO - Capex) | C35: =C13+C16 -> -21 | D35: =D13+D16 -> 467 | E35: =E13+E16 -> -432 | F35: =F13+F16 -> -62
A36: RECONCILIATION CHECKS (added)
A37: Cash & cash equivalents per Balance Sheet | C37: =Hist_BS!C37 -> 708 | D37: =Hist_BS!D37 -> 852 | E37: =Hist_BS!E37 -> 678 | F37: =Hist_BS!F37 -> 781
A38: Difference: CF closing cash - Balance Sheet cash | C38: =C33-C37 -> -15 | D38: =D33-D37 -> -38 | E38: =E33-E37 -> -28 | F38: =F33-F37 -> -40
A39: Difference: CF opening cash - prior year CF closing cash | D39: =D32-C33 -> 0 | E39: =E32-D33 -> 2 | F39: =F32-E33 -> 0

Sheet Assumptions
A1: VOLTAS LIMITED - MASTER ASSUMPTIONS
A2: INR Crore unless stated
C4: HISTORICAL | G4: FORECAST
A5: Particulars | B5: Unit | C5: Mar-23A | D5: Mar-24A | E5: Mar-25A | F5: Mar-26A | G5: Mar-27E | H5: Mar-28E | I5: Mar-29E | J5: Mar-30E | K5: Mar-31E
A6: A. GENERAL
A7: Date of valuation | B7: text | C7: 19-Oct-2026
A8: Current market price used in valuation (Rs per share) | B8: Rs | C8: 1033
A9: Diluted shares outstanding (Cr) | B9: Cr | C9: 33.08
A10: B. SEGMENT 1 - UNITARY COOLING PRODUCTS (ROOM AC & COOLERS)
A11: RAC Industry Volume Growth % | B11: % | G11: 0.16 | H11: 0.11 | I11: 0.1 | J11: 0.09 | K11: 0.08
A12: Voltas Market Share % | B12: % | F12: 0.16 | G12: 0.16 | H12: 0.165 | I12: 0.168 | J12: 0.17 | K12: 0.174
A13: Implied Voltas Volume Growth % | B13: % | G13: =(1+G11)*G12/F12-1 -> 0.16 | H13: =(1+H11)*H12/G12-1 -> 0.1446875 | I13: =(1+I11)*I12/H12-1 -> 0.12 | J13: =(1+J11)*J12/I12-1 -> 0.10297619 | K13: =(1+K11)*K12/J12-1 -> 0.10541176
A14: Realization / ASP Growth % (Price Increase) | B14: % | G14: 0.06 | H14: 0.035 | I14: 0.03 | J14: 0.025 | K14: 0.025
A15: C. SEGMENT 2 - ELECTRO-MECHANICAL PROJECTS & SERVICES (EMPS)
A16: New Order Inflow Growth % | B16: % | G16: 0.06 | H16: 0.055 | I16: 0.05 | J16: 0.045 | K16: 0.045
A17: Order Book Execution Rate % (Revenue Recognition) | B17: % | G17: 0.39 | H17: 0.395 | I17: 0.4 | J17: 0.405 | K17: 0.41
A18: D. SEGMENT 3 - ENGINEERING PRODUCTS & SERVICES
A19: Engineering Products Segment Revenue Growth % | B19: % | D19: =Hist_IS!D9/Hist_IS!C9-1 -> 0.12643678 | E19: =Hist_IS!E9/Hist_IS!D9-1 -> -0.032312925 | F19: =Hist_IS!F9/Hist_IS!E9-1 -> 0.052724077 | G19: 0.049 | H19: 0.049 | I19: 0.049 | J19: 0.049 | K19: 0.049
A20: E. MARGIN & COST ASSUMPTIONS (% of Revenue unless noted)
A21: COGS % | B21: % | C21: =(Hist_IS!C14+Hist_IS!C15+Hist_IS!C16)/Hist_IS!C12 -> 0.77671334 | D21: =(Hist_IS!D14+Hist_IS!D15+Hist_IS!D16)/Hist_IS!D12 -> 0.7863152 | E21: =(Hist_IS!E14+Hist_IS!E15+Hist_IS!E16)/Hist_IS!E12 -> 0.77596834 | F21: =(Hist_IS!F14+Hist_IS!F15+Hist_IS!F16)/Hist_IS!F12 -> 0.77704458 | G21: 0.777 | H21: 0.776 | I21: 0.775 | J21: 0.775 | K21: 0.774
A22: Employee Cost % | B22: % | C22: =Hist_IS!C17/Hist_IS!C12 -> 0.070217918 | D22: =Hist_IS!D17/Hist_IS!D12 -> 0.062414871 | E22: =Hist_IS!E17/Hist_IS!E12 -> 0.057743463 | F22: =Hist_IS!F17/Hist_IS!F12 -> 0.065917866 | G22: 0.06 | H22: 0.06 | I22: 0.06 | J22: 0.06 | K22: 0.06
A23: Other Expenses (Selling+Mktg+Admin+Warranty+Other) % | B23: % | C23: =Hist_IS!C19/Hist_IS!C12 -> 0.092746605 | D23: =Hist_IS!D19/Hist_IS!D12 -> 0.1132922 | E23: =Hist_IS!E19/Hist_IS!E12 -> 0.093816908 | F23: =Hist_IS!F19/Hist_IS!F12 -> 0.11154791 | G23: 0.1 | H23: 0.095 | I23: 0.093 | J23: 0.093 | K23: 0.093
A24: Implied EBITDA Margin % (memo, computed on Cost_Schedule) | B24: % | C24: =Cost_Schedule!C19 -> 0.060322139 | D24: =Cost_Schedule!D19 -> 0.037977726 | E24: =Cost_Schedule!E19 -> 0.07247129 | F24: =Cost_Schedule!F19 -> 0.045489645 | G24: =Cost_Schedule!G19 -> 0.063 | H24: =Cost_Schedule!H19 -> 0.069 | I24: =Cost_Schedule!I19 -> 0.072 | J24: =Cost_Schedule!J19 -> 0.072 | K24: =Cost_Schedule!K19 -> 0.073
A25: Effective Tax Rate % | B25: % | G25: 0.3 | H25: 0.3 | I25: 0.3 | J25: 0.3 | K25: 0.3
A26: F. WORKING CAPITAL ASSUMPTIONS (Days)
A27: Receivable Days (DSO, on revenue) | B27: Days | G27: 71 | H27: 77 | I27: 76 | J27: 77 | K27: 76
A28: Inventory Days (DIO, on COGS) | B28: Days | G28: 102 | H28: 97 | I28: 95 | J28: 97 | K28: 94
A29: Payable Days (DPO, on COGS) | B29: Days | G29: 158 | H29: 153 | I29: 153 | J29: 150 | K29: 150
A30: Other Current Assets Days (on revenue) - values USED by WC_Schedule | B30: Days | G30: 67 | H30: 63 | I30: 61 | J30: 61 | K30: 60
A31: Memo: value DISPLAYED on published Assumptions page (not used - see Error_Log E-05) | B31: Days | G31: 25 | H31: 25 | I31: 25 | J31: 25 | K31: 25
A32: Other Current Liabilities Days (on revenue) | B32: Days | G32: 40 | H32: 40 | I32: 40 | J32: 40 | K32: 40
A33: G. DEBT & FINANCING ASSUMPTIONS
A34: LT Debt Repayment % of Opening Balance | B34: % | G34: 0.15 | H34: 0.15 | I34: 0.15 | J34: 0.15 | K34: 0.15
A35: ST Borrowings % (Receivables + Inventory) | B35: % | C35: =Hist_BS!C18/(Hist_BS!C36+Hist_BS!C35) -> 0.15724101 | D35: =Hist_BS!D18/(Hist_BS!D36+Hist_BS!D35) -> 0.10389889 | E35: =Hist_BS!E18/(Hist_BS!E36+Hist_BS!E35) -> 0.092039801 | F35: =Hist_BS!F18/(Hist_BS!F36+Hist_BS!F35) -> 0.091372913 | G35: 0.095 | H35: 0.093 | I35: 0.093 | J35: 0.093 | K35: 0.093
A36: Average Interest Rate LT (NOT USED in model - see Error_Log E-12) | B36: % | G36: 0.07 | H36: 0.072 | I36: 0.069 | J36: 0.067 | K36: 0.067
A37: Average Interest Rate ST (NOT USED in model - see Error_Log E-12) | B37: % | G37: 0.079 | H37: 0.08 | I37: 0.077 | J37: 0.075 | K37: 0.075
A38: Finance Cost % Revenue (inputs set to reproduce published output; page shows 0.6/0.6/0.5/0.5/0.5) | B38: % | C38: =Hist_IS!C26/Hist_IS!C12 -> 0.0031582272 | D38: =Hist_IS!D26/Hist_IS!D12 -> 0.00448682 | E38: =Hist_IS!E26/Hist_IS!E12 -> 0.0040225783 | F38: =Hist_IS!F26/Hist_IS!F12 -> 0.0061074061 | G38: 0.0061 | H38: 0.0055 | I38: 0.005 | J38: 0.005 | K38: 0.005
A39: Other Income % Revenue (inputs set to reproduce published output; page shows 2.0/1.8/2.0/1.9/2.0) | B39: % | C39: =Hist_IS!C27/Hist_IS!C12 -> 0.017686072 | D39: =Hist_IS!D27/Hist_IS!D12 -> 0.020270812 | E39: =Hist_IS!E27/Hist_IS!E12 -> 0.021021216 | F39: =Hist_IS!F27/Hist_IS!F12 -> 0.016707617 | G39: 0.02 | H39: 0.018 | I39: 0.02 | J39: 0.0187 | K39: 0.02
A40: H. DIVIDEND
A41: Dividend per share (Rs) - held flat | B41: Rs | G41: 4 | H41: 4 | I41: 4 | J41: 4 | K41: 4

Sheet Revenue_Build
A1: VOLTAS LIMITED - SEGMENT REVENUE BUILD-UP (Volume x Realization)
A2: INR Crore unless stated
C4: HISTORICAL | G4: FORECAST
A5: Particulars | B5: Unit | C5: Mar-23A | D5: Mar-24A | E5: Mar-25A | F5: Mar-26A | G5: Mar-27E | H5: Mar-28E | I5: Mar-29E | J5: Mar-30E | K5: Mar-31E
A6: SEGMENT 1: UNITARY COOLING PRODUCTS (ROOM AC & COOLERS)
A7: Volume Growth % YoY | G7: =Assumptions!G13 -> 0.16 | H7: =Assumptions!H13 -> 0.1446875 | I7: =Assumptions!I13 -> 0.12 | J7: =Assumptions!J13 -> 0.10297619 | K7: =Assumptions!K13 -> 0.10541176
A8: Realization / ASP Growth % YoY | G8: =Assumptions!G14 -> 0.06 | H8: =Assumptions!H14 -> 0.035 | I8: =Assumptions!I14 -> 0.03 | J8: =Assumptions!J14 -> 0.025 | K8: =Assumptions!K14 -> 0.025
A9: RAC Segment Revenue | C9: =Hist_IS!C7 -> 6475 | D9: =Hist_IS!D7 -> 8160 | E9: =Hist_IS!E7 -> 10614 | F9: =Hist_IS!F7 -> 9501 | G9: =F9*(1+G7)*(1+G8) -> 11682.43 | H9: =G9*(1+H7)*(1+H8) -> 13840.777 | I9: =H9*(1+I7)*(1+I8) -> 15966.72 | J9: =I9*(1+J7)*(1+J8) -> 18051.185 | K9: =J9*(1+K7)*(1+K8) -> 20452.842
A10: SEGMENT 2: ELECTRO-MECHANICAL PROJECTS & SERVICES (EMPS)
A11: Opening Order Book | G11: =F15 -> 6200 | H11: =G15 -> 6497.72 | I11: =H15 -> 6772.7209 | J11: =I15 -> 7022.6543 | K11: =J15 -> 7244.889
A12: New Order Inflow | F12: 4200 | G12: =F12*(1+Assumptions!G16) -> 4452 | H12: =G12*(1+Assumptions!H16) -> 4696.86 | I12: =H12*(1+Assumptions!I16) -> 4931.703 | J12: =I12*(1+Assumptions!J16) -> 5153.6296 | K12: =J12*(1+Assumptions!K16) -> 5385.543
A13: Execution Rate % (of Opening OB + New Orders) | C13: 0.245 | D13: 0.314 | E13: 0.39 | F13: 0.395 | G13: =Assumptions!G17 -> 0.39 | H13: =Assumptions!H17 -> 0.395 | I13: =Assumptions!I17 -> 0.4 | J13: =Assumptions!J17 -> 0.405 | K13: =Assumptions!K17 -> 0.41
A14: EMPS Segment Revenue (Revenue Recognized) | C14: =Hist_IS!C8 -> 2403 | D14: =Hist_IS!D8 -> 3683 | E14: =Hist_IS!E8 -> 4157 | F14: =Hist_IS!F8 -> 4053 | G14: =G13*(G11+G12) -> 4154.28 | H14: =H13*(H11+H12) -> 4421.8591 | I14: =I13*(I11+I12) -> 4681.7696 | J14: =J13*(J11+J12) -> 4931.395 | K14: =K13*(K11+K12) -> 5178.4771
A15: Closing Order Book | C15: 7414 | D15: 8054 | E15: 6500 | F15: 6200 | G15: =G11+G12-G14 -> 6497.72 | H15: =H11+H12-H14 -> 6772.7209 | I15: =I11+I12-I14 -> 7022.6543 | J15: =J11+J12-J14 -> 7244.889 | K15: =K11+K12-K14 -> 7451.9548
A16: Check: FY26 execution rate recomputed = EMPS revenue / (FY25 closing OB + FY26 new orders) | F16: =F14/(E15+F12) -> 0.37878505
A17: Check: FY26 order-book roll-forward = Opening OB + New orders - Revenue - Closing OB (should be 0) | F17: =E15+F12-F14-F15 -> 447
A18: SEGMENT 3: ENGINEERING PRODUCTS & SERVICES
A19: Segment Revenue Growth % YoY | D19: =D20/C20-1 -> 0.12643678 | E19: =E20/D20-1 -> -0.032312925 | F19: =F20/E20-1 -> 0.052724077 | G19: =Assumptions!G19 -> 0.049 | H19: =Assumptions!H19 -> 0.049 | I19: =Assumptions!I19 -> 0.049 | J19: =Assumptions!J19 -> 0.049 | K19: =Assumptions!K19 -> 0.049
A20: Engineering Products & Services Revenue | C20: =Hist_IS!C9 -> 522 | D20: =Hist_IS!D9 -> 588 | E20: =Hist_IS!E9 -> 569 | F20: =Hist_IS!F9 -> 599 | G20: =F20*(1+G19) -> 628.351 | H20: =G20*(1+H19) -> 659.1402 | I20: =H20*(1+I19) -> 691.43807 | J20: =I20*(1+J19) -> 725.31853 | K20: =J20*(1+K19) -> 760.85914
A22: Others / Unallocated Revenue | C22: =Hist_IS!C11 -> 99 | D22: =Hist_IS!D11 -> 50 | E22: =Hist_IS!E11 -> 73 | F22: =Hist_IS!F11 -> 92 | G22: =F22 -> 92 | H22: =G22 -> 92 | I22: =H22 -> 92 | J22: =I22 -> 92 | K22: =J22 -> 92
A24: TOTAL REVENUE FROM OPERATIONS | C24: =C9+C14+C20+C22 -> 9499 | D24: =D9+D14+D20+D22 -> 12481 | E24: =E9+E14+E20+E22 -> 15413 | F24: =F9+F14+F20+F22 -> 14245 | G24: =G9+G14+G20+G22 -> 16557.061 | H24: =H9+H14+H20+H22 -> 19013.776 | I24: =I9+I14+I20+I22 -> 21431.928 | J24: =J9+J14+J20+J22 -> 23799.898 | K24: =K9+K14+K20+K22 -> 26484.178

Sheet Cost_Schedule
A1: VOLTAS LIMITED - OPERATING COST DRIVER SCHEDULE
A2: INR Crore unless stated
C4: HISTORICAL | G4: FORECAST
A5: Particulars | B5: Unit | C5: Mar-23A | D5: Mar-24A | E5: Mar-25A | F5: Mar-26A | G5: Mar-27E | H5: Mar-28E | I5: Mar-29E | J5: Mar-30E | K5: Mar-31E
A6: Total Revenue (link) | C6: =Revenue_Build!C24 -> 9499 | D6: =Revenue_Build!D24 -> 12481 | E6: =Revenue_Build!E24 -> 15413 | F6: =Revenue_Build!F24 -> 14245 | G6: =Revenue_Build!G24 -> 16557.061 | H6: =Revenue_Build!H24 -> 19013.776 | I6: =Revenue_Build!I24 -> 21431.928 | J6: =Revenue_Build!J24 -> 23799.898 | K6: =Revenue_Build!K24 -> 26484.178
A8: Cost of Goods Sold - % of Revenue | C8: =Assumptions!C21 -> 0.77671334 | D8: =Assumptions!D21 -> 0.7863152 | E8: =Assumptions!E21 -> 0.77596834 | F8: =Assumptions!F21 -> 0.77704458 | G8: =Assumptions!G21 -> 0.777 | H8: =Assumptions!H21 -> 0.776 | I8: =Assumptions!I21 -> 0.775 | J8: =Assumptions!J21 -> 0.775 | K8: =Assumptions!K21 -> 0.774
A9: Cost of Goods Sold | C9: =Hist_IS!C14+Hist_IS!C15+Hist_IS!C16 -> 7378 | D9: =Hist_IS!D14+Hist_IS!D15+Hist_IS!D16 -> 9814 | E9: =Hist_IS!E14+Hist_IS!E15+Hist_IS!E16 -> 11960 | F9: =Hist_IS!F14+Hist_IS!F15+Hist_IS!F16 -> 11069 | G9: =G6*G8 -> 12864.836 | H9: =H6*H8 -> 14754.69 | I9: =I6*I8 -> 16609.744 | J9: =J6*J8 -> 18444.921 | K9: =K6*K8 -> 20498.754
A11: Employee Benefit Expense - % of Revenue | C11: =Assumptions!C22 -> 0.070217918 | D11: =Assumptions!D22 -> 0.062414871 | E11: =Assumptions!E22 -> 0.057743463 | F11: =Assumptions!F22 -> 0.065917866 | G11: =Assumptions!G22 -> 0.06 | H11: =Assumptions!H22 -> 0.06 | I11: =Assumptions!I22 -> 0.06 | J11: =Assumptions!J22 -> 0.06 | K11: =Assumptions!K22 -> 0.06
A12: Employee Benefit Expense | C12: =Hist_IS!C17 -> 667 | D12: =Hist_IS!D17 -> 779 | E12: =Hist_IS!E17 -> 890 | F12: =Hist_IS!F17 -> 939 | G12: =G6*G11 -> 993.42364 | H12: =H6*H11 -> 1140.8266 | I12: =I6*I11 -> 1285.9157 | J12: =J6*J11 -> 1427.9939 | K12: =K6*K11 -> 1589.0507
A14: Other Expenses (Selling+Mktg+Admin+Other) - % of Revenue | C14: =Assumptions!C23 -> 0.092746605 | D14: =Assumptions!D23 -> 0.1132922 | E14: =Assumptions!E23 -> 0.093816908 | F14: =Assumptions!F23 -> 0.11154791 | G14: =Assumptions!G23 -> 0.1 | H14: =Assumptions!H23 -> 0.095 | I14: =Assumptions!I23 -> 0.093 | J14: =Assumptions!J23 -> 0.093 | K14: =Assumptions!K23 -> 0.093
A15: Other Expenses (published label: "Sub-Contracting / Erection Charges (EMPS)" - mislabelled, see E-11) | C15: =Hist_IS!C19 -> 881 | D15: =Hist_IS!D19 -> 1414 | E15: =Hist_IS!E19 -> 1446 | F15: =Hist_IS!F19 -> 1589 | G15: =G6*G14 -> 1655.7061 | H15: =H6*H14 -> 1806.3087 | I15: =I6*I14 -> 1993.1693 | J15: =J6*J14 -> 2213.3905 | K15: =K6*K14 -> 2463.0286
A17: Total Operating Expenses | C17: =C9+C12+C15 -> 8926 | D17: =D9+D12+D15 -> 12007 | E17: =E9+E12+E15 -> 14296 | F17: =F9+F12+F15 -> 13597 | G17: =G9+G12+G15 -> 15513.966 | H17: =H9+H12+H15 -> 17701.825 | I17: =I9+I12+I15 -> 19888.829 | J17: =J9+J12+J15 -> 22086.306 | K17: =K9+K12+K15 -> 24550.833
A18: EBITDA (Revenue - Total Operating Expenses) | C18: =C6-C17 -> 573 | D18: =D6-D17 -> 474 | E18: =E6-E17 -> 1117 | F18: =F6-F17 -> 648 | G18: =G6-G17 -> 1043.0948 | H18: =H6-H17 -> 1311.9505 | I18: =I6-I17 -> 1543.0988 | J18: =J6-J17 -> 1713.5927 | K18: =K6-K17 -> 1933.345
A19: EBITDA Margin % | C19: =C18/C6 -> 0.060322139 | D19: =D18/D6 -> 0.037977726 | E19: =E18/E6 -> 0.07247129 | F19: =F18/F6 -> 0.045489645 | G19: =G18/G6 -> 0.063 | H19: =H18/H6 -> 0.069 | I19: =I18/I6 -> 0.072 | J19: =J18/J6 -> 0.072 | K19: =K18/K6 -> 0.073

Sheet WC_Schedule
A1: VOLTAS LIMITED - WORKING CAPITAL SCHEDULE
A2: INR Crore unless stated
C4: HISTORICAL | G4: FORECAST
A5: Particulars | B5: Unit | C5: Mar-23A | D5: Mar-24A | E5: Mar-25A | F5: Mar-26A | G5: Mar-27E | H5: Mar-28E | I5: Mar-29E | J5: Mar-30E | K5: Mar-31E
A6: Total Revenue (link) | C6: =Cost_Schedule!C6 -> 9499 | D6: =Cost_Schedule!D6 -> 12481 | E6: =Cost_Schedule!E6 -> 15413 | F6: =Cost_Schedule!F6 -> 14245 | G6: =Cost_Schedule!G6 -> 16557.061 | H6: =Cost_Schedule!H6 -> 19013.776 | I6: =Cost_Schedule!I6 -> 21431.928 | J6: =Cost_Schedule!J6 -> 23799.898 | K6: =Cost_Schedule!K6 -> 26484.178
A7: Cost of Goods Sold | C7: =Cost_Schedule!C9 -> 7378 | D7: =Cost_Schedule!D9 -> 9814 | E7: =Cost_Schedule!E9 -> 11960 | F7: =Cost_Schedule!F9 -> 11069 | G7: =Cost_Schedule!G9 -> 12864.836 | H7: =Cost_Schedule!H9 -> 14754.69 | I7: =Cost_Schedule!I9 -> 16609.744 | J7: =Cost_Schedule!J9 -> 18444.921 | K7: =Cost_Schedule!K9 -> 20498.754
A8: DAYS OUTSTANDING (Historical = computed | Forecast = Assumptions link)
A9: Trade Receivable Days (on Revenue) | C9: =Hist_BS!C36/C6*365 -> 84.227813 | D9: =Hist_BS!D36/D6*365 -> 74.076196 | E9: =Hist_BS!E36/E6*365 -> 59.463764 | F9: =Hist_BS!F36/F6*365 -> 77.765883 | G9: =Assumptions!G27 -> 71 | H9: =Assumptions!H27 -> 77 | I9: =Assumptions!I27 -> 76 | J9: =Assumptions!J27 -> 77 | K9: =Assumptions!K27 -> 76
A10: Inventory Days (on COGS) | C10: =Hist_BS!C35/C7*365 -> 78.758471 | D10: =Hist_BS!D35/D7*365 -> 79.404422 | E10: =Hist_BS!E35/E7*365 -> 82.857441 | F10: =Hist_BS!F35/F7*365 -> 113.20309 | G10: =Assumptions!G28 -> 102 | H10: =Assumptions!H28 -> 97 | I10: =Assumptions!I28 -> 95 | J10: =Assumptions!J28 -> 97 | K10: =Assumptions!K28 -> 94
A11: Trade Payable Days (on COGS) | C11: =Hist_BS!C20/C7*365 -> 149.05733 | D11: =Hist_BS!D20/D7*365 -> 143.41145 | E11: =Hist_BS!E20/E7*365 -> 118.80811 | F11: =Hist_BS!F20/F7*365 -> 172.39317 | G11: =Assumptions!G29 -> 158 | H11: =Assumptions!H29 -> 153 | I11: =Assumptions!I29 -> 153 | J11: =Assumptions!J29 -> 150 | K11: =Assumptions!K29 -> 150
A12: Other Current Assets Days (on Revenue) | C12: =(Hist_BS!C39+Hist_BS!C40)/C6*365 -> 63.286135 | D12: =(Hist_BS!D39+Hist_BS!D40)/D6*365 -> 49.803301 | E12: =(Hist_BS!E39+Hist_BS!E40)/E6*365 -> 60.979368 | F12: =(Hist_BS!F39+Hist_BS!F40)/F6*365 -> 71.821341 | G12: =Assumptions!G30 -> 67 | H12: =Assumptions!H30 -> 63 | I12: =Assumptions!I30 -> 61 | J12: =Assumptions!J30 -> 61 | K12: =Assumptions!K30 -> 60
A13: Other Current Liabilities Days (on Revenue) | C13: =Hist_BS!C21/C6*365 -> 38.540373 | D13: =Hist_BS!D21/D6*365 -> 41.117699 | E13: =Hist_BS!E21/E6*365 -> 38.3874 | F13: =Hist_BS!F21/F6*365 -> 44.174096 | G13: =Assumptions!G32 -> 40 | H13: =Assumptions!H32 -> 40 | I13: =Assumptions!I32 -> 40 | J13: =Assumptions!J32 -> 40 | K13: =Assumptions!K32 -> 40
A14: WORKING CAPITAL BALANCES (Rs Cr)
A15: Trade Receivables | C15: =Hist_BS!C36 -> 2192 | D15: =Hist_BS!D36 -> 2533 | E15: =Hist_BS!E36 -> 2511 | F15: =Hist_BS!F36 -> 3035 | G15: =G6*G9/365 -> 3220.6885 | H15: =H6*H9/365 -> 4011.1254 | I15: =I6*I9/365 -> 4462.5384 | J15: =J6*J9/365 -> 5020.8005 | K15: =K6*K9/365 -> 5514.5138
A16: Inventories | C16: =Hist_BS!C35 -> 1592 | D16: =Hist_BS!D35 -> 2135 | E16: =Hist_BS!E35 -> 2715 | F16: =Hist_BS!F35 -> 3433 | G16: =G7*G10/365 -> 3595.1049 | H16: =H7*H10/365 -> 3921.1094 | I16: =I7*I10/365 -> 4323.084 | J16: =J7*J10/365 -> 4901.801 | K16: =K7*K10/365 -> 5279.1311
A17: Other Current Assets (incl. contract assets) | C17: =Hist_BS!C39+Hist_BS!C40 -> 1647 | D17: =Hist_BS!D39+Hist_BS!D40 -> 1703 | E17: =Hist_BS!E39+Hist_BS!E40 -> 2575 | F17: =Hist_BS!F39+Hist_BS!F40 -> 2803 | G17: =G6*G12/365 -> 3039.2413 | H17: =H6*H12/365 -> 3281.8298 | I17: =I6*I12/365 -> 3581.7742 | J17: =J6*J12/365 -> 3977.5173 | K17: =K6*K12/365 -> 4353.5635
A18: Trade Payables | C18: =Hist_BS!C20 -> 3013 | D18: =Hist_BS!D20 -> 3856 | E18: =Hist_BS!E20 -> 3893 | F18: =Hist_BS!F20 -> 5228 | G18: =G7*G11/365 -> 5568.8879 | H18: =H7*H11/365 -> 6184.8427 | I18: =I7*I11/365 -> 6962.4406 | J18: =J7*J11/365 -> 7580.1046 | K18: =K7*K11/365 -> 8424.1454
A19: Other Current Liabilities | C19: =Hist_BS!C21 -> 1003 | D19: =Hist_BS!D21 -> 1406 | E19: =Hist_BS!E21 -> 1621 | F19: =Hist_BS!F21 -> 1724 | G19: =G6*G13/365 -> 1814.4724 | H19: =H6*H13/365 -> 2083.7015 | I19: =I6*I13/365 -> 2348.7044 | J19: =J6*J13/365 -> 2608.208 | K19: =K6*K13/365 -> 2902.3757
A21: Net Working Capital (AR+Inv+OCA-AP-OCL) | C21: =C15+C16+C17-C18-C19 -> 1415 | D21: =D15+D16+D17-D18-D19 -> 1109 | E21: =E15+E16+E17-E18-E19 -> 2287 | F21: =F15+F16+F17-F18-F19 -> 2319 | G21: =G15+G16+G17-G18-G19 -> 2471.6743 | H21: =H15+H16+H17-H18-H19 -> 2945.5204 | I21: =I15+I16+I17-I18-I19 -> 3056.2516 | J21: =J15+J16+J17-J18-J19 -> 3711.8061 | K21: =K15+K16+K17-K18-K19 -> 3820.6874
A22: (Increase) / Decrease in NWC [Cash Flow Impact] | G22: =F21-G21 -> -152.6743 | H22: =G21-H21 -> -473.84612 | I22: =H21-I21 -> -110.73119 | J22: =I21-J21 -> -655.55447 | K22: =J21-K21 -> -108.88128

Sheet Capex_Dep
A1: VOLTAS LIMITED - CAPEX & DEPRECIATION SCHEDULE
A2: INR Crore unless stated
C4: HISTORICAL | G4: FORECAST
A5: Particulars | B5: Unit | C5: Mar-23A | D5: Mar-24A | E5: Mar-25A | F5: Mar-26A | G5: Mar-27E | H5: Mar-28E | I5: Mar-29E | J5: Mar-30E | K5: Mar-31E
A6: Total Revenue | C6: =Revenue_Build!C24 -> 9499 | D6: =Revenue_Build!D24 -> 12481 | E6: =Revenue_Build!E24 -> 15413 | F6: =Revenue_Build!F24 -> 14245 | G6: =Revenue_Build!G24 -> 16557.061 | H6: =Revenue_Build!H24 -> 19013.776 | I6: =Revenue_Build!I24 -> 21431.928 | J6: =Revenue_Build!J24 -> 23799.898 | K6: =Revenue_Build!K24 -> 26484.178
A7: GROSS BLOCK ROLL-FORWARD - PPE (Rs Cr)
A8: Opening Gross Block | C8: 488 | D8: =C12 -> 638 | E8: =D12 -> 687 | F8: =E12 -> 1161 | G8: =F12 -> 1338 | H8: =G12 -> 1553.2418 | I8: =H12 -> 1800.4209 | J8: =I12 -> 2143.3317 | K8: =J12 -> 2452.7304
A9: Add: Capex | C9: 159 | D9: 63 | E9: 483 | F9: 183 | G9: =G6*G23 -> 215.24179 | H9: =H6*H23 -> 247.17909 | I9: =I6*I23 -> 342.91084 | J9: =J6*J23 -> 309.39868 | K9: =K6*K23 -> 344.29432
A10: Less: Disposal | C10: 13 | D10: 14 | E10: 11 | F10: 17
A11: Add: Other adjustments / transfers (shown in PDF as a 2nd "Less: Disposal" row - see E-08) | C11: 4 | D11: 1 | E11: 1 | F11: 11
A12: Closing Gross Block | C12: 638 | D12: 687 | E12: 1161 | F12: 1338 | G12: =G8+G9-N(G10)+N(G11) -> 1553.2418 | H12: =H8+H9-N(H10)+N(H11) -> 1800.4209 | I12: =I8+I9-N(I10)+N(I11) -> 2143.3317 | J12: =J8+J9-N(J10)+N(J11) -> 2452.7304 | K12: =K8+K9-N(K10)+N(K11) -> 2797.0247
A13: Check: roll-forward difference (rounding in source data) | C13: =C8+C9-C10+C11-C12 -> 0 | D13: =D8+D9-D10+D11-D12 -> 1 | E13: =E8+E9-E10+E11-E12 -> -1 | F13: =F8+F9-F10+F11-F12 -> 0
A14: DEPRECIATION & ACCUMULATED DEPRECIATION - PPE (Rs Cr)
A15: Opening Accumulated Depreciation | C15: 258 | D15: =C19 -> 277 | E15: =D19 -> 297 | F15: =E19 -> 341 | G15: =F19 -> 403 | H15: =G19 -> 482.78372 | I15: =H19 -> 573.80285 | J15: =I19 -> 680.40884 | K15: =J19 -> 801.0784
A16: Add: Dep exp | C16: 27 | D16: 32 | E16: 52 | F16: 70 | G16: =G33 -> 79.783718 | H16: =H33 -> 91.019131 | I16: =I33 -> 106.60599 | J16: =J33 -> 120.66956 | K16: =K33 -> 136.31931
A17: Less: Disposal | C17: 11 | D17: 13 | E17: 9 | F17: 15
A18: Add: Other adjustments (shown in PDF as a 2nd "Less: Disposal" row) | C18: 4 | D18: 1 | E18: 1 | F18: 7
A19: Closing Accumulated Depreciation | C19: 277 | D19: 297 | E19: 341 | F19: 403 | G19: =G15+G16-N(G17)+N(G18) -> 482.78372 | H19: =H15+H16-N(H17)+N(H18) -> 573.80285 | I19: =I15+I16-N(I17)+N(I18) -> 680.40884 | J19: =J15+J16-N(J17)+N(J18) -> 801.0784 | K19: =K15+K16-N(K17)+N(K18) -> 937.3977
A20: Check: roll-forward difference (rounding in source data) | C20: =C15+C16-C17+C18-C19 -> 1 | D20: =D15+D16-D17+D18-D19 -> 0 | E20: =E15+E16-E17+E18-E19 -> 0 | F20: =F15+F16-F17+F18-F19 -> 0
A21: Closing Net Block (Gross Block - Acc. Depreciation) | C21: =C12-C19 -> 361 | D21: =D12-D19 -> 390 | E21: =E12-E19 -> 820 | F21: =F12-F19 -> 935 | G21: =G12-G19 -> 1070.4581 | H21: =H12-H19 -> 1226.618 | I21: =I12-I19 -> 1462.9229 | J21: =J12-J19 -> 1651.652 | K21: =K12-K19 -> 1859.627
A23: CAPEX % Sales | C23: =C9/C6 -> 0.016738604 | D23: =D9/D6 -> 0.0050476725 | E23: =E9/E6 -> 0.031337183 | F23: =F9/F6 -> 0.012846613 | G23: 0.013 | H23: 0.013 | I23: 0.016 | J23: 0.013 | K23: 0.013
A24: Depreciation % Gross Block | C24: =C16/C12 -> 0.042319749 | D24: =D16/D12 -> 0.04657933 | E24: =E16/E12 -> 0.044788975 | F24: =F16/F12 -> 0.052316891 | G24: =1/G25 -> 0.045454545 | H24: =1/H25 -> 0.045454545 | I24: =1/I25 -> 0.045454545 | J24: =1/J25 -> 0.045454545 | K24: =1/K25 -> 0.045454545
A25: Avg Life (years) | C25: =1/C24 -> 23.62963 | D25: =1/D24 -> 21.46875 | E25: =1/E24 -> 22.326923 | F25: =1/F24 -> 19.114286 | G25: 22 | H25: 22 | I25: 22 | J25: 22 | K25: 22
A26: DEPRECIATION WATERFALL - PPE (depreciation on each year's capex over average life)
A27: Depreciation on existing block (held at FY26 level) | G27: =$F$16 -> 70 | H27: =$F$16 -> 70 | I27: =$F$16 -> 70 | J27: =$F$16 -> 70 | K27: =$F$16 -> 70
A28: Year 1 capex (Mar-27E) | G28: =$G$9/G$25 -> 9.7837176 | H28: =$G$9/H$25 -> 9.7837176 | I28: =$G$9/I$25 -> 9.7837176 | J28: =$G$9/J$25 -> 9.7837176 | K28: =$G$9/K$25 -> 9.7837176
A29: Year 2 capex (Mar-28E) | H29: =$H$9/H$25 -> 11.235413 | I29: =$H$9/I$25 -> 11.235413 | J29: =$H$9/J$25 -> 11.235413 | K29: =$H$9/K$25 -> 11.235413
A30: Year 3 capex (Mar-29E) | I30: =$I$9/I$25 -> 15.586856 | J30: =$I$9/J$25 -> 15.586856 | K30: =$I$9/K$25 -> 15.586856
A31: Year 4 capex (Mar-30E) | J31: =$J$9/J$25 -> 14.063576 | K31: =$J$9/K$25 -> 14.063576
A32: Year 5 capex (Mar-31E) | K32: =$K$9/K$25 -> 15.649742
A33: Total Depreciation - PPE | G33: =SUM(G27:G32) -> 79.783718 | H33: =SUM(H27:H32) -> 91.019131 | I33: =SUM(I27:I32) -> 106.60599 | J33: =SUM(J27:J32) -> 120.66956 | K33: =SUM(K27:K32) -> 136.31931
A34: GROSS RIGHT OF USE ASSETS (Rs Cr)
A35: Opening Gross Block | C35: 36 | D35: =C38 -> 60 | E35: =D38 -> 71 | F35: =E38 -> 60 | G35: =F38 -> 66 | H35: =G38 -> 75.934236 | I35: =H38 -> 87.342502 | J35: =I38 -> 100.20166 | K35: =J38 -> 114.4816
A36: Add: Additions | C36: 23 | D36: 11 | E36: 5 | F36: 9 | G36: =G6*G45 -> 9.9342364 | H36: =H6*H45 -> 11.408266 | I36: =I6*I45 -> 12.859157 | J36: =J6*J45 -> 14.279939 | K36: =K6*K45 -> 15.890507
A37: Less: Disposal | C37: 0 | D37: 0 | E37: 16 | F37: 3
A38: Closing Gross Block | C38: 60 | D38: 71 | E38: 60 | F38: 66 | G38: =G35+G36-N(G37) -> 75.934236 | H38: =H35+H36-N(H37) -> 87.342502 | I38: =I35+I36-N(I37) -> 100.20166 | J38: =J35+J36-N(J37) -> 114.4816 | K38: =K35+K36-N(K37) -> 130.3721
A39: DEPRECIATION & ACCUMULATED DEPRECIATION - ROU (Rs Cr)
A40: Opening Accumulated Depreciation | C40: 16 | D40: =C43 -> 24 | E40: =D43 -> 36 | F40: =E43 -> 26 | G40: =F43 -> 35 | H40: =G43 -> 48.019177 | I40: =H43 -> 62.668105 | J40: =I43 -> 79.154057 | K40: =J43 -> 97.679999
A41: Add: Dep exp | C41: 8 | D41: 12 | E41: 7 | F41: 11 | G41: =G55 -> 13.019177 | H41: =H55 -> 14.648929 | I41: =I55 -> 16.485951 | J41: =J55 -> 18.525943 | K41: =K55 -> 20.796015
A42: Less: Disposal | C42: 0 | D42: 0 | E42: 16 | F42: 3
A43: Closing Accumulated Depreciation | C43: 24 | D43: 36 | E43: 26 | F43: 35 | G43: =G40+G41-N(G42) -> 48.019177 | H43: =H40+H41-N(H42) -> 62.668105 | I43: =I40+I41-N(I42) -> 79.154057 | J43: =J40+J41-N(J42) -> 97.679999 | K43: =K40+K41-N(K42) -> 118.47601
A44: Closing Net Block - ROU (forecast rolled from Balance Sheet ROU) | C44: =C38-C43 -> 36 | D44: =D38-D43 -> 35 | E44: =E38-E43 -> 34 | F44: =F38-F43 -> 31 | G44: =Hist_BS!F28+G36-G41 -> 28.91506 | H44: =G44+H36-H41 -> 25.674396 | I44: =H44+I36-I41 -> 22.047602 | J44: =I44+J36-J41 -> 17.801598 | K44: =J44+K36-K41 -> 12.89609
A45: ROU additions % Sales | C45: =C36/C6 -> 0.0024213075 | D45: =D36/D6 -> 0.00088133964 | E45: =E36/E6 -> 0.00032440148 | F45: =F36/F6 -> 0.00063180063 | G45: 0.0006 | H45: 0.0006 | I45: 0.0006 | J45: 0.0006 | K45: 0.0006
A46: Depreciation % Gross Block | C46: =C41/C38 -> 0.13333333 | D46: =D41/D38 -> 0.16901408 | E46: =E41/E38 -> 0.11666667 | F46: =F41/F38 -> 0.16666667 | G46: =1/G47 -> 0.14285714 | H46: =1/H47 -> 0.14285714 | I46: =1/I47 -> 0.14285714 | J46: =1/J47 -> 0.14285714 | K46: =1/K47 -> 0.14285714
A47: Avg Life (years) | C47: =1/C46 -> 7.5 | D47: =1/D46 -> 5.9166667 | E47: =1/E46 -> 8.5714286 | F47: =1/F46 -> 6 | G47: 7 | H47: 7 | I47: 7 | J47: 7 | K47: 7
A48: DEPRECIATION WATERFALL - ROU
A49: Depreciation on existing ROU (calibrated input; FY26 shown as 11) | G49: 11.6 | H49: 11.6 | I49: 11.6 | J49: 11.6 | K49: 11.6
A50: Year 1 additions (Mar-27E) | G50: =$G$36/G$47 -> 1.4191766 | H50: =$G$36/H$47 -> 1.4191766 | I50: =$G$36/I$47 -> 1.4191766 | J50: =$G$36/J$47 -> 1.4191766 | K50: =$G$36/K$47 -> 1.4191766
A51: Year 2 additions (Mar-28E) | H51: =$H$36/H$47 -> 1.6297522 | I51: =$H$36/I$47 -> 1.6297522 | J51: =$H$36/J$47 -> 1.6297522 | K51: =$H$36/K$47 -> 1.6297522
A52: Year 3 additions (Mar-29E) | I52: =$I$36/I$47 -> 1.8370224 | J52: =$I$36/J$47 -> 1.8370224 | K52: =$I$36/K$47 -> 1.8370224
A53: Year 4 additions (Mar-30E) | J53: =$J$36/J$47 -> 2.0399913 | K53: =$J$36/K$47 -> 2.0399913
A54: Year 5 additions (Mar-31E) | K54: =$K$36/K$47 -> 2.2700724
A55: Total Depreciation - ROU | G55: =SUM(G49:G54) -> 13.019177 | H55: =SUM(H49:H54) -> 14.648929 | I55: =SUM(I49:I54) -> 16.485951 | J55: =SUM(J49:J54) -> 18.525943 | K55: =SUM(K49:K54) -> 20.796015
A56: TOTALS TO INCOME STATEMENT / CASH FLOW
A57: Total D&A (PPE + ROU; FY23-26 incl. intangibles per Hist_IS) | C57: =Hist_IS!C24 -> 40 | D57: =Hist_IS!D24 -> 48 | E57: =Hist_IS!E24 -> 62 | F57: =Hist_IS!F24 -> 84 | G57: =G16+G41 -> 92.802894 | H57: =H16+H41 -> 105.66806 | I57: =I16+I41 -> 123.09194 | J57: =J16+J41 -> 139.19551 | K57: =K16+K41 -> 157.11532
A58: Total Capex incl. ROU additions | G58: =G9+G36 -> 225.17602 | H58: =H9+H36 -> 258.58735 | I58: =I9+I36 -> 355.77 | J58: =J9+J36 -> 323.67862 | K58: =K9+K36 -> 360.18482

Sheet Debt_Schedule
A1: VOLTAS LIMITED - DEBT SCHEDULE
A2: INR Crore unless stated
C4: HISTORICAL | G4: FORECAST
A5: Particulars | B5: Unit | C5: Mar-23A | D5: Mar-24A | E5: Mar-25A | F5: Mar-26A | G5: Mar-27E | H5: Mar-28E | I5: Mar-29E | J5: Mar-30E | K5: Mar-31E
A6: LONG TERM BORROWINGS
A7: Long Term Debt - Opening Balance | G7: =F10 -> 376 | H7: =G10 -> 319.6 | I7: =H10 -> 271.66 | J7: =I10 -> 230.911 | K7: =J10 -> 196.27435
A8: Long Term Debt - New Borrowings / Additions | G8: 0 | H8: 0 | I8: 0 | J8: 0 | K8: 0
A9: Long Term Debt - Repayments (% of opening balance) | G9: =G7*Assumptions!G34 -> 56.4 | H9: =H7*Assumptions!H34 -> 47.94 | I9: =I7*Assumptions!I34 -> 40.749 | J9: =J7*Assumptions!J34 -> 34.63665 | K9: =K7*Assumptions!K34 -> 29.441153
A10: Long Term Debt - Closing Balance | C10: =Hist_BS!C12 -> 21 | D10: =Hist_BS!D12 -> 228 | E10: =Hist_BS!E12 -> 383 | F10: =Hist_BS!F12 -> 376 | G10: =G7+G8-G9 -> 319.6 | H10: =H7+H8-H9 -> 271.66 | I10: =I7+I8-I9 -> 230.911 | J10: =J7+J8-J9 -> 196.27435 | K10: =K7+K8-K9 -> 166.8332
A12: SHORT TERM BORROWINGS
A13: Short Term Borrowings - Opening | G13: =F15 -> 591 | H13: =G15 -> 647.50037 | I13: =H15 -> 737.69784 | J13: =I15 -> 817.06288 | K13: =J15 -> 922.80194
A14: Net increase / (decrease) (published label: "Short Term Borrowings % (Receivables + Inventories)" - see E-09) | G14: =G15-G13 -> 56.500371 | H14: =H15-H13 -> 90.197465 | I14: =I15-I13 -> 79.365047 | J14: =J15-J13 -> 105.73905 | K14: =K15-K13 -> 81.007042
A15: Short Term Borrowings - Closing Balance (= % x (Receivables + Inventories)) | C15: =Hist_BS!C18 -> 595 | D15: =Hist_BS!D18 -> 485 | E15: =Hist_BS!E18 -> 481 | F15: =Hist_BS!F18 -> 591 | G15: =Assumptions!G35*(WC_Schedule!G15+WC_Schedule!G16) -> 647.50037 | H15: =Assumptions!H35*(WC_Schedule!H15+WC_Schedule!H16) -> 737.69784 | I15: =Assumptions!I35*(WC_Schedule!I15+WC_Schedule!I16) -> 817.06288 | J15: =Assumptions!J35*(WC_Schedule!J15+WC_Schedule!J16) -> 922.80194 | K15: =Assumptions!K35*(WC_Schedule!K15+WC_Schedule!K16) -> 1003.809
A17: LEASE LIABILITIES
A18: Lease Liabilities (Non-Current, labelled "Total" in PDF) - Opening | G18: =F21 -> 15 | H18: =G21 -> 15 | I18: =H21 -> 15 | J18: =I21 -> 15 | K18: =J21 -> 15
A19: New Borrowings / Additions | G19: 0 | H19: 0 | I19: 0 | J19: 0 | K19: 0
A20: Repayments | G20: 0 | H20: 0 | I20: 0 | J20: 0 | K20: 0
A21: Lease Liabilities (Non-Current) - Closing Balance | C21: =Hist_BS!C13 -> 25 | D21: =Hist_BS!D13 -> 21 | E21: =Hist_BS!E13 -> 18 | F21: =Hist_BS!F13 -> 15 | G21: =G18+G19-G20 -> 15 | H21: =H18+H19-H20 -> 15 | I21: =I18+I19-I20 -> 15 | J21: =J18+J19-J20 -> 15 | K21: =K18+K19-K20 -> 15
A23: TOTAL DEBT (Closing Balance) - as published (excl. current lease liabilities) | C23: =C10+C15+C21 -> 641 | D23: =D10+D15+D21 -> 734 | E23: =E10+E15+E21 -> 882 | F23: =F10+F15+F21 -> 982 | G23: =G10+G15+G21 -> 982.10037 | H23: =H10+H15+H21 -> 1024.3578 | I23: =I10+I15+I21 -> 1062.9739 | J23: =J10+J15+J21 -> 1134.0763 | K23: =K10+K15+K21 -> 1185.6422
A24: Memo: Lease liabilities (Current) - omitted from published total debt | C24: =Hist_BS!C19 -> 9 | D24: =Hist_BS!D19 -> 9 | E24: =Hist_BS!E19 -> 11 | F24: =Hist_BS!F19 -> 11 | G24: =F24 -> 11 | H24: =G24 -> 11 | I24: =H24 -> 11 | J24: =I24 -> 11 | K24: =J24 -> 11
A25: Total debt incl. current lease liabilities | C25: =C23+C24 -> 650 | D25: =D23+D24 -> 743 | E25: =E23+E24 -> 893 | F25: =F23+F24 -> 993 | G25: =G23+G24 -> 993.10037 | H25: =H23+H24 -> 1035.3578 | I25: =I23+I24 -> 1073.9739 | J25: =J23+J24 -> 1145.0763 | K25: =K23+K24 -> 1196.6422
A26: Borrowings only (LT + ST) - used in Ratios EV / Net debt | C26: =C10+C15 -> 616 | D26: =D10+D15 -> 713 | E26: =E10+E15 -> 864 | F26: =F10+F15 -> 967 | G26: =G10+G15 -> 967.10037 | H26: =H10+H15 -> 1009.3578 | I26: =I10+I15 -> 1047.9739 | J26: =J10+J15 -> 1119.0763 | K26: =K10+K15 -> 1170.6422

Sheet Equity_Schedule
A1: VOLTAS LIMITED - EQUITY, SHARE CAPITAL & DIVIDEND SCHEDULE
A2: INR Crore unless stated
C4: HISTORICAL | G4: FORECAST
A5: Particulars | B5: Unit | C5: Mar-23A | D5: Mar-24A | E5: Mar-25A | F5: Mar-26A | G5: Mar-27E | H5: Mar-28E | I5: Mar-29E | J5: Mar-30E | K5: Mar-31E
A6: Share Capital | C6: =Hist_BS!C7 -> 33 | D6: =Hist_BS!D7 -> 33 | E6: =Hist_BS!E7 -> 33 | F6: =Hist_BS!F7 -> 33 | G6: =F6 -> 33 | H6: =G6 -> 33 | I6: =H6 -> 33 | J6: =I6 -> 33 | K6: =J6 -> 33
A7: Non-Controlling Interest (held flat) | C7: =Hist_BS!C9 -> 42 | D7: =Hist_BS!D9 -> 34 | E7: =Hist_BS!E9 -> 27 | F7: =Hist_BS!F9 -> 23 | G7: =F7 -> 23 | H7: =G7 -> 23 | I7: =H7 -> 23 | J7: =I7 -> 23 | K7: =J7 -> 23
A8: OTHER EQUITY ROLL-FORWARD
A9: Opening Other Equity | G9: =F13 -> 6343 | H9: =G13 -> 6945.2845 | I9: =H13 -> 7732.0328 | J9: =I13 -> 8727.0529 | K9: =J13 -> 9833.3519
A10: Add: Net profit attributable to owners | G10: =Income_Statement!G27 -> 734.60455 | H10: =Income_Statement!H27 -> 919.06828 | I10: =Income_Statement!I27 -> 1127.34 | J10: =Income_Statement!J27 -> 1238.619 | K10: =Income_Statement!K27 -> 1429.7446
A11: Dividend per share (Rs) | G11: =Assumptions!G41 -> 4 | H11: =Assumptions!H41 -> 4 | I11: =Assumptions!I41 -> 4 | J11: =Assumptions!J41 -> 4 | K11: =Assumptions!K41 -> 4
A12: Less: Dividend paid (DPS x shares) | G12: =G11*Assumptions!$C$9 -> 132.32 | H12: =H11*Assumptions!$C$9 -> 132.32 | I12: =I11*Assumptions!$C$9 -> 132.32 | J12: =J11*Assumptions!$C$9 -> 132.32 | K12: =K11*Assumptions!$C$9 -> 132.32
A13: Closing Other Equity | C13: =Hist_BS!C8 -> 5419 | D13: =Hist_BS!D8 -> 5787 | E13: =Hist_BS!E8 -> 6480 | F13: =Hist_BS!F8 -> 6343 | G13: =G9+G10-G12 -> 6945.2845 | H13: =H9+H10-H12 -> 7732.0328 | I13: =I9+I10-I12 -> 8727.0529 | J13: =J9+J10-J12 -> 9833.3519 | K13: =K9+K10-K12 -> 11130.777
A14: Total Equity | C14: =C6+C13+C7 -> 5494 | D14: =D6+D13+D7 -> 5854 | E14: =E6+E13+E7 -> 6540 | F14: =F6+F13+F7 -> 6399 | G14: =G6+G13+G7 -> 7001.2845 | H14: =H6+H13+H7 -> 7788.0328 | I14: =I6+I13+I7 -> 8783.0529 | J14: =J6+J13+J7 -> 9889.3519 | K14: =K6+K13+K7 -> 11186.777

Sheet Income_Statement
A1: VOLTAS LIMITED - INTEGRATED INCOME STATEMENT
A2: INR Crore unless stated
C4: HISTORICAL | G4: FORECAST
A5: Particulars | B5: Unit | C5: Mar-23A | D5: Mar-24A | E5: Mar-25A | F5: Mar-26A | G5: Mar-27E | H5: Mar-28E | I5: Mar-29E | J5: Mar-30E | K5: Mar-31E
A6: Total Revenue from Operations | C6: =Revenue_Build!C24 -> 9499 | D6: =Revenue_Build!D24 -> 12481 | E6: =Revenue_Build!E24 -> 15413 | F6: =Revenue_Build!F24 -> 14245 | G6: =Revenue_Build!G24 -> 16557.061 | H6: =Revenue_Build!H24 -> 19013.776 | I6: =Revenue_Build!I24 -> 21431.928 | J6: =Revenue_Build!J24 -> 23799.898 | K6: =Revenue_Build!K24 -> 26484.178
A7: Revenue Growth % YoY | D7: =D6/C6-1 -> 0.31392778 | E7: =E6/D6-1 -> 0.23491707 | F7: =F6/E6-1 -> -0.075780186 | G7: =G6/F6-1 -> 0.16230682 | H7: =H6/G6-1 -> 0.14837872 | I7: =I6/H6-1 -> 0.12717893 | J7: =J6/I6-1 -> 0.110488 | K7: =K6/J6-1 -> 0.11278534
A9: Cost of Goods Sold | C9: =Cost_Schedule!C9 -> 7378 | D9: =Cost_Schedule!D9 -> 9814 | E9: =Cost_Schedule!E9 -> 11960 | F9: =Cost_Schedule!F9 -> 11069 | G9: =Cost_Schedule!G9 -> 12864.836 | H9: =Cost_Schedule!H9 -> 14754.69 | I9: =Cost_Schedule!I9 -> 16609.744 | J9: =Cost_Schedule!J9 -> 18444.921 | K9: =Cost_Schedule!K9 -> 20498.754
A10: Employee Benefit Expense | C10: =Cost_Schedule!C12 -> 667 | D10: =Cost_Schedule!D12 -> 779 | E10: =Cost_Schedule!E12 -> 890 | F10: =Cost_Schedule!F12 -> 939 | G10: =Cost_Schedule!G12 -> 993.42364 | H10: =Cost_Schedule!H12 -> 1140.8266 | I10: =Cost_Schedule!I12 -> 1285.9157 | J10: =Cost_Schedule!J12 -> 1427.9939 | K10: =Cost_Schedule!K12 -> 1589.0507
A11: Other Expenses (Selling+Mktg+Admin+Warranty+Other) | C11: =Cost_Schedule!C15 -> 881 | D11: =Cost_Schedule!D15 -> 1414 | E11: =Cost_Schedule!E15 -> 1446 | F11: =Cost_Schedule!F15 -> 1589 | G11: =Cost_Schedule!G15 -> 1655.7061 | H11: =Cost_Schedule!H15 -> 1806.3087 | I11: =Cost_Schedule!I15 -> 1993.1693 | J11: =Cost_Schedule!J15 -> 2213.3905 | K11: =Cost_Schedule!K15 -> 2463.0286
A12: Total Operating Expenses | C12: =SUM(C9:C11) -> 8926 | D12: =SUM(D9:D11) -> 12007 | E12: =SUM(E9:E11) -> 14296 | F12: =SUM(F9:F11) -> 13597 | G12: =SUM(G9:G11) -> 15513.966 | H12: =SUM(H9:H11) -> 17701.825 | I12: =SUM(I9:I11) -> 19888.829 | J12: =SUM(J9:J11) -> 22086.306 | K12: =SUM(K9:K11) -> 24550.833
A14: EBITDA | C14: =C6-C12 -> 573 | D14: =D6-D12 -> 474 | E14: =E6-E12 -> 1117 | F14: =F6-F12 -> 648 | G14: =G6-G12 -> 1043.0948 | H14: =H6-H12 -> 1311.9505 | I14: =I6-I12 -> 1543.0988 | J14: =J6-J12 -> 1713.5927 | K14: =K6-K12 -> 1933.345
A15: EBITDA Margin % | C15: =C14/C6 -> 0.060322139 | D15: =D14/D6 -> 0.037977726 | E15: =E14/E6 -> 0.07247129 | F15: =F14/F6 -> 0.045489645 | G15: =G14/G6 -> 0.063 | H15: =H14/H6 -> 0.069 | I15: =I14/I6 -> 0.072 | J15: =J14/J6 -> 0.072 | K15: =K14/K6 -> 0.073
A16: Depreciation & Amortization | C16: =Hist_IS!C24 -> 40 | D16: =Hist_IS!D24 -> 48 | E16: =Hist_IS!E24 -> 62 | F16: =Hist_IS!F24 -> 84 | G16: =Capex_Dep!G57 -> 92.802894 | H16: =Capex_Dep!H57 -> 105.66806 | I16: =Capex_Dep!I57 -> 123.09194 | J16: =Capex_Dep!J57 -> 139.19551 | K16: =Capex_Dep!K57 -> 157.11532
A17: EBIT | C17: =C14-C16 -> 533 | D17: =D14-D16 -> 426 | E17: =E14-E16 -> 1055 | F17: =F14-F16 -> 564 | G17: =G14-G16 -> 950.29192 | H17: =H14-H16 -> 1206.2825 | I17: =I14-I16 -> 1420.0069 | J17: =J14-J16 -> 1574.3972 | K17: =K14-K16 -> 1776.2297
A18: EBIT Margin % | C18: =C17/C6 -> 0.05611117 | D18: =D17/D6 -> 0.03413188 | E18: =E17/E6 -> 0.068448712 | F18: =F17/F6 -> 0.03959284 | G18: =G17/G6 -> 0.057394966 | H18: =H17/H6 -> 0.063442553 | I18: =I17/I6 -> 0.066256609 | J18: =J17/J6 -> 0.066151424 | K18: =K17/K6 -> 0.067067578
A19: Finance Costs | C19: =Hist_IS!C26 -> 30 | D19: =Hist_IS!D26 -> 56 | E19: =Hist_IS!E26 -> 62 | F19: =Hist_IS!F26 -> 87 | G19: =G6*Assumptions!G38 -> 100.99807 | H19: =H6*Assumptions!H38 -> 104.57577 | I19: =I6*Assumptions!I38 -> 107.15964 | J19: =J6*Assumptions!J38 -> 118.99949 | K19: =K6*Assumptions!K38 -> 132.42089
A20: Other Income | C20: =Hist_IS!C27 -> 168 | D20: =Hist_IS!D27 -> 253 | E20: =Hist_IS!E27 -> 324 | F20: =Hist_IS!F27 -> 238 | G20: =G6*Assumptions!G39 -> 331.14121 | H20: =H6*Assumptions!H39 -> 342.24797 | I20: =I6*Assumptions!I39 -> 428.63855 | J20: =J6*Assumptions!J39 -> 445.0581 | K20: =K6*Assumptions!K39 -> 529.68356
A21: Share of Profit from Associates / JV (held at FY26 level) | C21: =Hist_IS!C28 -> -121 | D21: =Hist_IS!D28 -> -139 | E21: =Hist_IS!E28 -> -126 | F21: =Hist_IS!F28 -> -131 | G21: =F21 -> -131 | H21: =G21 -> -131 | I21: =H21 -> -131 | J21: =I21 -> -131 | K21: =J21 -> -131
A22: Exceptional Items | C22: =Hist_IS!C29 -> -244 | D22: =Hist_IS!D29 -> 0 | E22: =Hist_IS!E29 -> 0 | F22: =Hist_IS!F29 -> -26 | G22: 0 | H22: 0 | I22: 0 | J22: 0 | K22: 0
A23: Profit Before Tax (PBT) | C23: =C17-C19+C20+C21+C22 -> 306 | D23: =D17-D19+D20+D21+D22 -> 484 | E23: =E17-E19+E20+E21+E22 -> 1191 | F23: =F17-F19+F20+F21+F22 -> 558 | G23: =G17-G19+G20+G21+G22 -> 1049.4351 | H23: =H17-H19+H20+H21+H22 -> 1312.9547 | I23: =I17-I19+I20+I21+I22 -> 1610.4858 | J23: =J17-J19+J20+J21+J22 -> 1769.4558 | K23: =K17-K19+K20+K21+K22 -> 2042.4924
A24: Tax Expense | C24: =Hist_IS!C31 -> 171 | D24: =Hist_IS!D31 -> 238 | E24: =Hist_IS!E31 -> 356 | F24: =Hist_IS!F31 -> 187 | G24: =MAX(0,G23)*Assumptions!G25 -> 314.83052 | H24: =MAX(0,H23)*Assumptions!H25 -> 393.88641 | I24: =MAX(0,I23)*Assumptions!I25 -> 483.14573 | J24: =MAX(0,J23)*Assumptions!J25 -> 530.83674 | K24: =MAX(0,K23)*Assumptions!K25 -> 612.74771
A25: Profit After Tax (PAT) | C25: =C23-C24 -> 135 | D25: =D23-D24 -> 246 | E25: =E23-E24 -> 835 | F25: =F23-F24 -> 371 | G25: =G23-G24 -> 734.60455 | H25: =H23-H24 -> 919.06828 | I25: =I23-I24 -> 1127.34 | J25: =J23-J24 -> 1238.619 | K25: =K23-K24 -> 1429.7446
A26: Non-Controlling / Minority Interest | C26: 0 | D26: 0 | E26: 0 | F26: 0 | G26: 0 | H26: 0 | I26: 0 | J26: 0 | K26: 0
A27: Net Profit Attributable to Owners | C27: =C25-C26 -> 135 | D27: =D25-D26 -> 246 | E27: =E25-E26 -> 835 | F27: =F25-F26 -> 371 | G27: =G25-G26 -> 734.60455 | H27: =H25-H26 -> 919.06828 | I27: =I25-I26 -> 1127.34 | J27: =J25-J26 -> 1238.619 | K27: =K25-K26 -> 1429.7446
A29: Diluted Weighted Avg. Shares Outstanding (Cr) | C29: =Assumptions!$C$9 -> 33.08 | D29: =Assumptions!$C$9 -> 33.08 | E29: =Assumptions!$C$9 -> 33.08 | F29: =Assumptions!$C$9 -> 33.08 | G29: =Assumptions!$C$9 -> 33.08 | H29: =Assumptions!$C$9 -> 33.08 | I29: =Assumptions!$C$9 -> 33.08 | J29: =Assumptions!$C$9 -> 33.08 | K29: =Assumptions!$C$9 -> 33.08
A30: Diluted EPS (Rs) | C30: =C27/C29 -> 4.0810157 | D30: =D27/D29 -> 7.4365175 | E30: =E27/E29 -> 25.241838 | F30: =F27/F29 -> 11.215236 | G30: =G27/G29 -> 22.206909 | H30: =H27/H29 -> 27.783201 | I30: =I27/I29 -> 34.079203 | J30: =J27/J29 -> 37.443139 | K30: =K27/K29 -> 43.220818
A31: PAT Margin % | C31: =C25/C6 -> 0.014212022 | D31: =D25/D6 -> 0.019709959 | E31: =E25/E6 -> 0.054175047 | F31: =F25/F6 -> 0.026044226 | G31: =G25/G6 -> 0.044368053 | H31: =H25/H6 -> 0.048336968 | I31: =I25/I6 -> 0.052600963 | J31: =J25/J6 -> 0.052043039 | K31: =K25/K6 -> 0.05398486
A32: Effective Tax Rate % | C32: =C24/C23 -> 0.55882353 | D32: =D24/D23 -> 0.49173554 | E32: =E24/E23 -> 0.29890848 | F32: =F24/F23 -> 0.33512545 | G32: =G24/G23 -> 0.3 | H32: =H24/H23 -> 0.3 | I32: =I24/I23 -> 0.3 | J32: =J24/J23 -> 0.3 | K32: =K24/K23 -> 0.3

Sheet Balance_Sheet
A1: VOLTAS LIMITED - INTEGRATED BALANCE SHEET
A2: INR Crore unless stated
C4: HISTORICAL | G4: FORECAST
A5: Particulars | B5: Unit | C5: Mar-23A | D5: Mar-24A | E5: Mar-25A | F5: Mar-26A | G5: Mar-27E | H5: Mar-28E | I5: Mar-29E | J5: Mar-30E | K5: Mar-31E
A6: EQUITY & LIABILITIES
A7: Share Capital | B7: Rs Cr | C7: =Hist_BS!C7 -> 33 | D7: =Hist_BS!D7 -> 33 | E7: =Hist_BS!E7 -> 33 | F7: =Hist_BS!F7 -> 33 | G7: =Equity_Schedule!G6 -> 33 | H7: =Equity_Schedule!H6 -> 33 | I7: =Equity_Schedule!I6 -> 33 | J7: =Equity_Schedule!J6 -> 33 | K7: =Equity_Schedule!K6 -> 33
A8: Other Equity (Reserves & Surplus) | B8: Rs Cr | C8: =Hist_BS!C8 -> 5419 | D8: =Hist_BS!D8 -> 5787 | E8: =Hist_BS!E8 -> 6480 | F8: =Hist_BS!F8 -> 6343 | G8: =Equity_Schedule!G13 -> 6945.2845 | H8: =Equity_Schedule!H13 -> 7732.0328 | I8: =Equity_Schedule!I13 -> 8727.0529 | J8: =Equity_Schedule!J13 -> 9833.3519 | K8: =Equity_Schedule!K13 -> 11130.777
A9: Non-Controlling Interest | B9: Rs Cr | C9: =Hist_BS!C9 -> 42 | D9: =Hist_BS!D9 -> 34 | E9: =Hist_BS!E9 -> 27 | F9: =Hist_BS!F9 -> 23 | G9: =Equity_Schedule!G7 -> 23 | H9: =Equity_Schedule!H7 -> 23 | I9: =Equity_Schedule!I7 -> 23 | J9: =Equity_Schedule!J7 -> 23 | K9: =Equity_Schedule!K7 -> 23
A10: Total Equity | C10: =SUM(C7:C9) -> 5494 | D10: =SUM(D7:D9) -> 5854 | E10: =SUM(E7:E9) -> 6540 | F10: =SUM(F7:F9) -> 6399 | G10: =SUM(G7:G9) -> 7001.2845 | H10: =SUM(H7:H9) -> 7788.0328 | I10: =SUM(I7:I9) -> 8783.0529 | J10: =SUM(J7:J9) -> 9889.3519 | K10: =SUM(K7:K9) -> 11186.777
A12: Long Term Borrowings | B12: Rs Cr | C12: =Hist_BS!C12 -> 21 | D12: =Hist_BS!D12 -> 228 | E12: =Hist_BS!E12 -> 383 | F12: =Hist_BS!F12 -> 376 | G12: =Debt_Schedule!G10 -> 319.6 | H12: =Debt_Schedule!H10 -> 271.66 | I12: =Debt_Schedule!I10 -> 230.911 | J12: =Debt_Schedule!J10 -> 196.27435 | K12: =Debt_Schedule!K10 -> 166.8332
A13: Lease Liabilities (Non-Current) | B13: Rs Cr | C13: =Hist_BS!C13 -> 25 | D13: =Hist_BS!D13 -> 21 | E13: =Hist_BS!E13 -> 18 | F13: =Hist_BS!F13 -> 15 | G13: =Debt_Schedule!G21 -> 15 | H13: =Debt_Schedule!H21 -> 15 | I13: =Debt_Schedule!I21 -> 15 | J13: =Debt_Schedule!J21 -> 15 | K13: =Debt_Schedule!K21 -> 15
A14: Deferred Tax Liabilities (Net) | B14: Rs Cr | C14: =Hist_BS!C14 -> 5 | D14: =Hist_BS!D14 -> 59 | E14: =Hist_BS!E14 -> 58 | F14: =Hist_BS!F14 -> 14 | G14: =F14 -> 14 | H14: =G14 -> 14 | I14: =H14 -> 14 | J14: =I14 -> 14 | K14: =J14 -> 14
A15: Other Non-Current Liabilities & Provisions | B15: Rs Cr | C15: =Hist_BS!C15 -> 114 | D15: =Hist_BS!D15 -> 117 | E15: =Hist_BS!E15 -> 147 | F15: =Hist_BS!F15 -> 152 | G15: =F15 -> 152 | H15: =G15 -> 152 | I15: =H15 -> 152 | J15: =I15 -> 152 | K15: =J15 -> 152
A16: Total Non-Current Liabilities | C16: =SUM(C12:C15) -> 165 | D16: =SUM(D12:D15) -> 425 | E16: =SUM(E12:E15) -> 606 | F16: =SUM(F12:F15) -> 557 | G16: =SUM(G12:G15) -> 500.6 | H16: =SUM(H12:H15) -> 452.66 | I16: =SUM(I12:I15) -> 411.911 | J16: =SUM(J12:J15) -> 377.27435 | K16: =SUM(K12:K15) -> 347.8332
A18: Short Term Borrowings | B18: Rs Cr | C18: =Hist_BS!C18 -> 595 | D18: =Hist_BS!D18 -> 485 | E18: =Hist_BS!E18 -> 481 | F18: =Hist_BS!F18 -> 591 | G18: =Debt_Schedule!G15 -> 647.50037 | H18: =Debt_Schedule!H15 -> 737.69784 | I18: =Debt_Schedule!I15 -> 817.06288 | J18: =Debt_Schedule!J15 -> 922.80194 | K18: =Debt_Schedule!K15 -> 1003.809
A19: Lease Liabilities (Current) | B19: Rs Cr | C19: =Hist_BS!C19 -> 9 | D19: =Hist_BS!D19 -> 9 | E19: =Hist_BS!E19 -> 11 | F19: =Hist_BS!F19 -> 11 | G19: =F19 -> 11 | H19: =G19 -> 11 | I19: =H19 -> 11 | J19: =I19 -> 11 | K19: =J19 -> 11
A20: Trade Payables | B20: Rs Cr | C20: =Hist_BS!C20 -> 3013 | D20: =Hist_BS!D20 -> 3856 | E20: =Hist_BS!E20 -> 3893 | F20: =Hist_BS!F20 -> 5228 | G20: =WC_Schedule!G18 -> 5568.8879 | H20: =WC_Schedule!H18 -> 6184.8427 | I20: =WC_Schedule!I18 -> 6962.4406 | J20: =WC_Schedule!J18 -> 7580.1046 | K20: =WC_Schedule!K18 -> 8424.1454
A21: Other Current Liabilities & Provisions | B21: Rs Cr | C21: =Hist_BS!C21 -> 1003 | D21: =Hist_BS!D21 -> 1406 | E21: =Hist_BS!E21 -> 1621 | F21: =Hist_BS!F21 -> 1724 | G21: =WC_Schedule!G19 -> 1814.4724 | H21: =WC_Schedule!H19 -> 2083.7015 | I21: =WC_Schedule!I19 -> 2348.7044 | J21: =WC_Schedule!J19 -> 2608.208 | K21: =WC_Schedule!K19 -> 2902.3757
A22: Total Current Liabilities | C22: =SUM(C18:C21) -> 4620 | D22: =SUM(D18:D21) -> 5756 | E22: =SUM(E18:E21) -> 6006 | F22: =SUM(F18:F21) -> 7554 | G22: =SUM(G18:G21) -> 8041.8607 | H22: =SUM(H18:H21) -> 9017.2421 | I22: =SUM(I18:I21) -> 10139.208 | J22: =SUM(J18:J21) -> 11122.115 | K22: =SUM(K18:K21) -> 12341.33
A23: TOTAL EQUITY & LIABILITIES | C23: =C10+C16+C22 -> 10279 | D23: =D10+D16+D22 -> 12035 | E23: =E10+E16+E22 -> 13152 | F23: =F10+F16+F22 -> 14510 | G23: =G10+G16+G22 -> 15543.745 | H23: =H10+H16+H22 -> 17257.935 | I23: =I10+I16+I22 -> 19334.172 | J23: =J10+J16+J22 -> 21388.741 | K23: =K10+K16+K22 -> 23875.94
A25: ASSETS
A26: Net Block - Property, Plant & Equipment | B26: Rs Cr | C26: =Hist_BS!C26 -> 361 | D26: =Hist_BS!D26 -> 390 | E26: =Hist_BS!E26 -> 820 | F26: =Hist_BS!F26 -> 935 | G26: =Capex_Dep!G21 -> 1070.4581 | H26: =Capex_Dep!H21 -> 1226.618 | I26: =Capex_Dep!I21 -> 1462.9229 | J26: =Capex_Dep!J21 -> 1651.652 | K26: =Capex_Dep!K21 -> 1859.627
A27: Capital Work in Progress | B27: Rs Cr | C27: =Hist_BS!C27 -> 98 | D27: =Hist_BS!D27 -> 368 | E27: =Hist_BS!E27 -> 82 | F27: =Hist_BS!F27 -> 22 | G27: =F27 -> 22 | H27: =G27 -> 22 | I27: =H27 -> 22 | J27: =I27 -> 22 | K27: =J27 -> 22
A28: Right-of-Use Assets | B28: Rs Cr | C28: =Hist_BS!C28 -> 36 | D28: =Hist_BS!D28 -> 35 | E28: =Hist_BS!E28 -> 34 | F28: =Hist_BS!F28 -> 32 | G28: =Capex_Dep!G44 -> 28.91506 | H28: =Capex_Dep!H44 -> 25.674396 | I28: =Capex_Dep!I44 -> 22.047602 | J28: =Capex_Dep!J44 -> 17.801598 | K28: =Capex_Dep!K44 -> 12.89609
A29: Intangible Assets & Goodwill | B29: Rs Cr | C29: =Hist_BS!C29 -> 79 | D29: =Hist_BS!D29 -> 78 | E29: =Hist_BS!E29 -> 76 | F29: =Hist_BS!F29 -> 76 | G29: =F29 -> 76 | H29: =G29 -> 76 | I29: =H29 -> 76 | J29: =I29 -> 76 | K29: =J29 -> 76
A30: Non-Current Investments | B30: Rs Cr | C30: =Hist_BS!C30 -> 2531 | D30: =Hist_BS!D30 -> 2768 | E30: =Hist_BS!E30 -> 2638 | F30: =Hist_BS!F30 -> 2307 | G30: =F30 -> 2307 | H30: =G30 -> 2307 | I30: =H30 -> 2307 | J30: =I30 -> 2307 | K30: =J30 -> 2307
A31: Deferred Tax Assets (Net) | B31: Rs Cr | C31: =Hist_BS!C31 -> 36 | D31: =Hist_BS!D31 -> 41 | E31: =Hist_BS!E31 -> 44 | F31: =Hist_BS!F31 -> 51 | G31: =F31 -> 51 | H31: =G31 -> 51 | I31: =H31 -> 51 | J31: =I31 -> 51 | K31: =J31 -> 51
A32: Other Non-Current Assets | B32: Rs Cr | C32: =Hist_BS!C32 -> 692 | D32: =Hist_BS!D32 -> 632 | E32: =Hist_BS!E32 -> 580 | F32: =Hist_BS!F32 -> 758 | G32: =F32 -> 758 | H32: =G32 -> 758 | I32: =H32 -> 758 | J32: =I32 -> 758 | K32: =J32 -> 758
A33: Total Non-Current Assets | C33: =SUM(C26:C32) -> 3833 | D33: =SUM(D26:D32) -> 4312 | E33: =SUM(E26:E32) -> 4274 | F33: =SUM(F26:F32) -> 4181 | G33: =SUM(G26:G32) -> 4313.3731 | H33: =SUM(H26:H32) -> 4466.2924 | I33: =SUM(I26:I32) -> 4698.9705 | J33: =SUM(J26:J32) -> 4883.4536 | K33: =SUM(K26:K32) -> 5086.5231
A35: Inventories | B35: Rs Cr | C35: =Hist_BS!C35 -> 1592 | D35: =Hist_BS!D35 -> 2135 | E35: =Hist_BS!E35 -> 2715 | F35: =Hist_BS!F35 -> 3433 | G35: =WC_Schedule!G16 -> 3595.1049 | H35: =WC_Schedule!H16 -> 3921.1094 | I35: =WC_Schedule!I16 -> 4323.084 | J35: =WC_Schedule!J16 -> 4901.801 | K35: =WC_Schedule!K16 -> 5279.1311
A36: Trade Receivables | B36: Rs Cr | C36: =Hist_BS!C36 -> 2192 | D36: =Hist_BS!D36 -> 2533 | E36: =Hist_BS!E36 -> 2511 | F36: =Hist_BS!F36 -> 3035 | G36: =WC_Schedule!G15 -> 3220.6885 | H36: =WC_Schedule!H15 -> 4011.1254 | I36: =WC_Schedule!I15 -> 4462.5384 | J36: =WC_Schedule!J15 -> 5020.8005 | K36: =WC_Schedule!K15 -> 5514.5138
A37: Current Investments | B37: Rs Cr | C37: =Hist_BS!C38 -> 307 | D37: =Hist_BS!D38 -> 501 | E37: =Hist_BS!E38 -> 399 | F37: =Hist_BS!F38 -> 277 | G37: =F37 -> 277 | H37: =G37 -> 277 | I37: =H37 -> 277 | J37: =I37 -> 277 | K37: =J37 -> 277
A38: Other Current Assets (incl. Contract Assets) | B38: Rs Cr | C38: =Hist_BS!C39+Hist_BS!C40 -> 1647 | D38: =Hist_BS!D39+Hist_BS!D40 -> 1703 | E38: =Hist_BS!E39+Hist_BS!E40 -> 2575 | F38: =Hist_BS!F39+Hist_BS!F40 -> 2803 | G38: =WC_Schedule!G17 -> 3039.2413 | H38: =WC_Schedule!H17 -> 3281.8298 | I38: =WC_Schedule!I17 -> 3581.7742 | J38: =WC_Schedule!J17 -> 3977.5173 | K38: =WC_Schedule!K17 -> 4353.5635
A39: Cash & Cash Equivalents | B39: Rs Cr | C39: =Hist_BS!C37 -> 708 | D39: =Hist_BS!D37 -> 852 | E39: =Hist_BS!E37 -> 678 | F39: =Hist_BS!F37 -> 781 | G39: =Cash_Flow!G33 -> 1098.3375 | H39: =Cash_Flow!H33 -> 1300.5778 | I39: =Cash_Flow!I33 -> 1990.8047 | J39: =Cash_Flow!J33 -> 2328.1685 | K39: =Cash_Flow!K33 -> 3365.2083
A40: Total Current Assets | C40: =SUM(C35:C39) -> 6446 | D40: =SUM(D35:D39) -> 7724 | E40: =SUM(E35:E39) -> 8878 | F40: =SUM(F35:F39) -> 10329 | G40: =SUM(G35:G39) -> 11230.372 | H40: =SUM(H35:H39) -> 12791.642 | I40: =SUM(I35:I39) -> 14635.201 | J40: =SUM(J35:J39) -> 16505.287 | K40: =SUM(K35:K39) -> 18789.417
A41: TOTAL ASSETS | C41: =C33+C40 -> 10279 | D41: =D33+D40 -> 12036 | E41: =E33+E40 -> 13152 | F41: =F33+F40 -> 14510 | G41: =G33+G40 -> 15543.745 | H41: =H33+H40 -> 17257.935 | I41: =I33+I40 -> 19334.172 | J41: =J33+J40 -> 21388.741 | K41: =K33+K40 -> 23875.94
A43: BALANCE CHECK: Total Assets - Total Equity & Liabilities (opening FY26 source data differs by 1 due to rounding; carried forward) | C43: =C41-C23 -> 0 | D43: =D41-D23 -> 1 | E43: =E41-E23 -> 0 | F43: =F41-F23 -> 0 | G43: =G41-G23 -> 0 | H43: =H41-H23 -> 0 | I43: =I41-I23 -> 0 | J43: =J41-J23 -> 0 | K43: =K41-K23 -> 0

Sheet Cash_Flow
A1: VOLTAS LIMITED - CASH FLOW STATEMENT (INDIRECT METHOD)
A2: INR Crore unless stated
C4: HISTORICAL | G4: FORECAST
A5: Particulars | B5: Unit | C5: Mar-23A | D5: Mar-24A | E5: Mar-25A | F5: Mar-26A | G5: Mar-27E | H5: Mar-28E | I5: Mar-29E | J5: Mar-30E | K5: Mar-31E
A6: CASH FLOW FROM OPERATING ACTIVITIES
A7: Profit Before Tax | C7: =Hist_CF!C7 -> 306 | D7: =Hist_CF!D7 -> 484 | E7: =Hist_CF!E7 -> 1191 | F7: =Hist_CF!F7 -> 558 | G7: =Income_Statement!G23 -> 1049.4351 | H7: =Income_Statement!H23 -> 1312.9547 | I7: =Income_Statement!I23 -> 1610.4858 | J7: =Income_Statement!J23 -> 1769.4558 | K7: =Income_Statement!K23 -> 2042.4924
A8: Add: Depreciation & Amortization | C8: =Hist_CF!C8 -> 40 | D8: =Hist_CF!D8 -> 48 | E8: =Hist_CF!E8 -> 62 | F8: =Hist_CF!F8 -> 84 | G8: =Income_Statement!G16 -> 92.802894 | H8: =Income_Statement!H16 -> 105.66806 | I8: =Income_Statement!I16 -> 123.09194 | J8: =Income_Statement!J16 -> 139.19551 | K8: =Income_Statement!K16 -> 157.11532
A9: Add: Finance Costs | C9: =Hist_CF!C9 -> 30 | D9: =Hist_CF!D9 -> 56 | E9: =Hist_CF!E9 -> 62 | F9: =Hist_CF!F9 -> 87 | G9: =Income_Statement!G19 -> 100.99807 | H9: =Income_Statement!H19 -> 104.57577 | I9: =Income_Statement!I19 -> 107.15964 | J9: =Income_Statement!J19 -> 118.99949 | K9: =Income_Statement!K19 -> 132.42089
A10: Other Non-Cash Adjustments (forecast: nil - see E-13 on JV loss) | C10: =Hist_CF!C10 -> 333 | D10: =Hist_CF!D10 -> 304 | E10: =Hist_CF!E10 -> -134 | F10: =Hist_CF!F10 -> -95 | G10: 0 | H10: 0 | I10: 0 | J10: 0 | K10: 0
A11: Changes in Working Capital | C11: =Hist_CF!C11 -> -384 | D11: =Hist_CF!D11 -> 80 | E11: =Hist_CF!E11 -> -1094 | F11: =Hist_CF!F11 -> -352 | G11: =WC_Schedule!G22 -> -152.6743 | H11: =WC_Schedule!H22 -> -473.84612 | I11: =WC_Schedule!I22 -> -110.73119 | J11: =WC_Schedule!J22 -> -655.55447 | K11: =WC_Schedule!K22 -> -108.88128
A12: Less: Direct Taxes Paid | C12: =Hist_CF!C12 -> -166 | D12: =Hist_CF!D12 -> -212 | E12: =Hist_CF!E12 -> -311 | F12: =Hist_CF!F12 -> -211 | G12: =-Income_Statement!G24 -> -314.83052 | H12: =-Income_Statement!H24 -> -393.88641 | I12: =-Income_Statement!I24 -> -483.14573 | J12: =-Income_Statement!J24 -> -530.83674 | K12: =-Income_Statement!K24 -> -612.74771
A13: Net Cash from Operating Activities (CFO) | C13: =SUM(C7:C12) -> 159 | D13: =SUM(D7:D12) -> 760 | E13: =SUM(E7:E12) -> -224 | F13: =SUM(F7:F12) -> 71 | G13: =SUM(G7:G12) -> 775.73121 | H13: =SUM(H7:H12) -> 655.46599 | I13: =SUM(I7:I12) -> 1246.8604 | J13: =SUM(J7:J12) -> 841.25958 | K13: =SUM(K7:K12) -> 1610.3996
A15: CASH FLOW FROM INVESTING ACTIVITIES
A16: Purchase of PPE / Capex (forecast incl. ROU additions) | C16: =Hist_CF!C16 -> -180 | D16: =Hist_CF!D16 -> -293 | E16: =Hist_CF!E16 -> -208 | F16: =Hist_CF!F16 -> -133 | G16: =-Capex_Dep!G58 -> -225.17602 | H16: =-Capex_Dep!H58 -> -258.58735 | I16: =-Capex_Dep!I58 -> -355.77 | J16: =-Capex_Dep!J58 -> -323.67862 | K16: =-Capex_Dep!K58 -> -360.18482
A17: Proceeds from Sale of Assets | C17: =Hist_CF!C17 -> 2 | D17: =Hist_CF!D17 -> 5 | E17: =Hist_CF!E17 -> 17 | F17: =Hist_CF!F17 -> 4 | G17: 0 | H17: 0 | I17: 0 | J17: 0 | K17: 0
A18: Purchase / Sale of Investments (Net) | C18: =Hist_CF!C18 -> 25 | D18: =Hist_CF!D18 -> -318 | E18: =Hist_CF!E18 -> 218 | F18: =Hist_CF!F18 -> 306 | G18: 0 | H18: 0 | I18: 0 | J18: 0 | K18: 0
A19: Interest & Dividend Received | C19: =Hist_CF!C19 -> 71 | D19: =Hist_CF!D19 -> 83 | E19: =Hist_CF!E19 -> 131 | F19: =Hist_CF!F19 -> 105 | G19: 0 | H19: 0 | I19: 0 | J19: 0 | K19: 0
A20: Net Cash from Investing Activities (CFI) | C20: =SUM(C16:C19) -> -82 | D20: =SUM(D16:D19) -> -523 | E20: =SUM(E16:E19) -> 158 | F20: =SUM(F16:F19) -> 282 | G20: =SUM(G16:G19) -> -225.17602 | H20: =SUM(H16:H19) -> -258.58735 | I20: =SUM(I16:I19) -> -355.77 | J20: =SUM(J16:J19) -> -323.67862 | K20: =SUM(K16:K19) -> -360.18482
A22: CASH FLOW FROM FINANCING ACTIVITIES
A23: Proceeds from Borrowings (LT+ST) | C23: =Hist_CF!C23 -> 1504 | D23: =Hist_CF!D23 -> 590 | E23: =Hist_CF!E23 -> 454 | F23: =Hist_CF!F23 -> 2112 | G23: =Debt_Schedule!G14+Debt_Schedule!G8+Debt_Schedule!G19 -> 56.500371 | H23: =Debt_Schedule!H14+Debt_Schedule!H8+Debt_Schedule!H19 -> 90.197465 | I23: =Debt_Schedule!I14+Debt_Schedule!I8+Debt_Schedule!I19 -> 79.365047 | J23: =Debt_Schedule!J14+Debt_Schedule!J8+Debt_Schedule!J19 -> 105.73905 | K23: =Debt_Schedule!K14+Debt_Schedule!K8+Debt_Schedule!K19 -> 81.007042
A24: Repayment of Borrowings (LT+ST) | C24: =Hist_CF!C24 -> -1231 | D24: =Hist_CF!D24 -> -493 | E24: =Hist_CF!E24 -> -304 | F24: =Hist_CF!F24 -> -2039 | G24: =-Debt_Schedule!G9 -> -56.4 | H24: =-Debt_Schedule!H9 -> -47.94 | I24: =-Debt_Schedule!I9 -> -40.749 | J24: =-Debt_Schedule!J9 -> -34.63665 | K24: =-Debt_Schedule!K9 -> -29.441153
A25: Payment of Lease Liabilities | C25: =Hist_CF!C25 -> -10 | D25: =Hist_CF!D25 -> -18 | E25: =Hist_CF!E25 -> -14 | F25: =Hist_CF!F25 -> -14 | G25: =-Debt_Schedule!G20 -> 0 | H25: =-Debt_Schedule!H20 -> 0 | I25: =-Debt_Schedule!I20 -> 0 | J25: =-Debt_Schedule!J20 -> 0 | K25: =-Debt_Schedule!K20 -> 0
A26: Interest Paid | C26: =Hist_CF!C26 -> -25 | D26: =Hist_CF!D26 -> -52 | E26: =Hist_CF!E26 -> -54 | F26: =Hist_CF!F26 -> -89 | G26: =-Income_Statement!G19 -> -100.99807 | H26: =-Income_Statement!H19 -> -104.57577 | I26: =-Income_Statement!I19 -> -107.15964 | J26: =-Income_Statement!J19 -> -118.99949 | K26: =-Income_Statement!K19 -> -132.42089
A27: Dividend Paid | C27: =Hist_CF!C27 -> -183 | D27: =Hist_CF!D27 -> -143 | E27: =Hist_CF!E27 -> -182 | F27: =Hist_CF!F27 -> -232 | G27: =-Equity_Schedule!G12 -> -132.32 | H27: =-Equity_Schedule!H12 -> -132.32 | I27: =-Equity_Schedule!I12 -> -132.32 | J27: =-Equity_Schedule!J12 -> -132.32 | K27: =-Equity_Schedule!K12 -> -132.32
A28: Buyback of Shares / Other Financing | C28: =Hist_CF!C28 -> 0 | D28: =Hist_CF!D28 -> 0 | E28: =Hist_CF!E28 -> 0 | F28: =Hist_CF!F28 -> 0 | G28: 0 | H28: 0 | I28: 0 | J28: 0 | K28: 0
A29: Net Cash from Financing Activities (CFF) | C29: =SUM(C23:C28) -> 55 | D29: =SUM(D23:D28) -> -116 | E29: =SUM(E23:E28) -> -100 | F29: =SUM(F23:F28) -> -262 | G29: =SUM(G23:G28) -> -233.2177 | H29: =SUM(H23:H28) -> -194.6383 | I29: =SUM(I23:I28) -> -200.86359 | J29: =SUM(J23:J28) -> -180.21709 | K29: =SUM(K23:K28) -> -213.175
A31: Net Increase / (Decrease) in Cash | C31: =C13+C20+C29 -> 132 | D31: =D13+D20+D29 -> 121 | E31: =E13+E20+E29 -> -166 | F31: =F13+F20+F29 -> 91 | G31: =G13+G20+G29 -> 317.33749 | H31: =H13+H20+H29 -> 202.24033 | I31: =I13+I20+I29 -> 690.22684 | J31: =J13+J20+J29 -> 337.36387 | K31: =K13+K20+K29 -> 1037.0398
A32: Opening Cash & Cash Equivalents | C32: =Hist_CF!C32 -> 561 | D32: =Hist_CF!D32 -> 693 | E32: =Hist_CF!E32 -> 816 | F32: =Hist_CF!F32 -> 650 | G32: =Balance_Sheet!F39 -> 781 | H32: =Balance_Sheet!G39 -> 1098.3375 | I32: =Balance_Sheet!H39 -> 1300.5778 | J32: =Balance_Sheet!I39 -> 1990.8047 | K32: =Balance_Sheet!J39 -> 2328.1685
A33: Closing Cash & Cash Equivalents | C33: =C32+C31 -> 693 | D33: =D32+D31 -> 814 | E33: =E32+E31 -> 650 | F33: =F32+F31 -> 741 | G33: =G32+G31 -> 1098.3375 | H33: =H32+H31 -> 1300.5778 | I33: =I32+I31 -> 1990.8047 | J33: =J32+J31 -> 2328.1685 | K33: =K32+K31 -> 3365.2083
A35: FREE CASH FLOW TO FIRM (FCFF) & FREE CASH FLOW TO EQUITY (FCFE) - AS PUBLISHED
A36: EBIT | C36: =Income_Statement!C17 -> 533 | D36: =Income_Statement!D17 -> 426 | E36: =Income_Statement!E17 -> 1055 | F36: =Income_Statement!F17 -> 564 | G36: =Income_Statement!G17 -> 950.29192 | H36: =Income_Statement!H17 -> 1206.2825 | I36: =Income_Statement!I17 -> 1420.0069 | J36: =Income_Statement!J17 -> 1574.3972 | K36: =Income_Statement!K17 -> 1776.2297
A37: Tax rate applied (historical = effective rate; forecast = Assumptions) | C37: =Income_Statement!C32 -> 0.55882353 | D37: =Income_Statement!D32 -> 0.49173554 | E37: =Income_Statement!E32 -> 0.29890848 | F37: =Income_Statement!F32 -> 0.33512545 | G37: =Assumptions!G25 -> 0.3 | H37: =Assumptions!H25 -> 0.3 | I37: =Assumptions!I25 -> 0.3 | J37: =Assumptions!J25 -> 0.3 | K37: =Assumptions!K25 -> 0.3
A38: Less: Tax on EBIT (at Effective Tax Rate) | C38: =-C36*C37 -> -297.85294 | D38: =-D36*D37 -> -209.47934 | E38: =-E36*E37 -> -315.34845 | F38: =-F36*F37 -> -189.01075 | G38: =-G36*G37 -> -285.08758 | H38: =-H36*H37 -> -361.88475 | I38: =-I36*I37 -> -426.00206 | J38: =-J36*J37 -> -472.31915 | K38: =-K36*K37 -> -532.8689
A39: NOPAT (EBIT x (1-t)) | C39: =C36+C38 -> 235.14706 | D39: =D36+D38 -> 216.52066 | E39: =E36+E38 -> 739.65155 | F39: =F36+F38 -> 374.98925 | G39: =G36+G38 -> 665.20435 | H39: =H36+H38 -> 844.39774 | I39: =I36+I38 -> 994.0048 | J39: =J36+J38 -> 1102.078 | K39: =K36+K38 -> 1243.3608
A40: Add: Depreciation & Amortization | G40: =Income_Statement!G16 -> 92.802894 | H40: =Income_Statement!H16 -> 105.66806 | I40: =Income_Statement!I16 -> 123.09194 | J40: =Income_Statement!J16 -> 139.19551 | K40: =Income_Statement!K16 -> 157.11532
A41: Less: Capex - AS PUBLISHED (PPE capex MINUS ROU additions - sign error, see E-01) | G41: =-(Capex_Dep!G9-Capex_Dep!G36) -> -205.30755 | H41: =-(Capex_Dep!H9-Capex_Dep!H36) -> -235.77082 | I41: =-(Capex_Dep!I9-Capex_Dep!I36) -> -330.05169 | J41: =-(Capex_Dep!J9-Capex_Dep!J36) -> -295.11874 | K41: =-(Capex_Dep!K9-Capex_Dep!K36) -> -328.40381
A42: Less: Increase in Net Working Capital | G42: =WC_Schedule!G22 -> -152.6743 | H42: =WC_Schedule!H22 -> -473.84612 | I42: =WC_Schedule!I22 -> -110.73119 | J42: =WC_Schedule!J22 -> -655.55447 | K42: =WC_Schedule!K22 -> -108.88128
A43: FREE CASH FLOW TO FIRM (FCFF) - as published | G43: =G39+G40+G41+G42 -> 400.02539 | H43: =H39+H40+H41+H42 -> 240.44886 | I43: =I39+I40+I41+I42 -> 676.31386 | J43: =J39+J40+J41+J42 -> 290.60032 | K43: =K39+K40+K41+K42 -> 963.19101
A44: Less: After-Tax Interest Expense | G44: =-Income_Statement!G19*(1-Assumptions!G25) -> -70.698649 | H44: =-Income_Statement!H19*(1-Assumptions!H25) -> -73.203038 | I44: =-Income_Statement!I19*(1-Assumptions!I25) -> -75.011747 | J44: =-Income_Statement!J19*(1-Assumptions!J25) -> -83.299644 | K44: =-Income_Statement!K19*(1-Assumptions!K25) -> -92.694623
A45: Add: Net Borrowings (New Debt - Repayments) | G45: =G23+G24 -> 0.10037102 | H45: =H23+H24 -> 42.257465 | I45: =I23+I24 -> 38.616047 | J45: =J23+J24 -> 71.102403 | K45: =K23+K24 -> 51.56589
A46: FREE CASH FLOW TO EQUITY (FCFE) | G46: =G43+G44+G45 -> 329.42712 | H46: =H43+H44+H45 -> 209.50329 | I46: =I43+I44+I45 -> 639.91816 | J46: =J43+J44+J45 -> 278.40308 | K46: =K43+K44+K45 -> 922.06227
A47: CORRECTED FCFF (added by reviewer)
A48: Less: Capex - CORRECTED (PPE capex PLUS ROU additions = Cash Flow capex) | G48: =G16 -> -225.17602 | H48: =H16 -> -258.58735 | I48: =I16 -> -355.77 | J48: =J16 -> -323.67862 | K48: =K16 -> -360.18482
A49: FREE CASH FLOW TO FIRM (FCFF) - corrected | G49: =G39+G40+G48+G42 -> 380.15692 | H49: =H39+H40+H48+H42 -> 217.63233 | I49: =I39+I40+I48+I42 -> 650.59555 | J49: =J39+J40+J48+J42 -> 262.04044 | K49: =K39+K40+K48+K42 -> 931.40999
A50: Overstatement of published FCFF | G50: =G43-G49 -> 19.868473 | H50: =H43-H49 -> 22.816531 | I50: =I43-I49 -> 25.718313 | J50: =J43-J49 -> 28.559878 | K50: =K43-K49 -> 31.781014
A51: RECONCILIATION CHECKS (added)
A52: Cash per Balance Sheet | C52: =Balance_Sheet!C39 -> 708 | D52: =Balance_Sheet!D39 -> 852 | E52: =Balance_Sheet!E39 -> 678 | F52: =Balance_Sheet!F39 -> 781 | G52: =Balance_Sheet!G39 -> 1098.3375 | H52: =Balance_Sheet!H39 -> 1300.5778 | I52: =Balance_Sheet!I39 -> 1990.8047 | J52: =Balance_Sheet!J39 -> 2328.1685 | K52: =Balance_Sheet!K39 -> 3365.2083
A53: Difference: CF closing cash - Balance Sheet cash | C53: =C33-C52 -> -15 | D53: =D33-D52 -> -38 | E53: =E33-E52 -> -28 | F53: =F33-F52 -> -40 | G53: =G33-G52 -> 0 | H53: =H33-H52 -> 0 | I53: =I33-I52 -> 0 | J53: =J33-J52 -> 0 | K53: =K33-K52 -> 0

Sheet Ratios
A1: VOLTAS LIMITED - RATIO ANALYSIS
A2: INR Crore unless stated
C4: HISTORICAL | G4: FORECAST
A5: Particulars | B5: Unit | C5: Mar-23A | D5: Mar-24A | E5: Mar-25A | F5: Mar-26A | G5: Mar-27E | H5: Mar-28E | I5: Mar-29E | J5: Mar-30E | K5: Mar-31E
A6: PROFITABILITY RATIOS
A7: Gross Margin % ((Rev-COGS)/Rev) | C7: =(Income_Statement!C6-Income_Statement!C9)/Income_Statement!C6 -> 0.22328666 | D7: =(Income_Statement!D6-Income_Statement!D9)/Income_Statement!D6 -> 0.2136848 | E7: =(Income_Statement!E6-Income_Statement!E9)/Income_Statement!E6 -> 0.22403166 | F7: =(Income_Statement!F6-Income_Statement!F9)/Income_Statement!F6 -> 0.22295542 | G7: =(Income_Statement!G6-Income_Statement!G9)/Income_Statement!G6 -> 0.223 | H7: =(Income_Statement!H6-Income_Statement!H9)/Income_Statement!H6 -> 0.224 | I7: =(Income_Statement!I6-Income_Statement!I9)/Income_Statement!I6 -> 0.225 | J7: =(Income_Statement!J6-Income_Statement!J9)/Income_Statement!J6 -> 0.225 | K7: =(Income_Statement!K6-Income_Statement!K9)/Income_Statement!K6 -> 0.226
A8: EBITDA Margin % | C8: =Income_Statement!C14/Income_Statement!C6 -> 0.060322139 | D8: =Income_Statement!D14/Income_Statement!D6 -> 0.037977726 | E8: =Income_Statement!E14/Income_Statement!E6 -> 0.07247129 | F8: =Income_Statement!F14/Income_Statement!F6 -> 0.045489645 | G8: =Income_Statement!G14/Income_Statement!G6 -> 0.063 | H8: =Income_Statement!H14/Income_Statement!H6 -> 0.069 | I8: =Income_Statement!I14/Income_Statement!I6 -> 0.072 | J8: =Income_Statement!J14/Income_Statement!J6 -> 0.072 | K8: =Income_Statement!K14/Income_Statement!K6 -> 0.073
A9: EBIT Margin % | C9: =Income_Statement!C17/Income_Statement!C6 -> 0.05611117 | D9: =Income_Statement!D17/Income_Statement!D6 -> 0.03413188 | E9: =Income_Statement!E17/Income_Statement!E6 -> 0.068448712 | F9: =Income_Statement!F17/Income_Statement!F6 -> 0.03959284 | G9: =Income_Statement!G17/Income_Statement!G6 -> 0.057394966 | H9: =Income_Statement!H17/Income_Statement!H6 -> 0.063442553 | I9: =Income_Statement!I17/Income_Statement!I6 -> 0.066256609 | J9: =Income_Statement!J17/Income_Statement!J6 -> 0.066151424 | K9: =Income_Statement!K17/Income_Statement!K6 -> 0.067067578
A10: Net (PAT) Margin % | C10: =Income_Statement!C25/Income_Statement!C6 -> 0.014212022 | D10: =Income_Statement!D25/Income_Statement!D6 -> 0.019709959 | E10: =Income_Statement!E25/Income_Statement!E6 -> 0.054175047 | F10: =Income_Statement!F25/Income_Statement!F6 -> 0.026044226 | G10: =Income_Statement!G25/Income_Statement!G6 -> 0.044368053 | H10: =Income_Statement!H25/Income_Statement!H6 -> 0.048336968 | I10: =Income_Statement!I25/Income_Statement!I6 -> 0.052600963 | J10: =Income_Statement!J25/Income_Statement!J6 -> 0.052043039 | K10: =Income_Statement!K25/Income_Statement!K6 -> 0.05398486
A11: Return on Equity (ROE) % (PAT / average equity; FY23 on closing) | C11: =Income_Statement!C27/Balance_Sheet!C10 -> 0.024572261 | D11: =Income_Statement!D27/AVERAGE(Balance_Sheet!C10,Balance_Sheet!D10) -> 0.043355657 | E11: =Income_Statement!E27/AVERAGE(Balance_Sheet!D10,Balance_Sheet!E10) -> 0.13474262 | F11: =Income_Statement!F27/AVERAGE(Balance_Sheet!E10,Balance_Sheet!F10) -> 0.057346008 | G11: =Income_Statement!G27/AVERAGE(Balance_Sheet!F10,Balance_Sheet!G10) -> 0.10964014 | H11: =Income_Statement!H27/AVERAGE(Balance_Sheet!G10,Balance_Sheet!H10) -> 0.12428813 | I11: =Income_Statement!I27/AVERAGE(Balance_Sheet!H10,Balance_Sheet!I10) -> 0.1360611 | J11: =Income_Statement!J27/AVERAGE(Balance_Sheet!I10,Balance_Sheet!J10) -> 0.1326684 | K11: =Income_Statement!K27/AVERAGE(Balance_Sheet!J10,Balance_Sheet!K10) -> 0.13567432
A12: Return on Capital Employed (ROCE) % (EBIT / (Equity + Debt)) | C12: =Income_Statement!C17/(Balance_Sheet!C10+Debt_Schedule!C23) -> 0.086878566 | D12: =Income_Statement!D17/(Balance_Sheet!D10+Debt_Schedule!D23) -> 0.064663024 | E12: =Income_Statement!E17/(Balance_Sheet!E10+Debt_Schedule!E23) -> 0.14214497 | F12: =Income_Statement!F17/(Balance_Sheet!F10+Debt_Schedule!F23) -> 0.07641241 | G12: =Income_Statement!G17/(Balance_Sheet!G10+Debt_Schedule!G23) -> 0.11903371 | H12: =Income_Statement!H17/(Balance_Sheet!H10+Debt_Schedule!H23) -> 0.13688482 | I12: =Income_Statement!I17/(Balance_Sheet!I10+Debt_Schedule!I23) -> 0.14422131 | J12: =Income_Statement!J17/(Balance_Sheet!J10+Debt_Schedule!J23) -> 0.14282283 | K12: =Income_Statement!K17/(Balance_Sheet!K10+Debt_Schedule!K23) -> 0.14356366
A13: Return on Assets (ROA) % (PAT / closing total assets) | C13: =Income_Statement!C25/Balance_Sheet!C41 -> 0.013133573 | D13: =Income_Statement!D25/Balance_Sheet!D41 -> 0.020438684 | E13: =Income_Statement!E25/Balance_Sheet!E41 -> 0.063488443 | F13: =Income_Statement!F25/Balance_Sheet!F41 -> 0.025568573 | G13: =Income_Statement!G25/Balance_Sheet!G41 -> 0.04726046 | H13: =Income_Statement!H25/Balance_Sheet!H41 -> 0.053254824 | I13: =Income_Statement!I25/Balance_Sheet!I41 -> 0.058308163 | J13: =Income_Statement!J25/Balance_Sheet!J41 -> 0.057909863 | K13: =Income_Statement!K25/Balance_Sheet!K41 -> 0.059882235
A14: LIQUIDITY RATIOS
A15: Current Ratio (x) | C15: =Balance_Sheet!C40/Balance_Sheet!C22 -> 1.3952381 | D15: =Balance_Sheet!D40/Balance_Sheet!D22 -> 1.3419041 | E15: =Balance_Sheet!E40/Balance_Sheet!E22 -> 1.4781885 | F15: =Balance_Sheet!F40/Balance_Sheet!F22 -> 1.367355 | G15: =Balance_Sheet!G40/Balance_Sheet!G22 -> 1.3964893 | H15: =Balance_Sheet!H40/Balance_Sheet!H22 -> 1.4185759 | I15: =Balance_Sheet!I40/Balance_Sheet!I22 -> 1.4434265 | J15: =Balance_Sheet!J40/Balance_Sheet!J22 -> 1.4840062 | K15: =Balance_Sheet!K40/Balance_Sheet!K22 -> 1.5224791
A16: Quick Ratio (x) | C16: =(Balance_Sheet!C40-Balance_Sheet!C35)/Balance_Sheet!C22 -> 1.0506494 | D16: =(Balance_Sheet!D40-Balance_Sheet!D35)/Balance_Sheet!D22 -> 0.9709868 | E16: =(Balance_Sheet!E40-Balance_Sheet!E35)/Balance_Sheet!E22 -> 1.0261405 | F16: =(Balance_Sheet!F40-Balance_Sheet!F35)/Balance_Sheet!F22 -> 0.91289383 | G16: =(Balance_Sheet!G40-Balance_Sheet!G35)/Balance_Sheet!G22 -> 0.94944037 | H16: =(Balance_Sheet!H40-Balance_Sheet!H35)/Balance_Sheet!H22 -> 0.98373016 | I16: =(Balance_Sheet!I40-Balance_Sheet!I35)/Balance_Sheet!I22 -> 1.0170535 | J16: =(Balance_Sheet!J40-Balance_Sheet!J35)/Balance_Sheet!J22 -> 1.0432806 | K16: =(Balance_Sheet!K40-Balance_Sheet!K35)/Balance_Sheet!K22 -> 1.0947188
A17: Cash Ratio (x) | C17: =Balance_Sheet!C39/Balance_Sheet!C22 -> 0.15324675 | D17: =Balance_Sheet!D39/Balance_Sheet!D22 -> 0.14801946 | E17: =Balance_Sheet!E39/Balance_Sheet!E22 -> 0.11288711 | F17: =Balance_Sheet!F39/Balance_Sheet!F22 -> 0.10338893 | G17: =Balance_Sheet!G39/Balance_Sheet!G22 -> 0.13657753 | H17: =Balance_Sheet!H39/Balance_Sheet!H22 -> 0.14423233 | I17: =Balance_Sheet!I39/Balance_Sheet!I22 -> 0.19634716 | J17: =Balance_Sheet!J39/Balance_Sheet!J22 -> 0.20932787 | K17: =Balance_Sheet!K39/Balance_Sheet!K22 -> 0.27267793
A18: EFFICIENCY RATIOS
A19: Asset Turnover (x) | C19: =Income_Statement!C6/Balance_Sheet!C41 -> 0.92411713 | D19: =Income_Statement!D6/Balance_Sheet!D41 -> 1.0369724 | E19: =Income_Statement!E6/Balance_Sheet!E41 -> 1.171913 | F19: =Income_Statement!F6/Balance_Sheet!F41 -> 0.98173673 | G19: =Income_Statement!G6/Balance_Sheet!G41 -> 1.0651912 | H19: =Income_Statement!H6/Balance_Sheet!H41 -> 1.1017411 | I19: =Income_Statement!I6/Balance_Sheet!I41 -> 1.1084999 | J19: =Income_Statement!J6/Balance_Sheet!J41 -> 1.1127302 | K19: =Income_Statement!K6/Balance_Sheet!K41 -> 1.1092413
A20: Inventory Turnover (x) | C20: =Income_Statement!C9/Balance_Sheet!C35 -> 4.6344221 | D20: =Income_Statement!D9/Balance_Sheet!D35 -> 4.5967213 | E20: =Income_Statement!E9/Balance_Sheet!E35 -> 4.4051565 | F20: =Income_Statement!F9/Balance_Sheet!F35 -> 3.2242936 | G20: =Income_Statement!G9/Balance_Sheet!G35 -> 3.5784314 | H20: =Income_Statement!H9/Balance_Sheet!H35 -> 3.7628866 | I20: =Income_Statement!I9/Balance_Sheet!I35 -> 3.8421053 | J20: =Income_Statement!J9/Balance_Sheet!J35 -> 3.7628866 | K20: =Income_Statement!K9/Balance_Sheet!K35 -> 3.8829787
A21: Receivable Days | C21: =WC_Schedule!C9 -> 84.227813 | D21: =WC_Schedule!D9 -> 74.076196 | E21: =WC_Schedule!E9 -> 59.463764 | F21: =WC_Schedule!F9 -> 77.765883 | G21: =WC_Schedule!G9 -> 71 | H21: =WC_Schedule!H9 -> 77 | I21: =WC_Schedule!I9 -> 76 | J21: =WC_Schedule!J9 -> 77 | K21: =WC_Schedule!K9 -> 76
A22: Payable Days | C22: =WC_Schedule!C11 -> 149.05733 | D22: =WC_Schedule!D11 -> 143.41145 | E22: =WC_Schedule!E11 -> 118.80811 | F22: =WC_Schedule!F11 -> 172.39317 | G22: =WC_Schedule!G11 -> 158 | H22: =WC_Schedule!H11 -> 153 | I22: =WC_Schedule!I11 -> 153 | J22: =WC_Schedule!J11 -> 150 | K22: =WC_Schedule!K11 -> 150
A23: Cash Conversion Cycle (Days) = DSO + DIO - DPO | C23: =WC_Schedule!C9+WC_Schedule!C10-WC_Schedule!C11 -> 13.928952 | D23: =WC_Schedule!D9+WC_Schedule!D10-WC_Schedule!D11 -> 10.069165 | E23: =WC_Schedule!E9+WC_Schedule!E10-WC_Schedule!E11 -> 23.513095 | F23: =WC_Schedule!F9+WC_Schedule!F10-WC_Schedule!F11 -> 18.575802 | G23: =WC_Schedule!G9+WC_Schedule!G10-WC_Schedule!G11 -> 15 | H23: =WC_Schedule!H9+WC_Schedule!H10-WC_Schedule!H11 -> 21 | I23: =WC_Schedule!I9+WC_Schedule!I10-WC_Schedule!I11 -> 18 | J23: =WC_Schedule!J9+WC_Schedule!J10-WC_Schedule!J11 -> 24 | K23: =WC_Schedule!K9+WC_Schedule!K10-WC_Schedule!K11 -> 20
A24: LEVERAGE RATIOS
A25: Debt / Equity (x) | C25: =Debt_Schedule!C23/Balance_Sheet!C10 -> 0.11667273 | D25: =Debt_Schedule!D23/Balance_Sheet!D10 -> 0.12538435 | E25: =Debt_Schedule!E23/Balance_Sheet!E10 -> 0.13486239 | F25: =Debt_Schedule!F23/Balance_Sheet!F10 -> 0.15346148 | G25: =Debt_Schedule!G23/Balance_Sheet!G10 -> 0.14027431 | H25: =Debt_Schedule!H23/Balance_Sheet!H10 -> 0.13152973 | I25: =Debt_Schedule!I23/Balance_Sheet!I10 -> 0.12102556 | J25: =Debt_Schedule!J23/Balance_Sheet!J10 -> 0.1146765 | K25: =Debt_Schedule!K23/Balance_Sheet!K10 -> 0.10598604
A26: Interest Coverage Ratio (EBIT/Interest) (x) | C26: =Income_Statement!C17/Income_Statement!C19 -> 17.766667 | D26: =Income_Statement!D17/Income_Statement!D19 -> 7.6071429 | E26: =Income_Statement!E17/Income_Statement!E19 -> 17.016129 | F26: =Income_Statement!F17/Income_Statement!F19 -> 6.4827586 | G26: =Income_Statement!G17/Income_Statement!G19 -> 9.4090108 | H26: =Income_Statement!H17/Income_Statement!H19 -> 11.53501 | I26: =Income_Statement!I17/Income_Statement!I19 -> 13.251322 | J26: =Income_Statement!J17/Income_Statement!J19 -> 13.230285 | K26: =Income_Statement!K17/Income_Statement!K19 -> 13.413516
A27: Net Debt / EBITDA (x) (borrowings LT+ST less cash) | C27: =(Debt_Schedule!C26-Balance_Sheet!C39)/Income_Statement!C14 -> -0.16055846 | D27: =(Debt_Schedule!D26-Balance_Sheet!D39)/Income_Statement!D14 -> -0.29324895 | E27: =(Debt_Schedule!E26-Balance_Sheet!E39)/Income_Statement!E14 -> 0.16651746 | F27: =(Debt_Schedule!F26-Balance_Sheet!F39)/Income_Statement!F14 -> 0.28703704 | G27: =(Debt_Schedule!G26-Balance_Sheet!G39)/Income_Statement!G14 -> -0.12581514 | H27: =(Debt_Schedule!H26-Balance_Sheet!H39)/Income_Statement!H14 -> -0.22197482 | I27: =(Debt_Schedule!I26-Balance_Sheet!I39)/Income_Statement!I14 -> -0.61099833 | J27: =(Debt_Schedule!J26-Balance_Sheet!J39)/Income_Statement!J14 -> -0.70558906 | K27: =(Debt_Schedule!K26-Balance_Sheet!K39)/Income_Statement!K14 -> -1.1351136
A28: MARKET DATA FOR VALUATION RATIOS
A29: Share price used (Rs) [hist: year-end price; forecast: current price] | C29: 818 | D29: 1103 | E29: 1458 | F29: 1272 | G29: =Assumptions!$C$8 -> 1033 | H29: =Assumptions!$C$8 -> 1033 | I29: =Assumptions!$C$8 -> 1033 | J29: =Assumptions!$C$8 -> 1033 | K29: =Assumptions!$C$8 -> 1033
A30: Market capitalisation (Rs Cr) | C30: =C29*Assumptions!$C$9 -> 27059.44 | D30: =D29*Assumptions!$C$9 -> 36487.24 | E30: =E29*Assumptions!$C$9 -> 48230.64 | F30: =F29*Assumptions!$C$9 -> 42077.76 | G30: =G29*Assumptions!$C$9 -> 34171.64 | H30: =H29*Assumptions!$C$9 -> 34171.64 | I30: =I29*Assumptions!$C$9 -> 34171.64 | J30: =J29*Assumptions!$C$9 -> 34171.64 | K30: =K29*Assumptions!$C$9 -> 34171.64
A31: Enterprise value (Rs Cr) = Mkt cap + borrowings - cash | C31: =C30+Debt_Schedule!C26-Balance_Sheet!C39 -> 26967.44 | D31: =D30+Debt_Schedule!D26-Balance_Sheet!D39 -> 36348.24 | E31: =E30+Debt_Schedule!E26-Balance_Sheet!E39 -> 48416.64 | F31: =F30+Debt_Schedule!F26-Balance_Sheet!F39 -> 42263.76 | G31: =G30+Debt_Schedule!G26-Balance_Sheet!G39 -> 34040.403 | H31: =H30+Debt_Schedule!H26-Balance_Sheet!H39 -> 33880.42 | I31: =I30+Debt_Schedule!I26-Balance_Sheet!I39 -> 33228.809 | J31: =J30+Debt_Schedule!J26-Balance_Sheet!J39 -> 32962.548 | K31: =K30+Debt_Schedule!K26-Balance_Sheet!K39 -> 31977.074
A32: VALUATION RATIOS (based on the share price above)
A33: EV / EBITDA (x) | C33: =C31/Income_Statement!C14 -> 47.063595 | D33: =D31/Income_Statement!D14 -> 76.684051 | E33: =E31/Income_Statement!E14 -> 43.345246 | F33: =F31/Income_Statement!F14 -> 65.221852 | G33: =G31/Income_Statement!G14 -> 32.634045 | H33: =H31/Income_Statement!H14 -> 25.824464 | I33: =I31/Income_Statement!I14 -> 21.533818 | J33: =J31/Income_Statement!J14 -> 19.235929 | K33: =K31/Income_Statement!K14 -> 16.539766
A34: P/E (x) | C34: =C30/Income_Statement!C27 -> 200.4403 | D34: =D30/Income_Statement!D27 -> 148.32211 | E34: =E30/Income_Statement!E27 -> 57.761246 | F34: =F30/Income_Statement!F27 -> 113.41714 | G34: =G30/Income_Statement!G27 -> 46.517055 | H34: =H30/Income_Statement!H27 -> 37.180741 | I34: =I30/Income_Statement!I27 -> 30.311742 | J34: =J30/Income_Statement!J27 -> 27.588499 | K34: =K30/Income_Statement!K27 -> 23.90052
A35: P/B (x) | C35: =C30/Balance_Sheet!C10 -> 4.9252712 | D35: =D30/Balance_Sheet!D10 -> 6.2328732 | E35: =E30/Balance_Sheet!E10 -> 7.3747156 | F35: =F30/Balance_Sheet!F10 -> 6.5756774 | G35: =G30/Balance_Sheet!G10 -> 4.8807672 | H35: =H30/Balance_Sheet!H10 -> 4.3877113 | I35: =I30/Balance_Sheet!I10 -> 3.8906335 | J35: =J30/Balance_Sheet!J10 -> 3.4553973 | K35: =K30/Balance_Sheet!K10 -> 3.0546458
A36: Dividend Yield % | C36: =-Cash_Flow!C27/C30 -> 0.0067628894 | D36: =-Cash_Flow!D27/D30 -> 0.0039191783 | E36: =-Cash_Flow!E27/E30 -> 0.0037735348 | F36: =-Cash_Flow!F27/F30 -> 0.0055136015 | G36: =-Cash_Flow!G27/G30 -> 0.0038722168 | H36: =-Cash_Flow!H27/H30 -> 0.0038722168 | I36: =-Cash_Flow!I27/I30 -> 0.0038722168 | J36: =-Cash_Flow!J27/J30 -> 0.0038722168 | K36: =-Cash_Flow!K27/K30 -> 0.0038722168

Sheet Market_Data
A1: VOLTAS LIMITED - PEER MARKET DATA & WEEKLY PRICE HISTORY (inputs to beta)
A2: Source: Screener.in / exchange prices as shown in the report (INR Crore unless stated). Blue = hard-coded from report.
A3: S.No. | B3: Company | C3: CMP Rs. | D3: Debt Rs.Cr. | E3: No. Eq. Shares Cr. | F3: Market Value of Equity | G3: EV Rs.Cr. | H3: Cash End Rs.Cr. | I3: Sales Rs.Cr. | J3: NP 12M Rs.Cr. | K3: Ind PE | L3: Debt / Eq | M3: EBITDA Cr. | N3: Net Debt (=Debt-Cash) | O3: Check: CMP x Shares - Mkt cap
A4: 1 | B4: LG Electronics | C4: 1718 | D4: 459 | E4: 67.88 | F4: 116618 | G4: 112596 | H4: 4476 | I4: 25575 | J4: 1824.7 | K4: 33.7 | L4: 0.1 | M4: 2412.9 | N4: =D4-H4 -> -4017 | O4: =C4*E4-F4 -> -0.16
A5: 2 | B5: Voltas | C5: 1032.85 | D5: 992 | E5: 33.09 | F5: 34177 | G5: 34387 | H5: 781 | I5: 14979 | J5: 442.2 | K5: 33.7 | L5: 0.2 | M5: 516.3 | N5: =D5-H5 -> 211 | O5: =C5*E5-F5 -> 0.0065
A6: 3 | B6: Blue Star | C6: 1571.75 | D6: 810 | E6: 20.56 | F6: 32315 | G6: 32725 | H6: 402 | I6: 12798 | J6: 509 | K6: 33.7 | L6: 0.2 | M6: 933.1 | N6: =D6-H6 -> 408 | O6: =C6*E6-F6 -> 0.18
A7: 4 | B7: Amber Enterp. | C7: 6688.55 | D7: 2702 | E7: 3.53 | F7: 23611 | G7: 25825 | H7: 466 | I7: 12625 | J7: 123.6 | K7: 33.7 | L7: 0.6 | M7: 864.8 | N7: =D7-H7 -> 2236 | O7: =C7*E7-F7 -> -0.4185
A8: 5 | B8: Crompton Gr. Con | C8: 216.55 | D8: 192 | E8: 64.39 | F8: 13944 | G8: 13965 | H8: 170 | I8: 7397 | J8: -228.1 | K8: 33.7 | L8: 0.1 | M8: 746.1 | N8: =D8-H8 -> 22 | O8: =C8*E8-F8 -> -0.3455
A10: Levered beta vs Nifty (SLOPE of weekly returns) | B10: =SLOPE(H14:H116,$I$14:$I$116) -> 0.93220703 | C10: =SLOPE(I14:I116,$I$14:$I$116) -> 1 | D10: =SLOPE(J14:J116,$I$14:$I$116) -> 0.74025079 | E10: =SLOPE(K14:K116,$I$14:$I$116) -> 1.1809716 | F10: =SLOPE(L14:L116,$I$14:$I$116) -> 1.6316239 | G10: =SLOPE(M14:M116,$I$14:$I$116) -> 1.1373903 | H10: Published (WACC sheet): LG 0.74 | Voltas 0.93 | Blue Star 1.18 | Amber 1.63 | Crompton 1.14
A11: No. of weekly return observations | B11: =COUNT(H14:H116) -> 103 | C11: =COUNT(I14:I116) -> 103 | D11: =COUNT(J14:J116) -> 51 | E11: =COUNT(K14:K116) -> 103 | F11: =COUNT(L14:L116) -> 103 | G11: =COUNT(M14:M116) -> 103 | H11: LG listed Oct-2025, so fewer observations; Nifty beta = 1.000 by construction
A12: WEEKLY PRICE HISTORY (Rs; Nifty in index points) AND WEEKLY RETURNS - base for regression beta
A13: Date | B13: Voltas | C13: Nifty | D13: LG | E13: Blue Star | F13: Amber | G13: Crompton | H13: Voltas ret | I13: Nifty ret | J13: LG ret | K13: Blue Star ret | L13: Amber ret | M13: Crompton ret
A14: 46306 | B14: 1029.1 | C14: 23146.15 | D14: 1720 | E14: 1567.6 | F14: 6668 | G14: 215.5 | H14: =B14/B15-1 -> -0.0044500339 | I14: =C14/C15-1 -> 0.027783637 | J14: =D14/D15-1 -> -0.021058623 | K14: =E14/E15-1 -> -0.0040660737 | L14: =F14/F15-1 -> 0.034600465 | M14: =G14/G15-1 -> 0.050655746
A15: 46299 | B15: 1033.7 | C15: 22520.45 | D15: 1757 | E15: 1574 | F15: 6445 | G15: 205.11 | H15: =B15/B16-1 -> -0.018515002 | I15: =C15/C16-1 -> 0.0043930167 | J15: =D15/D16-1 -> 0.020443722 | K15: =E15/E16-1 -> 0.078377638 | L15: =F15/F16-1 -> -0.0084615385 | M15: =G15/G16-1 -> 0.011889492
A16: 46292 | B16: 1053.2 | C16: 22421.95 | D16: 1721.8 | E16: 1459.6 | F16: 6500 | G16: 202.7 | H16: =B16/B17-1 -> -0.058129136 | I16: =C16/C17-1 -> -0.031051619 | J16: =D16/D17-1 -> -0.0020864727 | K16: =E16/E17-1 -> -0.067348243 | L16: =F16/F17-1 -> -0.066091954 | M16: =G16/G17-1 -> -0.07273559
A17: 46285 | B17: 1118.2 | C17: 23140.5 | D17: 1725.4 | E17: 1565 | F17: 6960 | G17: 218.6 | H17: =B17/B18-1 -> 0.0065712485 | I17: =C17/C18-1 -> -0.0088193469 | J17: =D17/D18-1 -> 0.016795333 | K17: =E17/E18-1 -> 0.021673848 | L17: =F17/F18-1 -> -0.023157895 | M17: =G17/G18-1 -> -0.037513209
A18: 46278 | B18: 1110.9 | C18: 23346.4 | D18: 1696.9 | E18: 1531.8 | F18: 7125 | G18: 227.12 | H18: =B18/B19-1 -> -0.046437768 | I18: =C18/C19-1 -> -0.0022095811 | J18: =D18/D19-1 -> 0.036717986 | K18: =E18/E19-1 -> -0.016816431 | L18: =F18/F19-1 -> -0.016563147 | M18: =G18/G19-1 -> -0.016796537
A19: 46271 | B19: 1165 | C19: 23398.1 | D19: 1636.8 | E19: 1558 | F19: 7245 | G19: 231 | H19: =B19/B20-1 -> -0.0042735043 | I19: =C19/C20-1 -> -0.020905778 | J19: =D19/D20-1 -> -0.0023770342 | K19: =E19/E20-1 -> 0.049865229 | L19: =F19/F20-1 -> -0.03063955 | M19: =G19/G20-1 -> -0.0060240964
A20: 46264 | B20: 1170 | C20: 23897.7 | D20: 1640.7 | E20: 1484 | F20: 7474 | G20: 232.4 | H20: =B20/B21-1 -> -0.025 | I20: =C20/C21-1 -> -0.011497106 | J20: =D20/D21-1 -> -0.029975168 | K20: =E20/E21-1 -> 0.0027027027 | L20: =F20/F21-1 -> -0.026188925 | M20: =G20/G21-1 -> -0.0025751073
A21: 46257 | B21: 1200 | C21: 24175.65 | D21: 1691.4 | E21: 1480 | F21: 7675 | G21: 233 | H21: =B21/B22-1 -> -0.028340081 | I21: =C21/C22-1 -> -0.003148194 | J21: =D21/D22-1 -> 0.04195158 | K21: =E21/E22-1 -> -0.021099279 | L21: =F21/F22-1 -> 0.044217687 | M21: =G21/G22-1 -> -0.075396825
A22: 46250 | B22: 1235 | C22: 24252 | D22: 1623.3 | E22: 1511.9 | F22: 7350 | G22: 252 | H22: =B22/B23-1 -> -0.064748201 | I22: =C22/C23-1 -> -0.0046786506 | J22: =D22/D23-1 -> -0.061513557 | K22: =E22/E23-1 -> 0.0025862069 | L22: =F22/F23-1 -> 0.017723622 | M22: =G22/G23-1 -> 0.014901329
A23: 46243 | B23: 1320.5 | C23: 24366 | D23: 1729.7 | E23: 1508 | F23: 7222 | G23: 248.3 | H23: =B23/B24-1 -> 0.027626459 | I23: =C23/C24-1 -> -0.008329043 | J23: =D23/D24-1 -> 0.090261582 | K23: =E23/E24-1 -> -0.0039630119 | L23: =F23/F24-1 -> -0.028648285 | M23: =G23/G24-1 -> -0.0066013203
A24: 46236 | B24: 1285 | C24: 24570.65 | D24: 1586.5 | E24: 1514 | F24: 7435 | G24: 249.95 | H24: =B24/B25-1 -> -0.033034841 | I24: =C24/C25-1 -> 0.0076711396 | J24: =D24/D25-1 -> 0.064407917 | K24: =E24/E25-1 -> -0.099452772 | L24: =F24/F25-1 -> -0.00073919763 | M24: =G24/G25-1 -> -0.039392775
A25: 46229 | B25: 1328.9 | C25: 24383.6 | D25: 1490.5 | E25: 1681.2 | F25: 7440.5 | G25: 260.2 | H25: =B25/B26-1 -> 0.0012054547 | I25: =C25/C26-1 -> 0.02592411 | J25: =D25/D26-1 -> -0.024030906 | K25: =E25/E26-1 -> 0.026875153 | L25: =F25/F26-1 -> 0.024650554 | M25: =G25/G26-1 -> 0.040175894
... A64: 45956 | B64: 1383.6 | C64: 25722.1 | D64: 1663.6 | E64: 1937.4 | F64: 8036.5 | G64: 282.7 | H64: =B64/B65-1 -> -0.040099903 | I64: =C64/C65-1 -> -0.0028319277 | J64: =D64/D65-1 -> 0.0090374234 | K64: =E64/E65-1 -> -0.034197408 | L64: =F64/F65-1 -> -0.034248633 | M64: =G64/G65-1 -> -0.036304755
A65: 45949 | B65: 1441.4 | C65: 25795.15 | D65: 1648.7 | E65: 2006 | F65: 8321.5 | G65: 293.35 | H65: =B65/B66-1 -> 0.010374317 | I65: =C65/C66-1 -> 0.0033177945 | K65: =E65/E66-1 -> 0.017550979 | L65: =F65/F66-1 -> 0.0087278017 | M65: =G65/G66-1 -> 0.020347826
A66: 45942 | B66: 1426.6 | C66: 25709.85 | E66: 1971.4 | F66: 8249.5 | G66: 287.5 | H66: =B66/B67-1 -> 0.0065617724 | I66: =C66/C67-1 -> 0.016788377 | K66: =E66/E67-1 -> 0.011441178 | L66: =F66/F67-1 -> -0.0042247571 | M66: =G66/G67-1 -> -0.00086880973
A67: 45935 | B67: 1417.3 | C67: 25285.35 | E67: 1949.1 | F67: 8284.5 | G67: 287.75 | H67: =B67/B68-1 -> 0.041825934 | I67: =C67/C68-1 -> 0.015710455 | K67: =E67/E68-1 -> 0.026274221 | L67: =F67/F68-1 -> 0.0085215168 | M67: =G67/G68-1 -> -0.025237127
A68: 45928 | B68: 1360.4 | C68: 24894.25 | E68: 1899.2 | F68: 8214.5 | G68: 295.2 | H68: =B68/B69-1 -> 0.015072377 | I68: =C68/C69-1 -> 0.0097162002 | K68: =E68/E69-1 -> 0.0048145601 | L68: =F68/F69-1 -> 0.0063705972 | M68: =G68/G69-1 -> 0.008885851
A69: 45921 | B69: 1340.2 | C69: 24654.7 | E69: 1890.1 | F69: 8162.5 | G69: 292.6 | H69: =B69/B70-1 -> -0.056130713 | I69: =C69/C70-1 -> -0.026546716 | K69: =E69/E70-1 -> -0.03752928 | L69: =F69/F70-1 -> -0.014964098 | M69: =G69/G70-1 -> -0.068004459
A70: 45914 | B70: 1419.9 | C70: 25327.05 | E70: 1963.8 | F70: 8286.5 | G70: 313.95 | H70: =B70/B71-1 -> 0.011612995 | I70: =C70/C71-1 -> 0.0084833161 | K70: =E70/E71-1 -> 0.041858985 | L70: =F70/F71-1 -> 0.044165827 | M70: =G70/G71-1 -> -0.0015900779
A71: 45907 | B71: 1403.6 | C71: 25114 | E71: 1884.9 | F71: 7936 | G71: 314.45 | H71: =B71/B72-1 -> -0.020379676 | I71: =C71/C72-1 -> 0.015076189 | K71: =E71/E72-1 -> -0.030151788 | L71: =F71/F72-1 -> 0.018284468 | M71: =G71/G72-1 -> -0.040140415
A72: 45900 | B72: 1432.8 | C72: 24741 | E72: 1943.5 | F72: 7793.5 | G72: 327.6 | H72: =B72/B73-1 -> 0.04279476 | I72: =C72/C73-1 -> 0.012860848 | K72: =E72/E73-1 -> 0.032842642 | L72: =F72/F73-1 -> 0.072377021 | M72: =G72/G73-1 -> -0.0072727273
A73: 45893 | B73: 1374 | C73: 24426.85 | E73: 1881.7 | F73: 7267.5 | G73: 330 | H73: =B73/B74-1 -> 0.015370973 | I73: =C73/C74-1 -> -0.017822606 | K73: =E73/E74-1 -> -0.019947917 | L73: =F73/F74-1 -> 0.00096412093 | M73: =G73/G74-1 -> 0.041995579
A74: 45886 | B74: 1353.2 | C74: 24870.1 | E74: 1920 | F74: 7260.5 | G74: 316.7 | H74: =B74/B75-1 -> 0.061499843 | I74: =C74/C75-1 -> 0.0096949816 | K74: =E74/E75-1 -> 0.075509747 | L74: =F74/F75-1 -> 0.053009427 | M74: =G74/G75-1 -> -0.0096935585
A75: 45879 | B75: 1274.8 | C75: 24631.3 | E75: 1785.2 | F75: 6895 | G75: 319.8 | H75: =B75/B76-1 -> -0.023066902 | I75: =C75/C76-1 -> 0.011000152 | K75: =E75/E76-1 -> -0.008387491 | L75: =F75/F76-1 -> -0.062478755 | M75: =G75/G76-1 -> 0.00031279324
A76: 45872 | B76: 1304.9 | C76: 24363.3 | E76: 1800.3 | F76: 7354.5 | G76: 319.7 | H76: =B76/B77-1 -> -0.0094883862 | I76: =C76/C77-1 -> -0.0082249998 | K76: =E76/E77-1 -> 0.060872127 | L76: =F76/F77-1 -> -0.065620633 | M76: =G76/G77-1 -> -0.0046699875
A77: 45865 | B77: 1317.4 | C77: 24565.35 | E77: 1697 | F77: 7871 | G77: 321.2 | H77: =B77/B78-1 -> 0.001368197 | I77: =C77/C78-1 -> -0.010937311 | K77: =E77/E78-1 -> -0.028731685 | L77: =F77/F78-1 -> 0.082147522 | M77: =G77/G78-1 -> -0.023559812
... A116: 45592 | B116: 1642.85 | C116: 24304.35 | E116: 1917.1 | F116: 6160.95 | G116: 392.15 | H116: =B116/B117-1 -> -0.063823119 | I116: =C116/C117-1 -> 0.0051094257 | K116: =E116/E117-1 -> 0.036746613 | L116: =F116/F117-1 -> -0.0016609411 | M116: =G116/G117-1 -> 0.00051026917
A117: 45585 | B117: 1754.85 | C117: 24180.8 | E117: 1849.15 | F117: 6171.2 | G117: 391.95

Sheet WACC
A1: VOLTAS LIMITED - CAPITAL STRUCTURE, COST OF CAPITAL & WACC
A3: Weighted Average Cost of Capital - peer beta analysis
A4: Name of Comps | B4: Country | C4: CMP Rs. | D4: No. Eq. Shares Cr. | E4: Total Debt | F4: Total Market Cap | G4: Tax Rate | H4: Debt / Capital | I4: Levered Beta | J4: Unlevered Beta
A5: LG Electronics | B5: India | C5: =Market_Data!C4 -> 1718 | D5: =Market_Data!E4 -> 67.88 | E5: =Market_Data!D4 -> 459 | F5: =Market_Data!F4 -> 116618 | G5: 0.25 | H5: =E5/(E5+F5) -> 0.0039204968 | I5: =Market_Data!D10 -> 0.74025079 | J5: =I5/(1+(1-G5)*E5/F5) -> 0.73807205
A6: Voltas | B6: India | C6: =Market_Data!C5 -> 1032.85 | D6: =Market_Data!E5 -> 33.09 | E6: =Market_Data!D5 -> 992 | F6: =Market_Data!F5 -> 34177 | G6: 0.25 | H6: =E6/(E6+F6) -> 0.028206659 | I6: =Market_Data!B10 -> 0.93220703 | J6: =I6/(1+(1-G6)*E6/F6) -> 0.91234614
A7: Blue Star | B7: India | C7: =Market_Data!C6 -> 1571.75 | D7: =Market_Data!E6 -> 20.56 | E7: =Market_Data!D6 -> 810 | F7: =Market_Data!F6 -> 32315 | G7: 0.25 | H7: =E7/(E7+F7) -> 0.02445283 | I7: =Market_Data!E10 -> 1.1809716 | J7: =I7/(1+(1-G7)*E7/F7) -> 1.1591798
A8: Amber Enterp. | B8: India | C8: =Market_Data!C7 -> 6688.55 | D8: =Market_Data!E7 -> 3.53 | E8: =Market_Data!D7 -> 2702 | F8: =Market_Data!F7 -> 23611 | G8: 0.25 | H8: =E8/(E8+F8) -> 0.10268688 | I8: =Market_Data!F10 -> 1.6316239 | J8: =I8/(1+(1-G8)*E8/F8) -> 1.5026532
A9: Crompton Gr. Con | B9: India | C9: =Market_Data!C8 -> 216.55 | D9: =Market_Data!E8 -> 64.39 | E9: =Market_Data!D8 -> 192 | F9: =Market_Data!F8 -> 13944 | G9: 0.25 | H9: =E9/(E9+F9) -> 0.013582343 | I9: =Market_Data!G10 -> 1.1373903 | J9: =I9/(1+(1-G9)*E9/F9) -> 1.1257645
G10: Average | H10: =AVERAGE(H5:H9) -> 0.034569843 | I10: =AVERAGE(I5:I9) -> 1.1244887 | J10: =AVERAGE(J5:J9) -> 1.0876032
G11: Median | H11: =MEDIAN(H5:H9) -> 0.02445283 | I11: =MEDIAN(I5:I9) -> 1.1373903 | J11: =MEDIAN(J5:J9) -> 1.1257645
A13: Cost of Debt
A14: Risk-Free Rate | B14: 0.074
A15: Credit Spread | B15: 0.006
A16: Pre-Tax Cost of Debt (published page displays 7.9%; 7.4% + 0.6% = 8.0%) | B16: =B14+B15 -> 0.08
A17: Tax Rate | B17: 0.25
A18: After Tax Cost of Debt | B18: =B16*(1-B17) -> 0.06
A20: Capital Structure
B21: Current (Rs Cr) | C21: Current % | D21: Target %
A22: Total Debt | B22: =E6 -> 992 | C22: =B22/B24 -> 0.028206659 | D22: 0.02
A23: Market Cap | B23: =F6 -> 34177 | C23: =B23/B24 -> 0.97179334 | D23: =1-D22 -> 0.98
A24: Total Capitalization | B24: =B22+B23 -> 35169 | C24: =C22+C23 -> 1 | D24: =D22+D23 -> 1
A25: Debt / Market cap | B25: =B22/B23 -> 0.029025368 | D25: 0.02
A27: Levered Beta (re-levered at target capital structure)
A28: Comps Median Unlevered Beta | B28: =J11 -> 1.1257645
A29: Target Debt / Market cap | B29: =D25 -> 0.02
A30: Tax Rate | B30: =B17 -> 0.25
A31: Levered Beta | B31: =B28*(1+(1-B30)*B29) -> 1.142651
A33: Cost of Equity
A34: Risk-Free Rate | B34: =B14 -> 0.074
A35: Equity Risk Premium | B35: 0.056
A36: Levered Beta | B36: =B31 -> 1.142651
A37: Cost of Equity | B37: =B34+B36*B35 -> 0.13798846
A39: Weighted Average Cost of Capital (explicit forecast period)
A40: Cost of Equity | B40: =B37 -> 0.13798846
A41: Weight of Equity | B41: =D23 -> 0.98
A42: Cost of Debt (after tax) | B42: =B18 -> 0.06
A43: Weight of Debt | B43: =D22 -> 0.02
A44: WACC | B44: =B40*B41+B42*B43 -> 0.13642869
A46: WACC Calculation for Terminal Value (published uses a separate set of inputs - see Error_Log E-03)
A47: Risk-Free Rate | B47: =B14 -> 0.074
A48: Equity Risk Premium | B48: =B35 -> 0.056
A49: Levered Beta (hard-coded 1.00 in report) | B49: 1
A50: Cost of Equity | B50: =B47+B49*B48 -> 0.13
A51: Weight of Equity | B51: =D23 -> 0.98
A52: Cost of Debt (after tax) | B52: =B18 -> 0.06
A53: Weight of Debt | B53: =D22 -> 0.02
A54: WACC (terminal value) | B54: =B50*B51+B52*B53 -> 0.1286
A56: Published values: WACC (explicit) 13.7% | WACC (terminal) 12.9% | Cost of equity 13.8% | After-tax Kd 6.0% | Levered beta 1.14

Sheet DCF
A1: VOLTAS LIMITED - DCF VALUATION (FCFF APPROACH)
A2: INR Crore unless stated. Section A replicates the published DCF; Section B isolates the effect of the errors found; Section C is a corrected sensitivity.
A4: A. DCF AS PUBLISHED (with the published FCFF)
A5: Particulars | C5: FY27E | D5: FY28E | E5: FY29E | F5: FY30E | G5: FY31E | H5: (published header shows FY26E-FY30E - label error, see E-02)
A6: Free Cash Flow to Firm (FCFF) - as published | C6: =Cash_Flow!G43 -> 400.02539 | D6: =Cash_Flow!H43 -> 240.44886 | E6: =Cash_Flow!I43 -> 676.31386 | F6: =Cash_Flow!J43 -> 290.60032 | G6: =Cash_Flow!K43 -> 963.19101
A7: Discount Period (Mid-Year Convention) | C7: 0.5 | D7: =C7+1 -> 1.5 | E7: =D7+1 -> 2.5 | F7: =E7+1 -> 3.5 | G7: =F7+1 -> 4.5
A8: Discount Factor = 1/(1+WACC)^period | C8: =1/(1+$B$14)^C7 -> 0.9380563 | D8: =1/(1+$B$14)^D7 -> 0.82544229 | E8: =1/(1+$B$14)^E7 -> 0.72634764 | F8: =1/(1+$B$14)^F7 -> 0.63914933 | G8: =1/(1+$B$14)^G7 -> 0.56241922
A9: Present Value of FCFF (as published) | C9: =C6*C8 -> 375.24634 | D9: =D6*D8 -> 198.47666 | E9: =E6*E8 -> 491.23898 | F9: =F6*F8 -> 185.737 | G9: =G6*G8 -> 541.71713
A10: FCFF - corrected (capex incl. ROU additions) | C10: =Cash_Flow!G49 -> 380.15692 | D10: =Cash_Flow!H49 -> 217.63233 | E10: =Cash_Flow!I49 -> 650.59555 | F10: =Cash_Flow!J49 -> 262.04044 | G10: =Cash_Flow!K49 -> 931.40999
A11: Present Value of FCFF (corrected) | C11: =C10*C8 -> 356.6086 | D11: =D10*D8 -> 179.64293 | E11: =E10*E8 -> 472.55854 | F11: =F10*F8 -> 167.48298 | G11: =G10*G8 -> 523.84288
A13: Discount rates
A14: WACC - explicit forecast period | B14: =WACC!B44 -> 0.13642869
A15: WACC - terminal value (separate calculation in report) | B15: =WACC!B54 -> 0.1286
A16: Terminal growth rate (g) (published links g to the risk-free rate - see E-14) | B16: =WACC!B14 -> 0.074
A18: TERMINAL VALUE - Gordon Growth Method (published)
A19: Terminal Year FCFF x (1+g) | B19: =G6*(1+B16) -> 1034.4671
A20: Terminal Value = TY FCFF(1+g) / (WACC - g) | B20: =B19/(B15-B16) -> 18946.285
A21: PV of Terminal Value (discounted at FY31E mid-year factor, as published) | B21: =B20*G8 -> 10655.755
A23: ENTERPRISE VALUE TO INTRINSIC VALUE PER SHARE (Base: Gordon Growth) - as published
A24: Sum of PV of Explicit FCFF (FY27E-FY31E) | B24: =SUM(C9:G9) -> 1792.4161
A25: Add: PV of Terminal Value | B25: =B21 -> 10655.755
A26: Enterprise Value (EV) | B26: =B24+B25 -> 12448.171
A27: Less: Net Debt (total debt per Debt_Schedule less cash, 31-Mar-26) | B27: =Debt_Schedule!F23-Balance_Sheet!F39 -> 201
A28: Equity Value | B28: =B26-B27 -> 12247.171
A29: Diluted Shares Outstanding (Cr) | B29: =Assumptions!$C$9 -> 33.08
A30: INTRINSIC VALUE PER SHARE (Rs) | B30: =B28/B29 -> 370.22886
A31: Current Market Price (Rs) | B31: =Assumptions!$C$8 -> 1033
A32: Upside / (Downside) % | B32: =B30/B31-1 -> -0.64159839
A35: B. EFFECT OF CORRECTIONS ON DCF VALUE (reviewer analysis)
A36: Step | B36: As published | C36: Fix 1: capex sign (E-01) | D36: Fix 1 + Fix 2: one WACC (E-03)
A37: FCFF series used | B37: Published | C37: Corrected | D37: Corrected
A38: WACC used for terminal value | B38: =$B$15 -> 0.1286 | C38: =$B$15 -> 0.1286 | D38: =$B$14 -> 0.13642869
A39: Sum of PV of explicit FCFF | B39: =SUM(C9:G9) -> 1792.4161 | C39: =SUM(C11:G11) -> 1700.1359 | D39: =SUM(C11:G11) -> 1700.1359
A40: Terminal-year FCFF | B40: =G6*(1+$B$16) -> 1034.4671 | C40: =G10*(1+$B$16) -> 1000.3343 | D40: =G10*(1+$B$16) -> 1000.3343
A41: Terminal value | B41: =B40/(B38-$B$16) -> 18946.285 | C41: =C40/(C38-$B$16) -> 18321.142 | D41: =D40/(D38-$B$16) -> 16023.632
A42: PV of terminal value | B42: =B41*$G$8 -> 10655.755 | C42: =C41*$G$8 -> 10304.162 | D42: =D41*$G$8 -> 9011.9987
A43: Enterprise value | B43: =B39+B42 -> 12448.171 | C43: =C39+C42 -> 12004.298 | D43: =D39+D42 -> 10712.135
A44: Less: net debt | B44: =$B$27 -> 201 | C44: =$B$27 -> 201 | D44: =$B$27 -> 201
A45: Equity value | B45: =B43-B44 -> 12247.171 | C45: =C43-C44 -> 11803.298 | D45: =D43-D44 -> 10511.135
A46: Value per share (Rs) | B46: =B45/$B$29 -> 370.22886 | C46: =C45/$B$29 -> 356.8107 | D46: =D45/$B$29 -> 317.74893
A47: Upside / (downside) vs CMP | B47: =B46/$B$31-1 -> -0.64159839 | C47: =C46/$B$31-1 -> -0.6545879 | D47: =D46/$B$31-1 -> -0.69240181
A48: Terminal value as % of EV | B48: =B42/B43 -> 0.85600968 | C48: =C42/C43 -> 0.85837273 | D48: =D42/D43 -> 0.84128878
A49: Change in value per share vs published (Rs) | B49: =B46-$B$46 -> 0 | C49: =C46-$B$46 -> -13.418157 | D49: =D46-$B$46 -> -52.47993
A50: Memo: non-operating investments excluded from DCF equity bridge (non-current + current investments, 31-Mar-26, book value) | B50: =Balance_Sheet!F30+Balance_Sheet!F37 -> 2584
A51: Memo: value per share if these investments were added (Rs) - not applied above (see E-15) | B51: =D46+B50/B29 -> 395.86259
A54: C. SENSITIVITY - corrected FCFF, single WACC for explicit and terminal periods: value per share (Rs)
A55: WACC (down) / terminal growth g (across) | B55: =$B$16+(-0.02) -> 0.054 | C55: =$B$16+(-0.01) -> 0.064 | D55: =$B$16+(0) -> 0.074 | E55: =$B$16+(0.01) -> 0.084 | F55: =$B$16+(0.02) -> 0.094
A56: =$B$14+(-0.02) -> 0.11642869 | B56: =(SUMPRODUCT($C$10:$G$10/(1+$A56)^$C$7:$G$7)+$G$10*(1+B$55)/($A56-B$55)/(1+$A56)^$G$7-$B$27)/$B$29 -> 337.44729 | C56: =(SUMPRODUCT($C$10:$G$10/(1+$A56)^$C$7:$G$7)+$G$10*(1+C$55)/($A56-C$55)/(1+$A56)^$G$7-$B$27)/$B$29 -> 395.95508 | D56: =(SUMPRODUCT($C$10:$G$10/(1+$A56)^$C$7:$G$7)+$G$10*(1+D$55)/($A56-D$55)/(1+$A56)^$G$7-$B$27)/$B$29 -> 482.04224 | E56: =(SUMPRODUCT($C$10:$G$10/(1+$A56)^$C$7:$G$7)+$G$10*(1+E$55)/($A56-E$55)/(1+$A56)^$G$7-$B$27)/$B$29 -> 621.2226 | F56: =(SUMPRODUCT($C$10:$G$10/(1+$A56)^$C$7:$G$7)+$G$10*(1+F$55)/($A56-F$55)/(1+$A56)^$G$7-$B$27)/$B$29 -> 884.51219
A57: =$B$14+(-0.01) -> 0.12642869 | B57: =(SUMPRODUCT($C$10:$G$10/(1+$A57)^$C$7:$G$7)+$G$10*(1+B$55)/($A57-B$55)/(1+$A57)^$G$7-$B$27)/$B$29 -> 286.3537 | C57: =(SUMPRODUCT($C$10:$G$10/(1+$A57)^$C$7:$G$7)+$G$10*(1+C$55)/($A57-C$55)/(1+$A57)^$G$7-$B$27)/$B$29 -> 327.40412 | D57: =(SUMPRODUCT($C$10:$G$10/(1+$A57)^$C$7:$G$7)+$G$10*(1+D$55)/($A57-D$55)/(1+$A57)^$G$7-$B$27)/$B$29 -> 384.11407 | E57: =(SUMPRODUCT($C$10:$G$10/(1+$A57)^$C$7:$G$7)+$G$10*(1+E$55)/($A57-E$55)/(1+$A57)^$G$7-$B$27)/$B$29 -> 467.5559 | F57: =(SUMPRODUCT($C$10:$G$10/(1+$A57)^$C$7:$G$7)+$G$10*(1+F$55)/($A57-F$55)/(1+$A57)^$G$7-$B$27)/$B$29 -> 602.45948
A58: =$B$14+(0) -> 0.13642869 | B58: =(SUMPRODUCT($C$10:$G$10/(1+$A58)^$C$7:$G$7)+$G$10*(1+B$55)/($A58-B$55)/(1+$A58)^$G$7-$B$27)/$B$29 -> 247.80579 | C58: =(SUMPRODUCT($C$10:$G$10/(1+$A58)^$C$7:$G$7)+$G$10*(1+C$55)/($A58-C$55)/(1+$A58)^$G$7-$B$27)/$B$29 -> 277.94894 | D58: =(SUMPRODUCT($C$10:$G$10/(1+$A58)^$C$7:$G$7)+$G$10*(1+D$55)/($A58-D$55)/(1+$A58)^$G$7-$B$27)/$B$29 -> 317.74893 | E58: =(SUMPRODUCT($C$10:$G$10/(1+$A58)^$C$7:$G$7)+$G$10*(1+E$55)/($A58-E$55)/(1+$A58)^$G$7-$B$27)/$B$29 -> 372.73144 | F58: =(SUMPRODUCT($C$10:$G$10/(1+$A58)^$C$7:$G$7)+$G$10*(1+F$55)/($A58-F$55)/(1+$A58)^$G$7-$B$27)/$B$29 -> 453.63155
A59: =$B$14+(0.01) -> 0.14642869 | B59: =(SUMPRODUCT($C$10:$G$10/(1+$A59)^$C$7:$G$7)+$G$10*(1+B$55)/($A59-B$55)/(1+$A59)^$G$7-$B$27)/$B$29 -> 217.72506 | C59: =(SUMPRODUCT($C$10:$G$10/(1+$A59)^$C$7:$G$7)+$G$10*(1+C$55)/($A59-C$55)/(1+$A59)^$G$7-$B$27)/$B$29 -> 240.63244 | D59: =(SUMPRODUCT($C$10:$G$10/(1+$A59)^$C$7:$G$7)+$G$10*(1+D$55)/($A59-D$55)/(1+$A59)^$G$7-$B$27)/$B$29 -> 269.86533 | E59: =(SUMPRODUCT($C$10:$G$10/(1+$A59)^$C$7:$G$7)+$G$10*(1+E$55)/($A59-E$55)/(1+$A59)^$G$7-$B$27)/$B$29 -> 308.46343 | F59: =(SUMPRODUCT($C$10:$G$10/(1+$A59)^$C$7:$G$7)+$G$10*(1+F$55)/($A59-F$55)/(1+$A59)^$G$7-$B$27)/$B$29 -> 361.78557
A60: =$B$14+(0.02) -> 0.15642869 | B60: =(SUMPRODUCT($C$10:$G$10/(1+$A60)^$C$7:$G$7)+$G$10*(1+B$55)/($A60-B$55)/(1+$A60)^$G$7-$B$27)/$B$29 -> 193.62606 | C60: =(SUMPRODUCT($C$10:$G$10/(1+$A60)^$C$7:$G$7)+$G$10*(1+C$55)/($A60-C$55)/(1+$A60)^$G$7-$B$27)/$B$29 -> 211.50867 | D60: =(SUMPRODUCT($C$10:$G$10/(1+$A60)^$C$7:$G$7)+$G$10*(1+D$55)/($A60-D$55)/(1+$A60)^$G$7-$B$27)/$B$29 -> 233.73022 | E60: =(SUMPRODUCT($C$10:$G$10/(1+$A60)^$C$7:$G$7)+$G$10*(1+E$55)/($A60-E$55)/(1+$A60)^$G$7-$B$27)/$B$29 -> 262.08788 | F60: =(SUMPRODUCT($C$10:$G$10/(1+$A60)^$C$7:$G$7)+$G$10*(1+F$55)/($A60-F$55)/(1+$A60)^$G$7-$B$27)/$B$29 -> 299.53035
A62: Centre cell equals Section B, column D (check): | B62: =ROUND(D58-D46,4) -> 0

Sheet Relative_Valuation
A1: VOLTAS LIMITED - COMPARABLE COMPANY VALUATION (Figures in Rs Crore)
A2: Source: Screener.in (as shown in report). Blue = inputs from report.
A4: Company | B4: Share Price | C4: Shares Outstanding | D4: Equity Value | E4: Net Debt | F4: Enterprise Value | G4: Revenue | H4: EBITDA | I4: Net Income | J4: EV/Revenue | K4: EV/EBITDA | L4: P/E
A5: LG Electronics | B5: 1718 | C5: 67.88 | D5: 116618 | E5: -4017 | F5: =D5+E5 -> 112601 | G5: 24605 | H5: 2412.9 | I5: 1685 | J5: =F5/G5 -> 4.5763463 | K5: =F5/H5 -> 46.666252 | L5: =D5/I5 -> 69.209496
A6: Voltas | B6: 1032.85 | C6: 33.09 | D6: 34177 | E6: 212 | F6: =D6+E6 -> 34389 | G6: 14245 | H6: 516.3 | I6: 370 | J6: =F6/G6 -> 2.4141102 | K6: =F6/H6 -> 66.606624 | L6: =D6/I6 -> 92.37027
A7: Blue Star | B7: 1571.75 | C7: 20.56 | D7: 32315 | E7: 408 | F7: =D7+E7 -> 32723 | G7: 12402 | H7: 933.1 | I7: 527 | J7: =F7/G7 -> 2.638526 | K7: =F7/H7 -> 35.069124 | L7: =D7/I7 -> 61.318786
A8: Amber Enterp. | B8: 6668 | C8: 3.53 | D8: 23538 | E8: 2236 | F8: =D8+E8 -> 25774 | G8: 12186 | H8: 864.8 | I8: 226 | J8: =F8/G8 -> 2.1150501 | K8: =F8/H8 -> 29.803423 | L8: =D8/I8 -> 104.15044
A9: Crompton Gr. Con | B9: 216.55 | C9: 64.39 | D9: 13944 | E9: 21 | F9: =D9+E9 -> 13965 | G9: 7193 | H9: 746.1 | I9: 516 | J9: =F9/G9 -> 1.9414709 | K9: =F9/H9 -> 18.71733 | L9: =D9/I9 -> 27.023256
A11: High | J11: =MAX(J5:J9) -> 4.5763463 | K11: =MAX(K5:K9) -> 66.606624 | L11: =MAX(L5:L9) -> 104.15044
A12: 75th Percentile | J12: =QUARTILE(J5:J9,3) -> 2.638526 | K12: =QUARTILE(K5:K9,3) -> 46.666252 | L12: =QUARTILE(L5:L9,3) -> 92.37027
A13: Average | J13: =AVERAGE(J5:J9) -> 2.7371007 | K13: =AVERAGE(K5:K9) -> 39.372551 | L13: =AVERAGE(L5:L9) -> 70.81445
A14: Median | J14: =MEDIAN(J5:J9) -> 2.4141102 | K14: =MEDIAN(K5:K9) -> 35.069124 | L14: =MEDIAN(L5:L9) -> 69.209496
A15: 25th Percentile | J15: =QUARTILE(J5:J9,1) -> 2.1150501 | K15: =QUARTILE(K5:K9,1) -> 29.803423 | L15: =QUARTILE(L5:L9,1) -> 61.318786
A16: Low | J16: =MIN(J5:J9) -> 1.9414709 | K16: =MIN(K5:K9) -> 18.71733 | L16: =MIN(L5:L9) -> 27.023256
A18: Voltas Implied Valuation (Peer Multiples) - as published (peer statistics INCLUDE Voltas itself - see E-06)
J19: EV/Revenue | K19: EV/EBITDA | L19: P/E
A20: Implied Enterprise Value | J20: =J14*G6 -> 34389 | K20: =K14*H6 -> 18106.189 | L20: =L22+L21 -> 25819.513
A21: Net Debt | J21: =$E$6 -> 212 | K21: =$E$6 -> 212 | L21: =$E$6 -> 212
A22: Implied Market Value | J22: =J20-J21 -> 34177 | K22: =K20-K21 -> 17894.189 | L22: =L14*I6 -> 25607.513
A23: Shares Outstanding | J23: =Assumptions!$C$9 -> 33.08 | K23: =Assumptions!$C$9 -> 33.08 | L23: =Assumptions!$C$9 -> 33.08
A24: Implied Value per Share (Rs) | J24: =J22/J23 -> 1033.162 | K24: =K22/K23 -> 540.93679 | L24: =L22/L23 -> 774.10863
A25: Weight | J25: 0.2 | K25: 0.6 | L25: 0.2
A26: Implied Target Price (Rs) - as published | L26: =SUMPRODUCT(J24:L24,J25:L25) -> 686.0162
A27: Check: weights total 100% (must be zero) | L27: =ROUND(SUM(J25:L25)-1,6) -> 0
A29: CORRECTED: peer statistics EXCLUDING Voltas (the company being valued)
A30: Peer (ex-Voltas) | J30: EV/Revenue | K30: EV/EBITDA | L30: P/E
A31: =A5 -> LG Electronics | J31: =J5 -> 4.5763463 | K31: =K5 -> 46.666252 | L31: =L5 -> 69.209496
A32: =A7 -> Blue Star | J32: =J7 -> 2.638526 | K32: =K7 -> 35.069124 | L32: =L7 -> 61.318786
A33: =A8 -> Amber Enterp. | J33: =J8 -> 2.1150501 | K33: =K8 -> 29.803423 | L33: =L8 -> 104.15044
A34: =A9 -> Crompton Gr. Con | J34: =J9 -> 1.9414709 | K34: =K9 -> 18.71733 | L34: =L9 -> 27.023256
A35: Median (ex-Voltas) | J35: =MEDIAN(J31:J34) -> 2.3767881 | K35: =MEDIAN(K31:K34) -> 32.436274 | L35: =MEDIAN(L31:L34) -> 65.264141
A36: Average (ex-Voltas) | J36: =AVERAGE(J31:J34) -> 2.8178483 | K36: =AVERAGE(K31:K34) -> 32.564032 | L36: =AVERAGE(L31:L34) -> 65.425495
A37: Implied Enterprise Value | J37: =J35*G6 -> 33857.346 | K37: =K35*H6 -> 16746.848 | L37: =L38+L39 -> 24359.732
A38: Implied Market Value | J38: =J37-J39 -> 33645.346 | K38: =K37-K39 -> 16534.848 | L38: =L35*I6 -> 24147.732
A39: Net Debt | J39: =$E$6 -> 212 | K39: =$E$6 -> 212 | L39: =$E$6 -> 212
A40: Implied Value per Share (Rs) | J40: =J38/J23 -> 1017.0903 | K40: =K38/K23 -> 499.84426 | L40: =L38/L23 -> 729.97981
A41: Implied Target Price (Rs) - corrected (same 20/60/20 weights) | L41: =SUMPRODUCT(J40:L40,J25:L25) -> 649.32057
A43: Note: Voltas EBITDA 516.3 (Screener) = model FY26 EBITDA 647 less share of JV loss 131; peer inputs on this page differ from the Market_Data / WACC sheets (e.g. Amber price 6,668 vs 6,688.55; Net income, Sales) - see E-16.

Sheet Peer_Multiples
A1: Peer multiples - how to choose each segment's multiple
A3: UCP (room AC, commercial AC & refrigeration)
A4: Company | B4: Price (Rs) | C4: EPS FY27E (Rs) | D4: EPS FY28E (Rs) | E4: P/E FY27E | F4: P/E FY28E | G4: Source / date
A5: Blue Star | B5: 1568 | C5: 28.12 | D5: 38.59 | E5: =B5/C5 -> 55.761024 | F5: =B5/D5 -> 40.632288 | G5: Price 7-Aug-26 from Motilal Oswal Report
A6: LG Electronics India | B6: 1718 | C6: 36.6 | D6: 40.8 | E6: =B6/C6 -> 46.939891 | F6: =B6/D6 -> 42.107843 | G6: Price 14-Aug-26; MOFSL
A7: Havells India | B7: 1121 | C7: 27.4 | D7: 30.6 | E7: =B7/C7 -> 40.912409 | F7: =B7/D7 -> 36.633987 | G7: LPK Securities Ltd 21 Jul 26
A8: Peer median | E8: =MEDIAN(E5:E7) -> 46.939891 | F8: =MEDIAN(F5:F7) -> 40.632288
A9: Voltas (reference only - excluded from median) | B9: 1033 | C9: 22.2 | D9: 27.8 | E9: =B9/C9 -> 46.531532 | F9: =B9/D9 -> 37.158273
A10: Voltas premium / (discount) to peer median (FY28E) | F10: =F9/F8-1 -> -0.085498871
A12: ADJUSTMENTS TO THE PEER MEDIAN
A13: Timing: valuing FY29E profit at Sep-28, growth will have slowed | B13: 0
A14: Earnings volatility: UCP margin fell from 8.4% to 3.2% in FY26 | B14: -0.05
A15: Market leadership: largest RAC share, widest lead over No. 2 | B15: 0.05
A16: Net adjustment | B16: =SUM(B13:B15) -> 0
A17: Suggested UCP multiple (P/E FY28E median x (1 + net adjustment)) | B17: =F8*(1+B16) -> 40.632288
A19: EMPS (electro-mechanical projects) - EPC peers
A20: Company | B20: Price (Rs) | C20: EPS FY27E (Rs) | D20: EPS FY28E (Rs) | E20: P/E FY27E | F20: P/E FY28E | G20: Source / date
A21: Kalpataru Projects (target multiple) | B21: 1364 | C21: 69.6 | D21: 81 | E21: =B21/C21 -> 19.597701 | F21: =B21/D21 -> 16.839506 | G21: Price 11-Aug-26 from Motilal Oswal Report
A22: KEC International (target multiple) | B22: 352.25 | C22: 23.9 | D22: 32.9 | E22: =B22/C22 -> 14.738494 | F22: =B22/D22 -> 10.706687 | G22: Price 11-Aug-26 from Motilal Oswal Report
A23: Blue Star (shown for reference; excluded from median as in report) | B23: 1568 | C23: 28.12 | D23: 38.59 | E23: =B23/C23 -> 55.761024 | F23: =B23/D23 -> 40.632288 | G23: Price 7-Aug-26 from Motilal Oswal Report
A24: Peer median (Kalpataru & KEC) | E24: =MEDIAN(E21:E22) -> 17.168097 | F24: =MEDIAN(F21:F22) -> 13.773097
A25: Suggested EMPS multiple | B25: =F24 -> 13.773097
A27: EP&S (mining, construction & textile machinery) - equipment peers
A28: Company | B28: Multiple (x) | G28: Source / date
A29: Elecon Engineering (Axis Direct) | B29: 28.7 | G29: Target P/E on FY28E EPS Axis Direct 22-Jul 26
A30: Peer median | B30: =MEDIAN(B29:B29) -> 28.7
A31: Suggested EP&S multiple | B31: =B30 -> 28.7

Sheet SoTP
A1: Voltas Ltd - Sum-of-the-Parts (SoTP) Valuation
A3: A. KEY INPUTS
A4: Current share price (Rs) | B4: =Assumptions!$C$8 -> 1033
A5: Shares outstanding (crore) | B5: =Assumptions!$C$9 -> 33.08
A6: Tax rate (note: forecast model uses 30%; SoTP uses 25% - see E-17) | B6: 0.25
A7: Years from today to valuation date | B7: 1.9
A8: Model FY29E EBIT (Rs cr) - for tie-out check | B8: =Income_Statement!I17 -> 1420.0069
A10: B. SEGMENT VALUATION (FY29E)
A11: Segment | B11: FY29E revenue | C11: EBIT margin | D11: Revenue share | E11: EBIT after allocation | F11: Tax | G11: Profit after tax | H11: Multiple (Peer Median) | I11: Value (Rs cr)
A12: UCP (room AC, commercial AC & refrigeration) | B12: =Revenue_Build!I9 -> 15966.72 | C12: 0.07 | D12: =B12/$B$16 -> 0.74499692 | E12: =B12*C12 -> 1117.6704 | F12: =E12*$B$6 -> 279.4176 | G12: =E12-F12 -> 838.2528 | H12: =Peer_Multiples!B17 -> 40.632288 | I12: =G12*H12 -> 34060.129
A13: EMPS (electro-mechanical projects) | B13: =Revenue_Build!I14 -> 4681.7696 | C13: 0.065 | D13: =B13/$B$16 -> 0.21844837 | E13: =B13*C13 -> 304.31502 | F13: =E13*$B$6 -> 76.078755 | G13: =E13-F13 -> 228.23627 | H13: =Peer_Multiples!B25 -> 13.773097 | I13: =G13*H13 -> 3143.5201
A14: EP&S (mining, construction, textile machinery) | B14: =Revenue_Build!I20 -> 691.43807 | C14: 0.25 | D14: =B14/$B$16 -> 0.032262057 | E14: =B14*C14 -> 172.85952 | F14: =E14*$B$6 -> 43.214879 | G14: =E14-F14 -> 129.64464 | H14: =Peer_Multiples!B31 -> 28.7 | I14: =G14*H14 -> 3720.8011
A15: Other Unallocated | B15: =Revenue_Build!I22 -> 92 | D15: =B15/$B$16 -> 0.004292661
A16: Total | B16: =SUM(B12:B15) -> 21431.928 | C16: =E16/B16 -> 0.074414442 | D16: =SUM(D12:D15) -> 1 | E16: =SUM(E12:E14) -> 1594.8449 | F16: =SUM(F12:F14) -> 398.71124 | G16: =SUM(G12:G14) -> 1196.1337 | H16: =I16/G16 -> 34.213943 | I16: =SUM(I12:I14) -> 40924.451
A17: Tie-out: SoTP segment EBIT less model FY29E EBIT (should be ~0 - see E-18) | E17: =E16-B8 -> 174.83809 | F17: =E16/B8-1 -> 0.12312482
A19: C. EQUITY VALUE BRIDGE
B20: As published | C20: Corrected (discounted) | D20: Note
A21: Operating value at valuation date (Rs cr) | B21: =I16 -> 40924.451 | C21: =I16 -> 40924.451
A22: Discount factor (published 1.000 despite 1.9 years; corrected = 1/(1+cost of equity)^years) | B22: 1 | C22: =1/(1+WACC!B37)^B7 -> 0.78223649
A23: Present value of operating value | B23: =B21*B22 -> 40924.451 | C23: =C21*C22 -> 32012.599
A24: Add: cash and bank balances | B24: =Balance_Sheet!F39 -> 781 | C24: =B24 -> 781 | D24: Mar-26 balance sheet (Hist_BS).
A25: Less: borrowings incl. leases | B25: 992 | C25: =B25 -> 992 | D25: Report note: term loan 423 + working-capital debt 544 + leases ~15 = 982 (not 992) - see E-19
A26: Add: Voltbek JV stake at book value | B26: 130 | C26: =B26 -> 130 | D26: FY26 annual report investment note (Rs 129.93 cr).
A27: Net non-operating items | B27: =B24-B25+B26 -> -81 | C27: =C24-C25+C26 -> -81
A28: Equity value (Rs cr) | B28: =B23+B27 -> 40843.451 | C28: =C23+C27 -> 31931.599
A29: Value per share (Rs) | B29: =B28/$B$5 -> 1234.6871 | C29: =C28/$B$5 -> 965.28412
A30: Current price (Rs) | B30: =$B$4 -> 1033 | C30: =$B$4 -> 1033
A31: Upside / (downside) | B31: =B29/B30-1 -> 0.19524409 | C31: =C29/C30-1 -> -0.065552644
A33: D. SCENARIOS (Low / Base / High)
A34: Item | B34: Low | C34: Base | D34: High
A35: UCP EBIT margin | B35: 0.06 | C35: =C12 -> 0.07 | D35: 0.08
A36: EMPS EBIT margin | B36: 0.055 | C36: =C13 -> 0.065 | D36: 0.07
A37: EP&S EBIT margin | B37: 0.22 | C37: =C14 -> 0.25 | D37: 0.27
A38: UCP multiple (x) | B38: 33 | C38: =H12 -> 40.632288 | D38: 42
A39: EMPS multiple (x) | B39: 10 | C39: =H13 -> 13.773097 | D39: 15
A40: EP&S multiple (x) | B40: 22 | C40: =H14 -> 28.7 | D40: 31
A41: UCP profit after tax | B41: =$B$12*B35*(1-$B$6) -> 718.5024 | C41: =$B$12*C35*(1-$B$6) -> 838.2528 | D41: =$B$12*D35*(1-$B$6) -> 958.0032
A42: EMPS profit after tax | B42: =$B$13*B36*(1-$B$6) -> 193.12299 | C42: =$B$13*C36*(1-$B$6) -> 228.23627 | D42: =$B$13*D36*(1-$B$6) -> 245.7929
A43: EP&S profit after tax | B43: =$B$14*B37*(1-$B$6) -> 114.08728 | C43: =$B$14*C37*(1-$B$6) -> 129.64464 | D43: =$B$14*D37*(1-$B$6) -> 140.01621
A44: Operating value (Rs cr) | B44: =B41*B38+B42*B39+B43*B40 -> 28151.729 | C44: =C41*C38+C42*C39+C43*C40 -> 40924.451 | D44: =D41*D38+D42*D39+D43*D40 -> 48263.53
A45: Equity value (Rs cr) - as published | B45: =B44*$B$22+$B$27 -> 28070.729 | C45: =C44*$B$22+$B$27 -> 40843.451 | D45: =D44*$B$22+$B$27 -> 48182.53
A46: Value per share (Rs) - as published | B46: =B45/$B$5 -> 848.57102 | C46: =C45/$B$5 -> 1234.6871 | D46: =D45/$B$5 -> 1456.5457
A47: Upside / (downside) - as published | B47: =B46/$B$4-1 -> -0.17853725 | C47: =C46/$B$4-1 -> 0.19524409 | D47: =D46/$B$4-1 -> 0.41001516
A48: Value per share (Rs) - corrected (discounted) | B48: =(B44*$C$22+$C$27)/$B$5 -> 663.25 | C48: =(C44*$C$22+$C$27)/$B$5 -> 965.28412 | D48: =(D44*$C$22+$C$27)/$B$5 -> 1138.8299
A49: Base column links to the inputs in Section B, so it always equals the main result. Check (must be zero): | C49: =ROUND(C46-B29,4) -> 0
A51: E. SENSITIVITY - value per share (Rs): UCP multiple vs UCP EBIT margin (as published, undiscounted)
A52: UCP margin (down) / UCP multiple (across) | B52: 35 | C52: =H12 -> 40.632288 | D52: 45
A53: 0.05 | B53: =(($B$12*$A53*(1-$B$6)*B$52+$I$13+$I$14)*$B$22+$B$27)/$B$5 -> 838.56231 | C53: =(($B$12*$A53*(1-$B$6)*C$52+$I$13+$I$14)*$B$22+$B$27)/$B$5 -> 940.50741 | D53: =(($B$12*$A53*(1-$B$6)*D$52+$I$13+$I$14)*$B$22+$B$27)/$B$5 -> 1019.5635
A54: 0.06 | B54: =(($B$12*$A54*(1-$B$6)*B$52+$I$13+$I$14)*$B$22+$B$27)/$B$5 -> 965.26316 | C54: =(($B$12*$A54*(1-$B$6)*C$52+$I$13+$I$14)*$B$22+$B$27)/$B$5 -> 1087.5973 | D54: =(($B$12*$A54*(1-$B$6)*D$52+$I$13+$I$14)*$B$22+$B$27)/$B$5 -> 1182.4646
A55: 0.07 | B55: =(($B$12*$A55*(1-$B$6)*B$52+$I$13+$I$14)*$B$22+$B$27)/$B$5 -> 1091.964 | C55: =(($B$12*$A55*(1-$B$6)*C$52+$I$13+$I$14)*$B$22+$B$27)/$B$5 -> 1234.6871 | D55: =(($B$12*$A55*(1-$B$6)*D$52+$I$13+$I$14)*$B$22+$B$27)/$B$5 -> 1345.3657
A56: 0.08 | B56: =(($B$12*$A56*(1-$B$6)*B$52+$I$13+$I$14)*$B$22+$B$27)/$B$5 -> 1218.6649 | C56: =(($B$12*$A56*(1-$B$6)*C$52+$I$13+$I$14)*$B$22+$B$27)/$B$5 -> 1381.777 | D56: =(($B$12*$A56*(1-$B$6)*D$52+$I$13+$I$14)*$B$22+$B$27)/$B$5 -> 1508.2668
A57: 0.09 | B57: =(($B$12*$A57*(1-$B$6)*B$52+$I$13+$I$14)*$B$22+$B$27)/$B$5 -> 1345.3657 | C57: =(($B$12*$A57*(1-$B$6)*C$52+$I$13+$I$14)*$B$22+$B$27)/$B$5 -> 1528.8669 | D57: =(($B$12*$A57*(1-$B$6)*D$52+$I$13+$I$14)*$B$22+$B$27)/$B$5 -> 1671.1679
A58: Centre cell equals base value per share (check, must be zero): | C58: =ROUND(C55-B29,4) -> 0
